Workbook

Sheet RESUMEN
A1: 📊 DASHBOARD FINANCIERO v4.0
A3: MÉTRICAS PRINCIPALES
A5: Total Ingresos: | B5: =SUMIF(TRANSACCIONES!B:B,"INGRESO",TRANSACCIONES!I:I)
A6: Total Egresos: | B6: =SUMIF(TRANSACCIONES!B:B,"EGRESO",TRANSACCIONES!I:I)
A7: Balance: | B7: =B5-B6
A9: Total por Pagar: | B9: =CxP!B3
A10: Total por Cobrar: | B10: =CxC!B3
A12: Transacciones Totales: | B12: =COUNTA(TRANSACCIONES!A:A)-1
A14: ESTADO DEL SISTEMA
A16: Versión: | B16: 4.0
A17: Última actualización: | B17: =NOW()

Sheet TRANSACCIONES
A1: Fecha | B1: Tipo | C1: Categoría | D1: Subcategoría | E1: Descripción | F1: Entidad | G1: Cuenta | H1: Método Pago | I1: Monto | J1: Referencia | K1: Notas | L1: Estado | M1: IVA | N1: Fecha Vencimiento | O1: Número Factura | P1: Personal/Negocio
A2: 45962 | B2: EGRESO | C2: Operaciones | D2: Nómina | E2: Pago de salario - Noviembre 2025 | F2: Juan Pérez | G2: BAC Corriente | H2: Transferencia | I2: 500000 | J2: TRF-2025-001 | K2: Pago quincenal | L2: PAGADO | M2: 0 | P2: Negocio
A3: 45966 | B3: EGRESO | C3: Operaciones | D3: Proveedores | E3: Compra de materiales | F3: Proveedor XYZ | G3: BAC Corriente | H3: Transferencia | I3: 150000 | J3: FAC-001 | K3: Materiales proyecto A | L3: PENDIENTE | M3: 19500 | N3: 45981 | O3: FAC-2025-001 | P3: Negocio
A4: 45971 | B4: INGRESO | C4: Ventas | D4: Servicios | E4: Pago cliente por servicio | F4: Cliente ABC | G4: BAC Corriente | H4: SINPE | I4: 300000 | J4: SINPE-001 | K4: Servicio de consultoría | L4: POR COBRAR | M4: 39000 | N4: 45986 | O4: INV-2025-001 | P4: Negocio

Sheet CxP
A1: 💰 CUENTAS POR PAGAR
A3: Total Pendiente: | B3: =SUM(D6:D55)
A5: Fecha | B5: Descripción | C5: Entidad | D5: Monto | E5: Fecha Vencimiento | F5: Días Pendientes | G5: Estado | H5: Notas
A6: =IFERROR(INDEX(TRANSACCIONES!$A$2:$A$1000,SMALL(IF(UPPER(TRANSACCIONES!$L$2:$L$1000)="PENDIENTE",ROW(TRANSACCIONES!$L$2:$L$1000)-ROW(TRANSACCIONES!$L$2)+1),1)),"") | B6: =IFERROR(INDEX(TRANSACCIONES!$E$2:$E$1000,SMALL(IF(UPPER(TRANSACCIONES!$L$2:$L$1000)="PENDIENTE",ROW(TRANSACCIONES!$L$2:$L$1000)-ROW(TRANSACCIONES!$L$2)+1),1)),"") | C6: =IFERROR(INDEX(TRANSACCIONES!$F$2:$F$1000,SMALL(IF(UPPER(TRANSACCIONES!$L$2:$L$1000)="PENDIENTE",ROW(TRANSACCIONES!$L$2:$L$1000)-ROW(TRANSACCIONES!$L$2)+1),1)),"") | D6: =IFERROR(INDEX(TRANSACCIONES!$I$2:$I$1000,SMALL(IF(UPPER(TRANSACCIONES!$L$2:$L$1000)="PENDIENTE",ROW(TRANSACCIONES!$L$2:$L$1000)-ROW(TRANSACCIONES!$L$2)+1),1)),"") | E6: =IFERROR(INDEX(TRANSACCIONES!$N$2:$N$1000,SMALL(IF(UPPER(TRANSACCIONES!$L$2:$L$1000)="PENDIENTE",ROW(TRANSACCIONES!$L$2:$L$1000)-ROW(TRANSACCIONES!$L$2)+1),1)),"") | F6: =IF(A6="","",TODAY()-A6) | G6: =IF(A6="","",IF(E6<TODAY(),"VENCIDO",IF(E6<=TODAY()+7,"POR VENCER","AL DÍA"))) | H6: =IFERROR(INDEX(TRANSACCIONES!$K$2:$K$1000,SMALL(IF(UPPER(TRANSACCIONES!$L$2:$L$1000)="PENDIENTE",ROW(TRANSACCIONES!$L$2:$L$1000)-ROW(TRANSACCIONES!$L$2)+1),1)),"")
A7: =IFERROR(INDEX(TRANSACCIONES!$A$2:$A$1000,SMALL(IF(UPPER(TRANSACCIONES!$L$2:$L$1000)="PENDIENTE",ROW(TRANSACCIONES!$L$2:$L$1000)-ROW(TRANSACCIONES!$L$2)+1),2)),"") | B7: =IFERROR(INDEX(TRANSACCIONES!$E$2:$E$1000,SMALL(IF(UPPER(TRANSACCIONES!$L$2:$L$1000)="PENDIENTE",ROW(TRANSACCIONES!$L$2:$L$1000)-ROW(TRANSACCIONES!$L$2)+1),2)),"") | C7: =IFERROR(INDEX(TRANSACCIONES!$F$2:$F$1000,SMALL(IF(UPPER(TRANSACCIONES!$L$2:$L$1000)="PENDIENTE",ROW(TRANSACCIONES!$L$2:$L$1000)-ROW(TRANSACCIONES!$L$2)+1),2)),"") | D7: =IFERROR(INDEX(TRANSACCIONES!$I$2:$I$1000,SMALL(IF(UPPER(TRANSACCIONES!$L$2:$L$1000)="PENDIENTE",ROW(TRANSACCIONES!$L$2:$L$1000)-ROW(TRANSACCIONES!$L$2)+1),2)),"") | E7: =IFERROR(INDEX(TRANSACCIONES!$N$2:$N$1000,SMALL(IF(UPPER(TRANSACCIONES!$L$2:$L$1000)="PENDIENTE",ROW(TRANSACCIONES!$L$2:$L$1000)-ROW(TRANSACCIONES!$L$2)+1),2)),"") | F7: =IF(A7="","",TODAY()-A7) | G7: =IF(A7="","",IF(E7<TODAY(),"VENCIDO",IF(E7<=TODAY()+7,"POR VENCER","AL DÍA"))) | H7: =IFERROR(INDEX(TRANSACCIONES!$K$2:$K$1000,SMALL(IF(UPPER(TRANSACCIONES!$L$2:$L$1000)="PENDIENTE",ROW(TRANSACCIONES!$L$2:$L$1000)-ROW(TRANSACCIONES!$L$2)+1),2)),"")
A8: =IFERROR(INDEX(TRANSACCIONES!$A$2:$A$1000,SMALL(IF(UPPER(TRANSACCIONES!$L$2:$L$1000)="PENDIENTE",ROW(TRANSACCIONES!$L$2:$L$1000)-ROW(TRANSACCIONES!$L$2)+1),3)),"") | B8: =IFERROR(INDEX(TRANSACCIONES!$E$2:$E$1000,SMALL(IF(UPPER(TRANSACCIONES!$L$2:$L$1000)="PENDIENTE",ROW(TRANSACCIONES!$L$2:$L$1000)-ROW(TRANSACCIONES!$L$2)+1),3)),"") | C8: =IFERROR(INDEX(TRANSACCIONES!$F$2:$F$1000,SMALL(IF(UPPER(TRANSACCIONES!$L$2:$L$1000)="PENDIENTE",ROW(TRANSACCIONES!$L$2:$L$1000)-ROW(TRANSACCIONES!$L$2)+1),3)),"") | D8: =IFERROR(INDEX(TRANSACCIONES!$I$2:$I$1000,SMALL(IF(UPPER(TRANSACCIONES!$L$2:$L$1000)="PENDIENTE",ROW(TRANSACCIONES!$L$2:$L$1000)-ROW(TRANSACCIONES!$L$2)+1),3)),"") | E8: =IFERROR(INDEX(TRANSACCIONES!$N$2:$N$1000,SMALL(IF(UPPER(TRANSACCIONES!$L$2:$L$1000)="PENDIENTE",ROW(TRANSACCIONES!$L$2:$L$1000)-ROW(TRANSACCIONES!$L$2)+1),3)),"") | F8: =IF(A8="","",TODAY()-A8) | G8: =IF(A8="","",IF(E8<TODAY(),"VENCIDO",IF(E8<=TODAY()+7,"POR VENCER","AL DÍA"))) | H8: =IFERROR(INDEX(TRANSACCIONES!$K$2:$K$1000,SMALL(IF(UPPER(TRANSACCIONES!$L$2:$L$1000)="PENDIENTE",ROW(TRANSACCIONES!$L$2:$L$1000)-ROW(TRANSACCIONES!$L$2)+1),3)),"")
A9: =IFERROR(INDEX(TRANSACCIONES!$A$2:$A$1000,SMALL(IF(UPPER(TRANSACCIONES!$L$2:$L$1000)="PENDIENTE",ROW(TRANSACCIONES!$L$2:$L$1000)-ROW(TRANSACCIONES!$L$2)+1),4)),"") | B9: =IFERROR(INDEX(TRANSACCIONES!$E$2:$E$1000,SMALL(IF(UPPER(TRANSACCIONES!$L$2:$L$1000)="PENDIENTE",ROW(TRANSACCIONES!$L$2:$L$1000)-ROW(TRANSACCIONES!$L$2)+1),4)),"") | C9: =IFERROR(INDEX(TRANSACCIONES!$F$2:$F$1000,SMALL(IF(UPPER(TRANSACCIONES!$L$2:$L$1000)="PENDIENTE",ROW(TRANSACCIONES!$L$2:$L$1000)-ROW(TRANSACCIONES!$L$2)+1),4)),"") | D9: =IFERROR(INDEX(TRANSACCIONES!$I$2:$I$1000,SMALL(IF(UPPER(TRANSACCIONES!$L$2:$L$1000)="PENDIENTE",ROW(TRANSACCIONES!$L$2:$L$1000)-ROW(TRANSACCIONES!$L$2)+1),4)),"") | E9: =IFERROR(INDEX(TRANSACCIONES!$N$2:$N$1000,SMALL(IF(UPPER(TRANSACCIONES!$L$2:$L$1000)="PENDIENTE",ROW(TRANSACCIONES!$L$2:$L$1000)-ROW(TRANSACCIONES!$L$2)+1),4)),"") | F9: =IF(A9="","",TODAY()-A9) | G9: =IF(A9="","",IF(E9<TODAY(),"VENCIDO",IF(E9<=TODAY()+7,"POR VENCER","AL DÍA"))) | H9: =IFERROR(INDEX(TRANSACCIONES!$K$2:$K$1000,SMALL(IF(UPPER(TRANSACCIONES!$L$2:$L$1000)="PENDIENTE",ROW(TRANSACCIONES!$L$2:$L$1000)-ROW(TRANSACCIONES!$L$2)+1),4)),"")
A10: =IFERROR(INDEX(TRANSACCIONES!$A$2:$A$1000,SMALL(IF(UPPER(TRANSACCIONES!$L$2:$L$1000)="PENDIENTE",ROW(TRANSACCIONES!$L$2:$L$1000)-ROW(TRANSACCIONES!$L$2)+1),5)),"") | B10: =IFERROR(INDEX(TRANSACCIONES!$E$2:$E$1000,SMALL(IF(UPPER(TRANSACCIONES!$L$2:$L$1000)="PENDIENTE",ROW(TRANSACCIONES!$L$2:$L$1000)-ROW(TRANSACCIONES!$L$2)+1),5)),"") | C10: =IFERROR(INDEX(TRANSACCIONES!$F$2:$F$1000,SMALL(IF(UPPER(TRANSACCIONES!$L$2:$L$1000)="PENDIENTE",ROW(TRANSACCIONES!$L$2:$L$1000)-ROW(TRANSACCIONES!$L$2)+1),5)),"") | D10: =IFERROR(INDEX(TRANSACCIONES!$I$2:$I$1000,SMALL(IF(UPPER(TRANSACCIONES!$L$2:$L$1000)="PENDIENTE",ROW(TRANSACCIONES!$L$2:$L$1000)-ROW(TRANSACCIONES!$L$2)+1),5)),"") | E10: =IFERROR(INDEX(TRANSACCIONES!$N$2:$N$1000,SMALL(IF(UPPER(TRANSACCIONES!$L$2:$L$1000)="PENDIENTE",ROW(TRANSACCIONES!$L$2:$L$1000)-ROW(TRANSACCIONES!$L$2)+1),5)),"") | F10: =IF(A10="","",TODAY()-A10) | G10: =IF(A10="","",IF(E10<TODAY(),"VENCIDO",IF(E10<=TODAY()+7,"POR VENCER","AL DÍA"))) | H10: =IFERROR(INDEX(TRANSACCIONES!$K$2:$K$1000,SMALL(IF(UPPER(TRANSACCIONES!$L$2:$L$1000)="PENDIENTE",ROW(TRANSACCIONES!$L$2:$L$1000)-ROW(TRANSACCIONES!$L$2)+1),5)),"")
A11: =IFERROR(INDEX(TRANSACCIONES!$A$2:$A$1000,SMALL(IF(UPPER(TRANSACCIONES!$L$2:$L$1000)="PENDIENTE",ROW(TRANSACCIONES!$L$2:$L$1000)-ROW(TRANSACCIONES!$L$2)+1),6)),"") | B11: =IFERROR(INDEX(TRANSACCIONES!$E$2:$E$1000,SMALL(IF(UPPER(TRANSACCIONES!$L$2:$L$1000)="PENDIENTE",ROW(TRANSACCIONES!$L$2:$L$1000)-ROW(TRANSACCIONES!$L$2)+1),6)),"") | C11: =IFERROR(INDEX(TRANSACCIONES!$F$2:$F$1000,SMALL(IF(UPPER(TRANSACCIONES!$L$2:$L$1000)="PENDIENTE",ROW(TRANSACCIONES!$L$2:$L$1000)-ROW(TRANSACCIONES!$L$2)+1),6)),"") | D11: =IFERROR(INDEX(TRANSACCIONES!$I$2:$I$1000,SMALL(IF(UPPER(TRANSACCIONES!$L$2:$L$1000)="PENDIENTE",ROW(TRANSACCIONES!$L$2:$L$1000)-ROW(TRANSACCIONES!$L$2)+1),6)),"") | E11: =IFERROR(INDEX(TRANSACCIONES!$N$2:$N$1000,SMALL(IF(UPPER(TRANSACCIONES!$L$2:$L$1000)="PENDIENTE",ROW(TRANSACCIONES!$L$2:$L$1000)-ROW(TRANSACCIONES!$L$2)+1),6)),"") | F11: =IF(A11="","",TODAY()-A11) | G11: =IF(A11="","",IF(E11<TODAY(),"VENCIDO",IF(E11<=TODAY()+7,"POR VENCER","AL DÍA"))) | H11: =IFERROR(INDEX(TRANSACCIONES!$K$2:$K$1000,SMALL(IF(UPPER(TRANSACCIONES!$L$2:$L$1000)="PENDIENTE",ROW(TRANSACCIONES!$L$2:$L$1000)-ROW(TRANSACCIONES!$L$2)+1),6)),"")
A12: =IFERROR(INDEX(TRANSACCIONES!$A$2:$A$1000,SMALL(IF(UPPER(TRANSACCIONES!$L$2:$L$1000)="PENDIENTE",ROW(TRANSACCIONES!$L$2:$L$1000)-ROW(TRANSACCIONES!$L$2)+1),7)),"") | B12: =IFERROR(INDEX(TRANSACCIONES!$E$2:$E$1000,SMALL(IF(UPPER(TRANSACCIONES!$L$2:$L$1000)="PENDIENTE",ROW(TRANSACCIONES!$L$2:$L$1000)-ROW(TRANSACCIONES!$L$2)+1),7)),"") | C12: =IFERROR(INDEX(TRANSACCIONES!$F$2:$F$1000,SMALL(IF(UPPER(TRANSACCIONES!$L$2:$L$1000)="PENDIENTE",ROW(TRANSACCIONES!$L$2:$L$1000)-ROW(TRANSACCIONES!$L$2)+1),7)),"") | D12: =IFERROR(INDEX(TRANSACCIONES!$I$2:$I$1000,SMALL(IF(UPPER(TRANSACCIONES!$L$2:$L$1000)="PENDIENTE",ROW(TRANSACCIONES!$L$2:$L$1000)-ROW(TRANSACCIONES!$L$2)+1),7)),"") | E12: =IFERROR(INDEX(TRANSACCIONES!$N$2:$N$1000,SMALL(IF(UPPER(TRANSACCIONES!$L$2:$L$1000)="PENDIENTE",ROW(TRANSACCIONES!$L$2:$L$1000)-ROW(TRANSACCIONES!$L$2)+1),7)),"") | F12: =IF(A12="","",TODAY()-A12) | G12: =IF(A12="","",IF(E12<TODAY(),"VENCIDO",IF(E12<=TODAY()+7,"POR VENCER","AL DÍA"))) | H12: =IFERROR(INDEX(TRANSACCIONES!$K$2:$K$1000,SMALL(IF(UPPER(TRANSACCIONES!$L$2:$L$1000)="PENDIENTE",ROW(TRANSACCIONES!$L$2:$L$1000)-ROW(TRANSACCIONES!$L$2)+1),7)),"")
A13: =IFERROR(INDEX(TRANSACCIONES!$A$2:$A$1000,SMALL(IF(UPPER(TRANSACCIONES!$L$2:$L$1000)="PENDIENTE",ROW(TRANSACCIONES!$L$2:$L$1000)-ROW(TRANSACCIONES!$L$2)+1),8)),"") | B13: =IFERROR(INDEX(TRANSACCIONES!$E$2:$E$1000,SMALL(IF(UPPER(TRANSACCIONES!$L$2:$L$1000)="PENDIENTE",ROW(TRANSACCIONES!$L$2:$L$1000)-ROW(TRANSACCIONES!$L$2)+1),8)),"") | C13: =IFERROR(INDEX(TRANSACCIONES!$F$2:$F$1000,SMALL(IF(UPPER(TRANSACCIONES!$L$2:$L$1000)="PENDIENTE",ROW(TRANSACCIONES!$L$2:$L$1000)-ROW(TRANSACCIONES!$L$2)+1),8)),"") | D13: =IFERROR(INDEX(TRANSACCIONES!$I$2:$I$1000,SMALL(IF(UPPER(TRANSACCIONES!$L$2:$L$1000)="PENDIENTE",ROW(TRANSACCIONES!$L$2:$L$1000)-ROW(TRANSACCIONES!$L$2)+1),8)),"") | E13: =IFERROR(INDEX(TRANSACCIONES!$N$2:$N$1000,SMALL(IF(UPPER(TRANSACCIONES!$L$2:$L$1000)="PENDIENTE",ROW(TRANSACCIONES!$L$2:$L$1000)-ROW(TRANSACCIONES!$L$2)+1),8)),"") | F13: =IF(A13="","",TODAY()-A13) | G13: =IF(A13="","",IF(E13<TODAY(),"VENCIDO",IF(E13<=TODAY()+7,"POR VENCER","AL DÍA"))) | H13: =IFERROR(INDEX(TRANSACCIONES!$K$2:$K$1000,SMALL(IF(UPPER(TRANSACCIONES!$L$2:$L$1000)="PENDIENTE",ROW(TRANSACCIONES!$L$2:$L$1000)-ROW(TRANSACCIONES!$L$2)+1),8)),"")
A14: =IFERROR(INDEX(TRANSACCIONES!$A$2:$A$1000,SMALL(IF(UPPER(TRANSACCIONES!$L$2:$L$1000)="PENDIENTE",ROW(TRANSACCIONES!$L$2:$L$1000)-ROW(TRANSACCIONES!$L$2)+1),9)),"") | B14: =IFERROR(INDEX(TRANSACCIONES!$E$2:$E$1000,SMALL(IF(UPPER(TRANSACCIONES!$L$2:$L$1000)="PENDIENTE",ROW(TRANSACCIONES!$L$2:$L$1000)-ROW(TRANSACCIONES!$L$2)+1),9)),"") | C14: =IFERROR(INDEX(TRANSACCIONES!$F$2:$F$1000,SMALL(IF(UPPER(TRANSACCIONES!$L$2:$L$1000)="PENDIENTE",ROW(TRANSACCIONES!$L$2:$L$1000)-ROW(TRANSACCIONES!$L$2)+1),9)),"") | D14: =IFERROR(INDEX(TRANSACCIONES!$I$2:$I$1000,SMALL(IF(UPPER(TRANSACCIONES!$L$2:$L$1000)="PENDIENTE",ROW(TRANSACCIONES!$L$2:$L$1000)-ROW(TRANSACCIONES!$L$2)+1),9)),"") | E14: =IFERROR(INDEX(TRANSACCIONES!$N$2:$N$1000,SMALL(IF(UPPER(TRANSACCIONES!$L$2:$L$1000)="PENDIENTE",ROW(TRANSACCIONES!$L$2:$L$1000)-ROW(TRANSACCIONES!$L$2)+1),9)),"") | F14: =IF(A14="","",TODAY()-A14) | G14: =IF(A14="","",IF(E14<TODAY(),"VENCIDO",IF(E14<=TODAY()+7,"POR VENCER","AL DÍA"))) | H14: =IFERROR(INDEX(TRANSACCIONES!$K$2:$K$1000,SMALL(IF(UPPER(TRANSACCIONES!$L$2:$L$1000)="PENDIENTE",ROW(TRANSACCIONES!$L$2:$L$1000)-ROW(TRANSACCIONES!$L$2)+1),9)),"")
A15: =IFERROR(INDEX(TRANSACCIONES!$A$2:$A$1000,SMALL(IF(UPPER(TRANSACCIONES!$L$2:$L$1000)="PENDIENTE",ROW(TRANSACCIONES!$L$2:$L$1000)-ROW(TRANSACCIONES!$L$2)+1),10)),"") | B15: =IFERROR(INDEX(TRANSACCIONES!$E$2:$E$1000,SMALL(IF(UPPER(TRANSACCIONES!$L$2:$L$1000)="PENDIENTE",ROW(TRANSACCIONES!$L$2:$L$1000)-ROW(TRANSACCIONES!$L$2)+1),10)),"") | C15: =IFERROR(INDEX(TRANSACCIONES!$F$2:$F$1000,SMALL(IF(UPPER(TRANSACCIONES!$L$2:$L$1000)="PENDIENTE",ROW(TRANSACCIONES!$L$2:$L$1000)-ROW(TRANSACCIONES!$L$2)+1),10)),"") | D15: =IFERROR(INDEX(TRANSACCIONES!$I$2:$I$1000,SMALL(IF(UPPER(TRANSACCIONES!$L$2:$L$1000)="PENDIENTE",ROW(TRANSACCIONES!$L$2:$L$1000)-ROW(TRANSACCIONES!$L$2)+1),10)),"") | E15: =IFERROR(INDEX(TRANSACCIONES!$N$2:$N$1000,SMALL(IF(UPPER(TRANSACCIONES!$L$2:$L$1000)="PENDIENTE",ROW(TRANSACCIONES!$L$2:$L$1000)-ROW(TRANSACCIONES!$L$2)+1),10)),"") | F15: =IF(A15="","",TODAY()-A15) | G15: =IF(A15="","",IF(E15<TODAY(),"VENCIDO",IF(E15<=TODAY()+7,"POR VENCER","AL DÍA"))) | H15: =IFERROR(INDEX(TRANSACCIONES!$K$2:$K$1000,SMALL(IF(UPPER(TRANSACCIONES!$L$2:$L$1000)="PENDIENTE",ROW(TRANSACCIONES!$L$2:$L$1000)-ROW(TRANSACCIONES!$L$2)+1),10)),"")
A16: =IFERROR(INDEX(TRANSACCIONES!$A$2:$A$1000,SMALL(IF(UPPER(TRANSACCIONES!$L$2:$L$1000)="PENDIENTE",ROW(TRANSACCIONES!$L$2:$L$1000)-ROW(TRANSACCIONES!$L$2)+1),11)),"") | B16: =IFERROR(INDEX(TRANSACCIONES!$E$2:$E$1000,SMALL(IF(UPPER(TRANSACCIONES!$L$2:$L$1000)="PENDIENTE",ROW(TRANSACCIONES!$L$2:$L$1000)-ROW(TRANSACCIONES!$L$2)+1),11)),"") | C16: =IFERROR(INDEX(TRANSACCIONES!$F$2:$F$1000,SMALL(IF(UPPER(TRANSACCIONES!$L$2:$L$1000)="PENDIENTE",ROW(TRANSACCIONES!$L$2:$L$1000)-ROW(TRANSACCIONES!$L$2)+1),11)),"") | D16: =IFERROR(INDEX(TRANSACCIONES!$I$2:$I$1000,SMALL(IF(UPPER(TRANSACCIONES!$L$2:$L$1000)="PENDIENTE",ROW(TRANSACCIONES!$L$2:$L$1000)-ROW(TRANSACCIONES!$L$2)+1),11)),"") | E16: =IFERROR(INDEX(TRANSACCIONES!$N$2:$N$1000,SMALL(IF(UPPER(TRANSACCIONES!$L$2:$L$1000)="PENDIENTE",ROW(TRANSACCIONES!$L$2:$L$1000)-ROW(TRANSACCIONES!$L$2)+1),11)),"") | F16: =IF(A16="","",TODAY()-A16) | G16: =IF(A16="","",IF(E16<TODAY(),"VENCIDO",IF(E16<=TODAY()+7,"POR VENCER","AL DÍA"))) | H16: =IFERROR(INDEX(TRANSACCIONES!$K$2:$K$1000,SMALL(IF(UPPER(TRANSACCIONES!$L$2:$L$1000)="PENDIENTE",ROW(TRANSACCIONES!$L$2:$L$1000)-ROW(TRANSACCIONES!$L$2)+1),11)),"")
A17: =IFERROR(INDEX(TRANSACCIONES!$A$2:$A$1000,SMALL(IF(UPPER(TRANSACCIONES!$L$2:$L$1000)="PENDIENTE",ROW(TRANSACCIONES!$L$2:$L$1000)-ROW(TRANSACCIONES!$L$2)+1),12)),"") | B17: =IFERROR(INDEX(TRANSACCIONES!$E$2:$E$1000,SMALL(IF(UPPER(TRANSACCIONES!$L$2:$L$1000)="PENDIENTE",ROW(TRANSACCIONES!$L$2:$L$1000)-ROW(TRANSACCIONES!$L$2)+1),12)),"") | C17: =IFERROR(INDEX(TRANSACCIONES!$F$2:$F$1000,SMALL(IF(UPPER(TRANSACCIONES!$L$2:$L$1000)="PENDIENTE",ROW(TRANSACCIONES!$L$2:$L$1000)-ROW(TRANSACCIONES!$L$2)+1),12)),"") | D17: =IFERROR(INDEX(TRANSACCIONES!$I$2:$I$1000,SMALL(IF(UPPER(TRANSACCIONES!$L$2:$L$1000)="PENDIENTE",ROW(TRANSACCIONES!$L$2:$L$1000)-ROW(TRANSACCIONES!$L$2)+1),12)),"") | E17: =IFERROR(INDEX(TRANSACCIONES!$N$2:$N$1000,SMALL(IF(UPPER(TRANSACCIONES!$L$2:$L$1000)="PENDIENTE",ROW(TRANSACCIONES!$L$2:$L$1000)-ROW(TRANSACCIONES!$L$2)+1),12)),"") | F17: =IF(A17="","",TODAY()-A17) | G17: =IF(A17="","",IF(E17<TODAY(),"VENCIDO",IF(E17<=TODAY()+7,"POR VENCER","AL DÍA"))) | H17: =IFERROR(INDEX(TRANSACCIONES!$K$2:$K$1000,SMALL(IF(UPPER(TRANSACCIONES!$L$2:$L$1000)="PENDIENTE",ROW(TRANSACCIONES!$L$2:$L$1000)-ROW(TRANSACCIONES!$L$2)+1),12)),"")
A18: =IFERROR(INDEX(TRANSACCIONES!$A$2:$A$1000,SMALL(IF(UPPER(TRANSACCIONES!$L$2:$L$1000)="PENDIENTE",ROW(TRANSACCIONES!$L$2:$L$1000)-ROW(TRANSACCIONES!$L$2)+1),13)),"") | B18: =IFERROR(INDEX(TRANSACCIONES!$E$2:$E$1000,SMALL(IF(UPPER(TRANSACCIONES!$L$2:$L$1000)="PENDIENTE",ROW(TRANSACCIONES!$L$2:$L$1000)-ROW(TRANSACCIONES!$L$2)+1),13)),"") | C18: =IFERROR(INDEX(TRANSACCIONES!$F$2:$F$1000,SMALL(IF(UPPER(TRANSACCIONES!$L$2:$L$1000)="PENDIENTE",ROW(TRANSACCIONES!$L$2:$L$1000)-ROW(TRANSACCIONES!$L$2)+1),13)),"") | D18: =IFERROR(INDEX(TRANSACCIONES!$I$2:$I$1000,SMALL(IF(UPPER(TRANSACCIONES!$L$2:$L$1000)="PENDIENTE",ROW(TRANSACCIONES!$L$2:$L$1000)-ROW(TRANSACCIONES!$L$2)+1),13)),"") | E18: =IFERROR(INDEX(TRANSACCIONES!$N$2:$N$1000,SMALL(IF(UPPER(TRANSACCIONES!$L$2:$L$1000)="PENDIENTE",ROW(TRANSACCIONES!$L$2:$L$1000)-ROW(TRANSACCIONES!$L$2)+1),13)),"") | F18: =IF(A18="","",TODAY()-A18) | G18: =IF(A18="","",IF(E18<TODAY(),"VENCIDO",IF(E18<=TODAY()+7,"POR VENCER","AL DÍA"))) | H18: =IFERROR(INDEX(TRANSACCIONES!$K$2:$K$1000,SMALL(IF(UPPER(TRANSACCIONES!$L$2:$L$1000)="PENDIENTE",ROW(TRANSACCIONES!$L$2:$L$1000)-ROW(TRANSACCIONES!$L$2)+1),13)),"")
A19: =IFERROR(INDEX(TRANSACCIONES!$A$2:$A$1000,SMALL(IF(UPPER(TRANSACCIONES!$L$2:$L$1000)="PENDIENTE",ROW(TRANSACCIONES!$L$2:$L$1000)-ROW(TRANSACCIONES!$L$2)+1),14)),"") | B19: =IFERROR(INDEX(TRANSACCIONES!$E$2:$E$1000,SMALL(IF(UPPER(TRANSACCIONES!$L$2:$L$1000)="PENDIENTE",ROW(TRANSACCIONES!$L$2:$L$1000)-ROW(TRANSACCIONES!$L$2)+1),14)),"") | C19: =IFERROR(INDEX(TRANSACCIONES!$F$2:$F$1000,SMALL(IF(UPPER(TRANSACCIONES!$L$2:$L$1000)="PENDIENTE",ROW(TRANSACCIONES!$L$2:$L$1000)-ROW(TRANSACCIONES!$L$2)+1),14)),"") | D19: =IFERROR(INDEX(TRANSACCIONES!$I$2:$I$1000,SMALL(IF(UPPER(TRANSACCIONES!$L$2:$L$1000)="PENDIENTE",ROW(TRANSACCIONES!$L$2:$L$1000)-ROW(TRANSACCIONES!$L$2)+1),14)),"") | E19: =IFERROR(INDEX(TRANSACCIONES!$N$2:$N$1000,SMALL(IF(UPPER(TRANSACCIONES!$L$2:$L$1000)="PENDIENTE",ROW(TRANSACCIONES!$L$2:$L$1000)-ROW(TRANSACCIONES!$L$2)+1),14)),"") | F19: =IF(A19="","",TODAY()-A19) | G19: =IF(A19="","",IF(E19<TODAY(),"VENCIDO",IF(E19<=TODAY()+7,"POR VENCER","AL DÍA"))) | H19: =IFERROR(INDEX(TRANSACCIONES!$K$2:$K$1000,SMALL(IF(UPPER(TRANSACCIONES!$L$2:$L$1000)="PENDIENTE",ROW(TRANSACCIONES!$L$2:$L$1000)-ROW(TRANSACCIONES!$L$2)+1),14)),"")
A20: =IFERROR(INDEX(TRANSACCIONES!$A$2:$A$1000,SMALL(IF(UPPER(TRANSACCIONES!$L$2:$L$1000)="PENDIENTE",ROW(TRANSACCIONES!$L$2:$L$1000)-ROW(TRANSACCIONES!$L$2)+1),15)),"") | B20: =IFERROR(INDEX(TRANSACCIONES!$E$2:$E$1000,SMALL(IF(UPPER(TRANSACCIONES!$L$2:$L$1000)="PENDIENTE",ROW(TRANSACCIONES!$L$2:$L$1000)-ROW(TRANSACCIONES!$L$2)+1),15)),"") | C20: =IFERROR(INDEX(TRANSACCIONES!$F$2:$F$1000,SMALL(IF(UPPER(TRANSACCIONES!$L$2:$L$1000)="PENDIENTE",ROW(TRANSACCIONES!$L$2:$L$1000)-ROW(TRANSACCIONES!$L$2)+1),15)),"") | D20: =IFERROR(INDEX(TRANSACCIONES!$I$2:$I$1000,SMALL(IF(UPPER(TRANSACCIONES!$L$2:$L$1000)="PENDIENTE",ROW(TRANSACCIONES!$L$2:$L$1000)-ROW(TRANSACCIONES!$L$2)+1),15)),"") | E20: =IFERROR(INDEX(TRANSACCIONES!$N$2:$N$1000,SMALL(IF(UPPER(TRANSACCIONES!$L$2:$L$1000)="PENDIENTE",ROW(TRANSACCIONES!$L$2:$L$1000)-ROW(TRANSACCIONES!$L$2)+1),15)),"") | F20: =IF(A20="","",TODAY()-A20) | G20: =IF(A20="","",IF(E20<TODAY(),"VENCIDO",IF(E20<=TODAY()+7,"POR VENCER","AL DÍA"))) | H20: =IFERROR(INDEX(TRANSACCIONES!$K$2:$K$1000,SMALL(IF(UPPER(TRANSACCIONES!$L$2:$L$1000)="PENDIENTE",ROW(TRANSACCIONES!$L$2:$L$1000)-ROW(TRANSACCIONES!$L$2)+1),15)),"")
A21: =IFERROR(INDEX(TRANSACCIONES!$A$2:$A$1000,SMALL(IF(UPPER(TRANSACCIONES!$L$2:$L$1000)="PENDIENTE",ROW(TRANSACCIONES!$L$2:$L$1000)-ROW(TRANSACCIONES!$L$2)+1),16)),"") | B21: =IFERROR(INDEX(TRANSACCIONES!$E$2:$E$1000,SMALL(IF(UPPER(TRANSACCIONES!$L$2:$L$1000)="PENDIENTE",ROW(TRANSACCIONES!$L$2:$L$1000)-ROW(TRANSACCIONES!$L$2)+1),16)),"") | C21: =IFERROR(INDEX(TRANSACCIONES!$F$2:$F$1000,SMALL(IF(UPPER(TRANSACCIONES!$L$2:$L$1000)="PENDIENTE",ROW(TRANSACCIONES!$L$2:$L$1000)-ROW(TRANSACCIONES!$L$2)+1),16)),"") | D21: =IFERROR(INDEX(TRANSACCIONES!$I$2:$I$1000,SMALL(IF(UPPER(TRANSACCIONES!$L$2:$L$1000)="PENDIENTE",ROW(TRANSACCIONES!$L$2:$L$1000)-ROW(TRANSACCIONES!$L$2)+1),16)),"") | E21: =IFERROR(INDEX(TRANSACCIONES!$N$2:$N$1000,SMALL(IF(UPPER(TRANSACCIONES!$L$2:$L$1000)="PENDIENTE",ROW(TRANSACCIONES!$L$2:$L$1000)-ROW(TRANSACCIONES!$L$2)+1),16)),"") | F21: =IF(A21="","",TODAY()-A21) | G21: =IF(A21="","",IF(E21<TODAY(),"VENCIDO",IF(E21<=TODAY()+7,"POR VENCER","AL DÍA"))) | H21: =IFERROR(INDEX(TRANSACCIONES!$K$2:$K$1000,SMALL(IF(UPPER(TRANSACCIONES!$L$2:$L$1000)="PENDIENTE",ROW(TRANSACCIONES!$L$2:$L$1000)-ROW(TRANSACCIONES!$L$2)+1),16)),"")
A22: =IFERROR(INDEX(TRANSACCIONES!$A$2:$A$1000,SMALL(IF(UPPER(TRANSACCIONES!$L$2:$L$1000)="PENDIENTE",ROW(TRANSACCIONES!$L$2:$L$1000)-ROW(TRANSACCIONES!$L$2)+1),17)),"") | B22: =IFERROR(INDEX(TRANSACCIONES!$E$2:$E$1000,SMALL(IF(UPPER(TRANSACCIONES!$L$2:$L$1000)="PENDIENTE",ROW(TRANSACCIONES!$L$2:$L$1000)-ROW(TRANSACCIONES!$L$2)+1),17)),"") | C22: =IFERROR(INDEX(TRANSACCIONES!$F$2:$F$1000,SMALL(IF(UPPER(TRANSACCIONES!$L$2:$L$1000)="PENDIENTE",ROW(TRANSACCIONES!$L$2:$L$1000)-ROW(TRANSACCIONES!$L$2)+1),17)),"") | D22: =IFERROR(INDEX(TRANSACCIONES!$I$2:$I$1000,SMALL(IF(UPPER(TRANSACCIONES!$L$2:$L$1000)="PENDIENTE",ROW(TRANSACCIONES!$L$2:$L$1000)-ROW(TRANSACCIONES!$L$2)+1),17)),"") | E22: =IFERROR(INDEX(TRANSACCIONES!$N$2:$N$1000,SMALL(IF(UPPER(TRANSACCIONES!$L$2:$L$1000)="PENDIENTE",ROW(TRANSACCIONES!$L$2:$L$1000)-ROW(TRANSACCIONES!$L$2)+1),17)),"") | F22: =IF(A22="","",TODAY()-A22) | G22: =IF(A22="","",IF(E22<TODAY(),"VENCIDO",IF(E22<=TODAY()+7,"POR VENCER","AL DÍA"))) | H22: =IFERROR(INDEX(TRANSACCIONES!$K$2:$K$1000,SMALL(IF(UPPER(TRANSACCIONES!$L$2:$L$1000)="PENDIENTE",ROW(TRANSACCIONES!$L$2:$L$1000)-ROW(TRANSACCIONES!$L$2)+1),17)),"")
A23: =IFERROR(INDEX(TRANSACCIONES!$A$2:$A$1000,SMALL(IF(UPPER(TRANSACCIONES!$L$2:$L$1000)="PENDIENTE",ROW(TRANSACCIONES!$L$2:$L$1000)-ROW(TRANSACCIONES!$L$2)+1),18)),"") | B23: =IFERROR(INDEX(TRANSACCIONES!$E$2:$E$1000,SMALL(IF(UPPER(TRANSACCIONES!$L$2:$L$1000)="PENDIENTE",ROW(TRANSACCIONES!$L$2:$L$1000)-ROW(TRANSACCIONES!$L$2)+1),18)),"") | C23: =IFERROR(INDEX(TRANSACCIONES!$F$2:$F$1000,SMALL(IF(UPPER(TRANSACCIONES!$L$2:$L$1000)="PENDIENTE",ROW(TRANSACCIONES!$L$2:$L$1000)-ROW(TRANSACCIONES!$L$2)+1),18)),"") | D23: =IFERROR(INDEX(TRANSACCIONES!$I$2:$I$1000,SMALL(IF(UPPER(TRANSACCIONES!$L$2:$L$1000)="PENDIENTE",ROW(TRANSACCIONES!$L$2:$L$1000)-ROW(TRANSACCIONES!$L$2)+1),18)),"") | E23: =IFERROR(INDEX(TRANSACCIONES!$N$2:$N$1000,SMALL(IF(UPPER(TRANSACCIONES!$L$2:$L$1000)="PENDIENTE",ROW(TRANSACCIONES!$L$2:$L$1000)-ROW(TRANSACCIONES!$L$2)+1),18)),"") | F23: =IF(A23="","",TODAY()-A23) | G23: =IF(A23="","",IF(E23<TODAY(),"VENCIDO",IF(E23<=TODAY()+7,"POR VENCER","AL DÍA"))) | H23: =IFERROR(INDEX(TRANSACCIONES!$K$2:$K$1000,SMALL(IF(UPPER(TRANSACCIONES!$L$2:$L$1000)="PENDIENTE",ROW(TRANSACCIONES!$L$2:$L$1000)-ROW(TRANSACCIONES!$L$2)+1),18)),"")
A24: =IFERROR(INDEX(TRANSACCIONES!$A$2:$A$1000,SMALL(IF(UPPER(TRANSACCIONES!$L$2:$L$1000)="PENDIENTE",ROW(TRANSACCIONES!$L$2:$L$1000)-ROW(TRANSACCIONES!$L$2)+1),19)),"") | B24: =IFERROR(INDEX(TRANSACCIONES!$E$2:$E$1000,SMALL(IF(UPPER(TRANSACCIONES!$L$2:$L$1000)="PENDIENTE",ROW(TRANSACCIONES!$L$2:$L$1000)-ROW(TRANSACCIONES!$L$2)+1),19)),"") | C24: =IFERROR(INDEX(TRANSACCIONES!$F$2:$F$1000,SMALL(IF(UPPER(TRANSACCIONES!$L$2:$L$1000)="PENDIENTE",ROW(TRANSACCIONES!$L$2:$L$1000)-ROW(TRANSACCIONES!$L$2)+1),19)),"") | D24: =IFERROR(INDEX(TRANSACCIONES!$I$2:$I$1000,SMALL(IF(UPPER(TRANSACCIONES!$L$2:$L$1000)="PENDIENTE",ROW(TRANSACCIONES!$L$2:$L$1000)-ROW(TRANSACCIONES!$L$2)+1),19)),"") | E24: =IFERROR(INDEX(TRANSACCIONES!$N$2:$N$1000,SMALL(IF(UPPER(TRANSACCIONES!$L$2:$L$1000)="PENDIENTE",ROW(TRANSACCIONES!$L$2:$L$1000)-ROW(TRANSACCIONES!$L$2)+1),19)),"") | F24: =IF(A24="","",TODAY()-A24) | G24: =IF(A24="","",IF(E24<TODAY(),"VENCIDO",IF(E24<=TODAY()+7,"POR VENCER","AL DÍA"))) | H24: =IFERROR(INDEX(TRANSACCIONES!$K$2:$K$1000,SMALL(IF(UPPER(TRANSACCIONES!$L$2:$L$1000)="PENDIENTE",ROW(TRANSACCIONES!$L$2:$L$1000)-ROW(TRANSACCIONES!$L$2)+1),19)),"")
A25: =IFERROR(INDEX(TRANSACCIONES!$A$2:$A$1000,SMALL(IF(UPPER(TRANSACCIONES!$L$2:$L$1000)="PENDIENTE",ROW(TRANSACCIONES!$L$2:$L$1000)-ROW(TRANSACCIONES!$L$2)+1),20)),"") | B25: =IFERROR(INDEX(TRANSACCIONES!$E$2:$E$1000,SMALL(IF(UPPER(TRANSACCIONES!$L$2:$L$1000)="PENDIENTE",ROW(TRANSACCIONES!$L$2:$L$1000)-ROW(TRANSACCIONES!$L$2)+1),20)),"") | C25: =IFERROR(INDEX(TRANSACCIONES!$F$2:$F$1000,SMALL(IF(UPPER(TRANSACCIONES!$L$2:$L$1000)="PENDIENTE",ROW(TRANSACCIONES!$L$2:$L$1000)-ROW(TRANSACCIONES!$L$2)+1),20)),"") | D25: =IFERROR(INDEX(TRANSACCIONES!$I$2:$I$1000,SMALL(IF(UPPER(TRANSACCIONES!$L$2:$L$1000)="PENDIENTE",ROW(TRANSACCIONES!$L$2:$L$1000)-ROW(TRANSACCIONES!$L$2)+1),20)),"") | E25: =IFERROR(INDEX(TRANSACCIONES!$N$2:$N$1000,SMALL(IF(UPPER(TRANSACCIONES!$L$2:$L$1000)="PENDIENTE",ROW(TRANSACCIONES!$L$2:$L$1000)-ROW(TRANSACCIONES!$L$2)+1),20)),"") | F25: =IF(A25="","",TODAY()-A25) | G25: =IF(A25="","",IF(E25<TODAY(),"VENCIDO",IF(E25<=TODAY()+7,"POR VENCER","AL DÍA"))) | H25: =IFERROR(INDEX(TRANSACCIONES!$K$2:$K$1000,SMALL(IF(UPPER(TRANSACCIONES!$L$2:$L$1000)="PENDIENTE",ROW(TRANSACCIONES!$L$2:$L$1000)-ROW(TRANSACCIONES!$L$2)+1),20)),"")
A26: =IFERROR(INDEX(TRANSACCIONES!$A$2:$A$1000,SMALL(IF(UPPER(TRANSACCIONES!$L$2:$L$1000)="PENDIENTE",ROW(TRANSACCIONES!$L$2:$L$1000)-ROW(TRANSACCIONES!$L$2)+1),21)),"") | B26: =IFERROR(INDEX(TRANSACCIONES!$E$2:$E$1000,SMALL(IF(UPPER(TRANSACCIONES!$L$2:$L$1000)="PENDIENTE",ROW(TRANSACCIONES!$L$2:$L$1000)-ROW(TRANSACCIONES!$L$2)+1),21)),"") | C26: =IFERROR(INDEX(TRANSACCIONES!$F$2:$F$1000,SMALL(IF(UPPER(TRANSACCIONES!$L$2:$L$1000)="PENDIENTE",ROW(TRANSACCIONES!$L$2:$L$1000)-ROW(TRANSACCIONES!$L$2)+1),21)),"") | D26: =IFERROR(INDEX(TRANSACCIONES!$I$2:$I$1000,SMALL(IF(UPPER(TRANSACCIONES!$L$2:$L$1000)="PENDIENTE",ROW(TRANSACCIONES!$L$2:$L$1000)-ROW(TRANSACCIONES!$L$2)+1),21)),"") | E26: =IFERROR(INDEX(TRANSACCIONES!$N$2:$N$1000,SMALL(IF(UPPER(TRANSACCIONES!$L$2:$L$1000)="PENDIENTE",ROW(TRANSACCIONES!$L$2:$L$1000)-ROW(TRANSACCIONES!$L$2)+1),21)),"") | F26: =IF(A26="","",TODAY()-A26) | G26: =IF(A26="","",IF(E26<TODAY(),"VENCIDO",IF(E26<=TODAY()+7,"POR VENCER","AL DÍA"))) | H26: =IFERROR(INDEX(TRANSACCIONES!$K$2:$K$1000,SMALL(IF(UPPER(TRANSACCIONES!$L$2:$L$1000)="PENDIENTE",ROW(TRANSACCIONES!$L$2:$L$1000)-ROW(TRANSACCIONES!$L$2)+1),21)),"")
A27: =IFERROR(INDEX(TRANSACCIONES!$A$2:$A$1000,SMALL(IF(UPPER(TRANSACCIONES!$L$2:$L$1000)="PENDIENTE",ROW(TRANSACCIONES!$L$2:$L$1000)-ROW(TRANSACCIONES!$L$2)+1),22)),"") | B27: =IFERROR(INDEX(TRANSACCIONES!$E$2:$E$1000,SMALL(IF(UPPER(TRANSACCIONES!$L$2:$L$1000)="PENDIENTE",ROW(TRANSACCIONES!$L$2:$L$1000)-ROW(TRANSACCIONES!$L$2)+1),22)),"") | C27: =IFERROR(INDEX(TRANSACCIONES!$F$2:$F$1000,SMALL(IF(UPPER(TRANSACCIONES!$L$2:$L$1000)="PENDIENTE",ROW(TRANSACCIONES!$L$2:$L$1000)-ROW(TRANSACCIONES!$L$2)+1),22)),"") | D27: =IFERROR(INDEX(TRANSACCIONES!$I$2:$I$1000,SMALL(IF(UPPER(TRANSACCIONES!$L$2:$L$1000)="PENDIENTE",ROW(TRANSACCIONES!$L$2:$L$1000)-ROW(TRANSACCIONES!$L$2)+1),22)),"") | E27: =IFERROR(INDEX(TRANSACCIONES!$N$2:$N$1000,SMALL(IF(UPPER(TRANSACCIONES!$L$2:$L$1000)="PENDIENTE",ROW(TRANSACCIONES!$L$2:$L$1000)-ROW(TRANSACCIONES!$L$2)+1),22)),"") | F27: =IF(A27="","",TODAY()-A27) | G27: =IF(A27="","",IF(E27<TODAY(),"VENCIDO",IF(E27<=TODAY()+7,"POR VENCER","AL DÍA"))) | H27: =IFERROR(INDEX(TRANSACCIONES!$K$2:$K$1000,SMALL(IF(UPPER(TRANSACCIONES!$L$2:$L$1000)="PENDIENTE",ROW(TRANSACCIONES!$L$2:$L$1000)-ROW(TRANSACCIONES!$L$2)+1),22)),"")
A28: =IFERROR(INDEX(TRANSACCIONES!$A$2:$A$1000,SMALL(IF(UPPER(TRANSACCIONES!$L$2:$L$1000)="PENDIENTE",ROW(TRANSACCIONES!$L$2:$L$1000)-ROW(TRANSACCIONES!$L$2)+1),23)),"") | B28: =IFERROR(INDEX(TRANSACCIONES!$E$2:$E$1000,SMALL(IF(UPPER(TRANSACCIONES!$L$2:$L$1000)="PENDIENTE",ROW(TRANSACCIONES!$L$2:$L$1000)-ROW(TRANSACCIONES!$L$2)+1),23)),"") | C28: =IFERROR(INDEX(TRANSACCIONES!$F$2:$F$1000,SMALL(IF(UPPER(TRANSACCIONES!$L$2:$L$1000)="PENDIENTE",ROW(TRANSACCIONES!$L$2:$L$1000)-ROW(TRANSACCIONES!$L$2)+1),23)),"") | D28: =IFERROR(INDEX(TRANSACCIONES!$I$2:$I$1000,SMALL(IF(UPPER(TRANSACCIONES!$L$2:$L$1000)="PENDIENTE",ROW(TRANSACCIONES!$L$2:$L$1000)-ROW(TRANSACCIONES!$L$2)+1),23)),"") | E28: =IFERROR(INDEX(TRANSACCIONES!$N$2:$N$1000,SMALL(IF(UPPER(TRANSACCIONES!$L$2:$L$1000)="PENDIENTE",ROW(TRANSACCIONES!$L$2:$L$1000)-ROW(TRANSACCIONES!$L$2)+1),23)),"") | F28: =IF(A28="","",TODAY()-A28) | G28: =IF(A28="","",IF(E28<TODAY(),"VENCIDO",IF(E28<=TODAY()+7,"POR VENCER","AL DÍA"))) | H28: =IFERROR(INDEX(TRANSACCIONES!$K$2:$K$1000,SMALL(IF(UPPER(TRANSACCIONES!$L$2:$L$1000)="PENDIENTE",ROW(TRANSACCIONES!$L$2:$L$1000)-ROW(TRANSACCIONES!$L$2)+1),23)),"")
A29: =IFERROR(INDEX(TRANSACCIONES!$A$2:$A$1000,SMALL(IF(UPPER(TRANSACCIONES!$L$2:$L$1000)="PENDIENTE",ROW(TRANSACCIONES!$L$2:$L$1000)-ROW(TRANSACCIONES!$L$2)+1),24)),"") | B29: =IFERROR(INDEX(TRANSACCIONES!$E$2:$E$1000,SMALL(IF(UPPER(TRANSACCIONES!$L$2:$L$1000)="PENDIENTE",ROW(TRANSACCIONES!$L$2:$L$1000)-ROW(TRANSACCIONES!$L$2)+1),24)),"") | C29: =IFERROR(INDEX(TRANSACCIONES!$F$2:$F$1000,SMALL(IF(UPPER(TRANSACCIONES!$L$2:$L$1000)="PENDIENTE",ROW(TRANSACCIONES!$L$2:$L$1000)-ROW(TRANSACCIONES!$L$2)+1),24)),"") | D29: =IFERROR(INDEX(TRANSACCIONES!$I$2:$I$1000,SMALL(IF(UPPER(TRANSACCIONES!$L$2:$L$1000)="PENDIENTE",ROW(TRANSACCIONES!$L$2:$L$1000)-ROW(TRANSACCIONES!$L$2)+1),24)),"") | E29: =IFERROR(INDEX(TRANSACCIONES!$N$2:$N$1000,SMALL(IF(UPPER(TRANSACCIONES!$L$2:$L$1000)="PENDIENTE",ROW(TRANSACCIONES!$L$2:$L$1000)-ROW(TRANSACCIONES!$L$2)+1),24)),"") | F29: =IF(A29="","",TODAY()-A29) | G29: =IF(A29="","",IF(E29<TODAY(),"VENCIDO",IF(E29<=TODAY()+7,"POR VENCER","AL DÍA"))) | H29: =IFERROR(INDEX(TRANSACCIONES!$K$2:$K$1000,SMALL(IF(UPPER(TRANSACCIONES!$L$2:$L$1000)="PENDIENTE",ROW(TRANSACCIONES!$L$2:$L$1000)-ROW(TRANSACCIONES!$L$2)+1),24)),"")
A30: =IFERROR(INDEX(TRANSACCIONES!$A$2:$A$1000,SMALL(IF(UPPER(TRANSACCIONES!$L$2:$L$1000)="PENDIENTE",ROW(TRANSACCIONES!$L$2:$L$1000)-ROW(TRANSACCIONES!$L$2)+1),25)),"") | B30: =IFERROR(INDEX(TRANSACCIONES!$E$2:$E$1000,SMALL(IF(UPPER(TRANSACCIONES!$L$2:$L$1000)="PENDIENTE",ROW(TRANSACCIONES!$L$2:$L$1000)-ROW(TRANSACCIONES!$L$2)+1),25)),"") | C30: =IFERROR(INDEX(TRANSACCIONES!$F$2:$F$1000,SMALL(IF(UPPER(TRANSACCIONES!$L$2:$L$1000)="PENDIENTE",ROW(TRANSACCIONES!$L$2:$L$1000)-ROW(TRANSACCIONES!$L$2)+1),25)),"") | D30: =IFERROR(INDEX(TRANSACCIONES!$I$2:$I$1000,SMALL(IF(UPPER(TRANSACCIONES!$L$2:$L$1000)="PENDIENTE",ROW(TRANSACCIONES!$L$2:$L$1000)-ROW(TRANSACCIONES!$L$2)+1),25)),"") | E30: =IFERROR(INDEX(TRANSACCIONES!$N$2:$N$1000,SMALL(IF(UPPER(TRANSACCIONES!$L$2:$L$1000)="PENDIENTE",ROW(TRANSACCIONES!$L$2:$L$1000)-ROW(TRANSACCIONES!$L$2)+1),25)),"") | F30: =IF(A30="","",TODAY()-A30) | G30: =IF(A30="","",IF(E30<TODAY(),"VENCIDO",IF(E30<=TODAY()+7,"POR VENCER","AL DÍA"))) | H30: =IFERROR(INDEX(TRANSACCIONES!$K$2:$K$1000,SMALL(IF(UPPER(TRANSACCIONES!$L$2:$L$1000)="PENDIENTE",ROW(TRANSACCIONES!$L$2:$L$1000)-ROW(TRANSACCIONES!$L$2)+1),25)),"")
A31: =IFERROR(INDEX(TRANSACCIONES!$A$2:$A$1000,SMALL(IF(UPPER(TRANSACCIONES!$L$2:$L$1000)="PENDIENTE",ROW(TRANSACCIONES!$L$2:$L$1000)-ROW(TRANSACCIONES!$L$2)+1),26)),"") | B31: =IFERROR(INDEX(TRANSACCIONES!$E$2:$E$1000,SMALL(IF(UPPER(TRANSACCIONES!$L$2:$L$1000)="PENDIENTE",ROW(TRANSACCIONES!$L$2:$L$1000)-ROW(TRANSACCIONES!$L$2)+1),26)),"") | C31: =IFERROR(INDEX(TRANSACCIONES!$F$2:$F$1000,SMALL(IF(UPPER(TRANSACCIONES!$L$2:$L$1000)="PENDIENTE",ROW(TRANSACCIONES!$L$2:$L$1000)-ROW(TRANSACCIONES!$L$2)+1),26)),"") | D31: =IFERROR(INDEX(TRANSACCIONES!$I$2:$I$1000,SMALL(IF(UPPER(TRANSACCIONES!$L$2:$L$1000)="PENDIENTE",ROW(TRANSACCIONES!$L$2:$L$1000)-ROW(TRANSACCIONES!$L$2)+1),26)),"") | E31: =IFERROR(INDEX(TRANSACCIONES!$N$2:$N$1000,SMALL(IF(UPPER(TRANSACCIONES!$L$2:$L$1000)="PENDIENTE",ROW(TRANSACCIONES!$L$2:$L$1000)-ROW(TRANSACCIONES!$L$2)+1),26)),"") | F31: =IF(A31="","",TODAY()-A31) | G31: =IF(A31="","",IF(E31<TODAY(),"VENCIDO",IF(E31<=TODAY()+7,"POR VENCER","AL DÍA"))) | H31: =IFERROR(INDEX(TRANSACCIONES!$K$2:$K$1000,SMALL(IF(UPPER(TRANSACCIONES!$L$2:$L$1000)="PENDIENTE",ROW(TRANSACCIONES!$L$2:$L$1000)-ROW(TRANSACCIONES!$L$2)+1),26)),"")
A32: =IFERROR(INDEX(TRANSACCIONES!$A$2:$A$1000,SMALL(IF(UPPER(TRANSACCIONES!$L$2:$L$1000)="PENDIENTE",ROW(TRANSACCIONES!$L$2:$L$1000)-ROW(TRANSACCIONES!$L$2)+1),27)),"") | B32: =IFERROR(INDEX(TRANSACCIONES!$E$2:$E$1000,SMALL(IF(UPPER(TRANSACCIONES!$L$2:$L$1000)="PENDIENTE",ROW(TRANSACCIONES!$L$2:$L$1000)-ROW(TRANSACCIONES!$L$2)+1),27)),"") | C32: =IFERROR(INDEX(TRANSACCIONES!$F$2:$F$1000,SMALL(IF(UPPER(TRANSACCIONES!$L$2:$L$1000)="PENDIENTE",ROW(TRANSACCIONES!$L$2:$L$1000)-ROW(TRANSACCIONES!$L$2)+1),27)),"") | D32: =IFERROR(INDEX(TRANSACCIONES!$I$2:$I$1000,SMALL(IF(UPPER(TRANSACCIONES!$L$2:$L$1000)="PENDIENTE",ROW(TRANSACCIONES!$L$2:$L$1000)-ROW(TRANSACCIONES!$L$2)+1),27)),"") | E32: =IFERROR(INDEX(TRANSACCIONES!$N$2:$N$1000,SMALL(IF(UPPER(TRANSACCIONES!$L$2:$L$1000)="PENDIENTE",ROW(TRANSACCIONES!$L$2:$L$1000)-ROW(TRANSACCIONES!$L$2)+1),27)),"") | F32: =IF(A32="","",TODAY()-A32) | G32: =IF(A32="","",IF(E32<TODAY(),"VENCIDO",IF(E32<=TODAY()+7,"POR VENCER","AL DÍA"))) | H32: =IFERROR(INDEX(TRANSACCIONES!$K$2:$K$1000,SMALL(IF(UPPER(TRANSACCIONES!$L$2:$L$1000)="PENDIENTE",ROW(TRANSACCIONES!$L$2:$L$1000)-ROW(TRANSACCIONES!$L$2)+1),27)),"")
A33: =IFERROR(INDEX(TRANSACCIONES!$A$2:$A$1000,SMALL(IF(UPPER(TRANSACCIONES!$L$2:$L$1000)="PENDIENTE",ROW(TRANSACCIONES!$L$2:$L$1000)-ROW(TRANSACCIONES!$L$2)+1),28)),"") | B33: =IFERROR(INDEX(TRANSACCIONES!$E$2:$E$1000,SMALL(IF(UPPER(TRANSACCIONES!$L$2:$L$1000)="PENDIENTE",ROW(TRANSACCIONES!$L$2:$L$1000)-ROW(TRANSACCIONES!$L$2)+1),28)),"") | C33: =IFERROR(INDEX(TRANSACCIONES!$F$2:$F$1000,SMALL(IF(UPPER(TRANSACCIONES!$L$2:$L$1000)="PENDIENTE",ROW(TRANSACCIONES!$L$2:$L$1000)-ROW(TRANSACCIONES!$L$2)+1),28)),"") | D33: =IFERROR(INDEX(TRANSACCIONES!$I$2:$I$1000,SMALL(IF(UPPER(TRANSACCIONES!$L$2:$L$1000)="PENDIENTE",ROW(TRANSACCIONES!$L$2:$L$1000)-ROW(TRANSACCIONES!$L$2)+1),28)),"") | E33: =IFERROR(INDEX(TRANSACCIONES!$N$2:$N$1000,SMALL(IF(UPPER(TRANSACCIONES!$L$2:$L$1000)="PENDIENTE",ROW(TRANSACCIONES!$L$2:$L$1000)-ROW(TRANSACCIONES!$L$2)+1),28)),"") | F33: =IF(A33="","",TODAY()-A33) | G33: =IF(A33="","",IF(E33<TODAY(),"VENCIDO",IF(E33<=TODAY()+7,"POR VENCER","AL DÍA"))) | H33: =IFERROR(INDEX(TRANSACCIONES!$K$2:$K$1000,SMALL(IF(UPPER(TRANSACCIONES!$L$2:$L$1000)="PENDIENTE",ROW(TRANSACCIONES!$L$2:$L$1000)-ROW(TRANSACCIONES!$L$2)+1),28)),"")
A34: =IFERROR(INDEX(TRANSACCIONES!$A$2:$A$1000,SMALL(IF(UPPER(TRANSACCIONES!$L$2:$L$1000)="PENDIENTE",ROW(TRANSACCIONES!$L$2:$L$1000)-ROW(TRANSACCIONES!$L$2)+1),29)),"") | B34: =IFERROR(INDEX(TRANSACCIONES!$E$2:$E$1000,SMALL(IF(UPPER(TRANSACCIONES!$L$2:$L$1000)="PENDIENTE",ROW(TRANSACCIONES!$L$2:$L$1000)-ROW(TRANSACCIONES!$L$2)+1),29)),"") | C34: =IFERROR(INDEX(TRANSACCIONES!$F$2:$F$1000,SMALL(IF(UPPER(TRANSACCIONES!$L$2:$L$1000)="PENDIENTE",ROW(TRANSACCIONES!$L$2:$L$1000)-ROW(TRANSACCIONES!$L$2)+1),29)),"") | D34: =IFERROR(INDEX(TRANSACCIONES!$I$2:$I$1000,SMALL(IF(UPPER(TRANSACCIONES!$L$2:$L$1000)="PENDIENTE",ROW(TRANSACCIONES!$L$2:$L$1000)-ROW(TRANSACCIONES!$L$2)+1),29)),"") | E34: =IFERROR(INDEX(TRANSACCIONES!$N$2:$N$1000,SMALL(IF(UPPER(TRANSACCIONES!$L$2:$L$1000)="PENDIENTE",ROW(TRANSACCIONES!$L$2:$L$1000)-ROW(TRANSACCIONES!$L$2)+1),29)),"") | F34: =IF(A34="","",TODAY()-A34) | G34: =IF(A34="","",IF(E34<TODAY(),"VENCIDO",IF(E34<=TODAY()+7,"POR VENCER","AL DÍA"))) | H34: =IFERROR(INDEX(TRANSACCIONES!$K$2:$K$1000,SMALL(IF(UPPER(TRANSACCIONES!$L$2:$L$1000)="PENDIENTE",ROW(TRANSACCIONES!$L$2:$L$1000)-ROW(TRANSACCIONES!$L$2)+1),29)),"")
A35: =IFERROR(INDEX(TRANSACCIONES!$A$2:$A$1000,SMALL(IF(UPPER(TRANSACCIONES!$L$2:$L$1000)="PENDIENTE",ROW(TRANSACCIONES!$L$2:$L$1000)-ROW(TRANSACCIONES!$L$2)+1),30)),"") | B35: =IFERROR(INDEX(TRANSACCIONES!$E$2:$E$1000,SMALL(IF(UPPER(TRANSACCIONES!$L$2:$L$1000)="PENDIENTE",ROW(TRANSACCIONES!$L$2:$L$1000)-ROW(TRANSACCIONES!$L$2)+1),30)),"") | C35: =IFERROR(INDEX(TRANSACCIONES!$F$2:$F$1000,SMALL(IF(UPPER(TRANSACCIONES!$L$2:$L$1000)="PENDIENTE",ROW(TRANSACCIONES!$L$2:$L$1000)-ROW(TRANSACCIONES!$L$2)+1),30)),"") | D35: =IFERROR(INDEX(TRANSACCIONES!$I$2:$I$1000,SMALL(IF(UPPER(TRANSACCIONES!$L$2:$L$1000)="PENDIENTE",ROW(TRANSACCIONES!$L$2:$L$1000)-ROW(TRANSACCIONES!$L$2)+1),30)),"") | E35: =IFERROR(INDEX(TRANSACCIONES!$N$2:$N$1000,SMALL(IF(UPPER(TRANSACCIONES!$L$2:$L$1000)="PENDIENTE",ROW(TRANSACCIONES!$L$2:$L$1000)-ROW(TRANSACCIONES!$L$2)+1),30)),"") | F35: =IF(A35="","",TODAY()-A35) | G35: =IF(A35="","",IF(E35<TODAY(),"VENCIDO",IF(E35<=TODAY()+7,"POR VENCER","AL DÍA"))) | H35: =IFERROR(INDEX(TRANSACCIONES!$K$2:$K$1000,SMALL(IF(UPPER(TRANSACCIONES!$L$2:$L$1000)="PENDIENTE",ROW(TRANSACCIONES!$L$2:$L$1000)-ROW(TRANSACCIONES!$L$2)+1),30)),"")
A36: =IFERROR(INDEX(TRANSACCIONES!$A$2:$A$1000,SMALL(IF(UPPER(TRANSACCIONES!$L$2:$L$1000)="PENDIENTE",ROW(TRANSACCIONES!$L$2:$L$1000)-ROW(TRANSACCIONES!$L$2)+1),31)),"") | B36: =IFERROR(INDEX(TRANSACCIONES!$E$2:$E$1000,SMALL(IF(UPPER(TRANSACCIONES!$L$2:$L$1000)="PENDIENTE",ROW(TRANSACCIONES!$L$2:$L$1000)-ROW(TRANSACCIONES!$L$2)+1),31)),"") | C36: =IFERROR(INDEX(TRANSACCIONES!$F$2:$F$1000,SMALL(IF(UPPER(TRANSACCIONES!$L$2:$L$1000)="PENDIENTE",ROW(TRANSACCIONES!$L$2:$L$1000)-ROW(TRANSACCIONES!$L$2)+1),31)),"") | D36: =IFERROR(INDEX(TRANSACCIONES!$I$2:$I$1000,SMALL(IF(UPPER(TRANSACCIONES!$L$2:$L$1000)="PENDIENTE",ROW(TRANSACCIONES!$L$2:$L$1000)-ROW(TRANSACCIONES!$L$2)+1),31)),"") | E36: =IFERROR(INDEX(TRANSACCIONES!$N$2:$N$1000,SMALL(IF(UPPER(TRANSACCIONES!$L$2:$L$1000)="PENDIENTE",ROW(TRANSACCIONES!$L$2:$L$1000)-ROW(TRANSACCIONES!$L$2)+1),31)),"") | F36: =IF(A36="","",TODAY()-A36) | G36: =IF(A36="","",IF(E36<TODAY(),"VENCIDO",IF(E36<=TODAY()+7,"POR VENCER","AL DÍA"))) | H36: =IFERROR(INDEX(TRANSACCIONES!$K$2:$K$1000,SMALL(IF(UPPER(TRANSACCIONES!$L$2:$L$1000)="PENDIENTE",ROW(TRANSACCIONES!$L$2:$L$1000)-ROW(TRANSACCIONES!$L$2)+1),31)),"")
A37: =IFERROR(INDEX(TRANSACCIONES!$A$2:$A$1000,SMALL(IF(UPPER(TRANSACCIONES!$L$2:$L$1000)="PENDIENTE",ROW(TRANSACCIONES!$L$2:$L$1000)-ROW(TRANSACCIONES!$L$2)+1),32)),"") | B37: =IFERROR(INDEX(TRANSACCIONES!$E$2:$E$1000,SMALL(IF(UPPER(TRANSACCIONES!$L$2:$L$1000)="PENDIENTE",ROW(TRANSACCIONES!$L$2:$L$1000)-ROW(TRANSACCIONES!$L$2)+1),32)),"") | C37: =IFERROR(INDEX(TRANSACCIONES!$F$2:$F$1000,SMALL(IF(UPPER(TRANSACCIONES!$L$2:$L$1000)="PENDIENTE",ROW(TRANSACCIONES!$L$2:$L$1000)-ROW(TRANSACCIONES!$L$2)+1),32)),"") | D37: =IFERROR(INDEX(TRANSACCIONES!$I$2:$I$1000,SMALL(IF(UPPER(TRANSACCIONES!$L$2:$L$1000)="PENDIENTE",ROW(TRANSACCIONES!$L$2:$L$1000)-ROW(TRANSACCIONES!$L$2)+1),32)),"") | E37: =IFERROR(INDEX(TRANSACCIONES!$N$2:$N$1000,SMALL(IF(UPPER(TRANSACCIONES!$L$2:$L$1000)="PENDIENTE",ROW(TRANSACCIONES!$L$2:$L$1000)-ROW(TRANSACCIONES!$L$2)+1),32)),"") | F37: =IF(A37="","",TODAY()-A37) | G37: =IF(A37="","",IF(E37<TODAY(),"VENCIDO",IF(E37<=TODAY()+7,"POR VENCER","AL DÍA"))) | H37: =IFERROR(INDEX(TRANSACCIONES!$K$2:$K$1000,SMALL(IF(UPPER(TRANSACCIONES!$L$2:$L$1000)="PENDIENTE",ROW(TRANSACCIONES!$L$2:$L$1000)-ROW(TRANSACCIONES!$L$2)+1),32)),"")
A38: =IFERROR(INDEX(TRANSACCIONES!$A$2:$A$1000,SMALL(IF(UPPER(TRANSACCIONES!$L$2:$L$1000)="PENDIENTE",ROW(TRANSACCIONES!$L$2:$L$1000)-ROW(TRANSACCIONES!$L$2)+1),33)),"") | B38: =IFERROR(INDEX(TRANSACCIONES!$E$2:$E$1000,SMALL(IF(UPPER(TRANSACCIONES!$L$2:$L$1000)="PENDIENTE",ROW(TRANSACCIONES!$L$2:$L$1000)-ROW(TRANSACCIONES!$L$2)+1),33)),"") | C38: =IFERROR(INDEX(TRANSACCIONES!$F$2:$F$1000,SMALL(IF(UPPER(TRANSACCIONES!$L$2:$L$1000)="PENDIENTE",ROW(TRANSACCIONES!$L$2:$L$1000)-ROW(TRANSACCIONES!$L$2)+1),33)),"") | D38: =IFERROR(INDEX(TRANSACCIONES!$I$2:$I$1000,SMALL(IF(UPPER(TRANSACCIONES!$L$2:$L$1000)="PENDIENTE",ROW(TRANSACCIONES!$L$2:$L$1000)-ROW(TRANSACCIONES!$L$2)+1),33)),"") | E38: =IFERROR(INDEX(TRANSACCIONES!$N$2:$N$1000,SMALL(IF(UPPER(TRANSACCIONES!$L$2:$L$1000)="PENDIENTE",ROW(TRANSACCIONES!$L$2:$L$1000)-ROW(TRANSACCIONES!$L$2)+1),33)),"") | F38: =IF(A38="","",TODAY()-A38) | G38: =IF(A38="","",IF(E38<TODAY(),"VENCIDO",IF(E38<=TODAY()+7,"POR VENCER","AL DÍA"))) | H38: =IFERROR(INDEX(TRANSACCIONES!$K$2:$K$1000,SMALL(IF(UPPER(TRANSACCIONES!$L$2:$L$1000)="PENDIENTE",ROW(TRANSACCIONES!$L$2:$L$1000)-ROW(TRANSACCIONES!$L$2)+1),33)),"")
A39: =IFERROR(INDEX(TRANSACCIONES!$A$2:$A$1000,SMALL(IF(UPPER(TRANSACCIONES!$L$2:$L$1000)="PENDIENTE",ROW(TRANSACCIONES!$L$2:$L$1000)-ROW(TRANSACCIONES!$L$2)+1),34)),"") | B39: =IFERROR(INDEX(TRANSACCIONES!$E$2:$E$1000,SMALL(IF(UPPER(TRANSACCIONES!$L$2:$L$1000)="PENDIENTE",ROW(TRANSACCIONES!$L$2:$L$1000)-ROW(TRANSACCIONES!$L$2)+1),34)),"") | C39: =IFERROR(INDEX(TRANSACCIONES!$F$2:$F$1000,SMALL(IF(UPPER(TRANSACCIONES!$L$2:$L$1000)="PENDIENTE",ROW(TRANSACCIONES!$L$2:$L$1000)-ROW(TRANSACCIONES!$L$2)+1),34)),"") | D39: =IFERROR(INDEX(TRANSACCIONES!$I$2:$I$1000,SMALL(IF(UPPER(TRANSACCIONES!$L$2:$L$1000)="PENDIENTE",ROW(TRANSACCIONES!$L$2:$L$1000)-ROW(TRANSACCIONES!$L$2)+1),34)),"") | E39: =IFERROR(INDEX(TRANSACCIONES!$N$2:$N$1000,SMALL(IF(UPPER(TRANSACCIONES!$L$2:$L$1000)="PENDIENTE",ROW(TRANSACCIONES!$L$2:$L$1000)-ROW(TRANSACCIONES!$L$2)+1),34)),"") | F39: =IF(A39="","",TODAY()-A39) | G39: =IF(A39="","",IF(E39<TODAY(),"VENCIDO",IF(E39<=TODAY()+7,"POR VENCER","AL DÍA"))) | H39: =IFERROR(INDEX(TRANSACCIONES!$K$2:$K$1000,SMALL(IF(UPPER(TRANSACCIONES!$L$2:$L$1000)="PENDIENTE",ROW(TRANSACCIONES!$L$2:$L$1000)-ROW(TRANSACCIONES!$L$2)+1),34)),"")
A40: =IFERROR(INDEX(TRANSACCIONES!$A$2:$A$1000,SMALL(IF(UPPER(TRANSACCIONES!$L$2:$L$1000)="PENDIENTE",ROW(TRANSACCIONES!$L$2:$L$1000)-ROW(TRANSACCIONES!$L$2)+1),35)),"") | B40: =IFERROR(INDEX(TRANSACCIONES!$E$2:$E$1000,SMALL(IF(UPPER(TRANSACCIONES!$L$2:$L$1000)="PENDIENTE",ROW(TRANSACCIONES!$L$2:$L$1000)-ROW(TRANSACCIONES!$L$2)+1),35)),"") | C40: =IFERROR(INDEX(TRANSACCIONES!$F$2:$F$1000,SMALL(IF(UPPER(TRANSACCIONES!$L$2:$L$1000)="PENDIENTE",ROW(TRANSACCIONES!$L$2:$L$1000)-ROW(TRANSACCIONES!$L$2)+1),35)),"") | D40: =IFERROR(INDEX(TRANSACCIONES!$I$2:$I$1000,SMALL(IF(UPPER(TRANSACCIONES!$L$2:$L$1000)="PENDIENTE",ROW(TRANSACCIONES!$L$2:$L$1000)-ROW(TRANSACCIONES!$L$2)+1),35)),"") | E40: =IFERROR(INDEX(TRANSACCIONES!$N$2:$N$1000,SMALL(IF(UPPER(TRANSACCIONES!$L$2:$L$1000)="PENDIENTE",ROW(TRANSACCIONES!$L$2:$L$1000)-ROW(TRANSACCIONES!$L$2)+1),35)),"") | F40: =IF(A40="","",TODAY()-A40) | G40: =IF(A40="","",IF(E40<TODAY(),"VENCIDO",IF(E40<=TODAY()+7,"POR VENCER","AL DÍA"))) | H40: =IFERROR(INDEX(TRANSACCIONES!$K$2:$K$1000,SMALL(IF(UPPER(TRANSACCIONES!$L$2:$L$1000)="PENDIENTE",ROW(TRANSACCIONES!$L$2:$L$1000)-ROW(TRANSACCIONES!$L$2)+1),35)),"")
A41: =IFERROR(INDEX(TRANSACCIONES!$A$2:$A$1000,SMALL(IF(UPPER(TRANSACCIONES!$L$2:$L$1000)="PENDIENTE",ROW(TRANSACCIONES!$L$2:$L$1000)-ROW(TRANSACCIONES!$L$2)+1),36)),"") | B41: =IFERROR(INDEX(TRANSACCIONES!$E$2:$E$1000,SMALL(IF(UPPER(TRANSACCIONES!$L$2:$L$1000)="PENDIENTE",ROW(TRANSACCIONES!$L$2:$L$1000)-ROW(TRANSACCIONES!$L$2)+1),36)),"") | C41: =IFERROR(INDEX(TRANSACCIONES!$F$2:$F$1000,SMALL(IF(UPPER(TRANSACCIONES!$L$2:$L$1000)="PENDIENTE",ROW(TRANSACCIONES!$L$2:$L$1000)-ROW(TRANSACCIONES!$L$2)+1),36)),"") | D41: =IFERROR(INDEX(TRANSACCIONES!$I$2:$I$1000,SMALL(IF(UPPER(TRANSACCIONES!$L$2:$L$1000)="PENDIENTE",ROW(TRANSACCIONES!$L$2:$L$1000)-ROW(TRANSACCIONES!$L$2)+1),36)),"") | E41: =IFERROR(INDEX(TRANSACCIONES!$N$2:$N$1000,SMALL(IF(UPPER(TRANSACCIONES!$L$2:$L$1000)="PENDIENTE",ROW(TRANSACCIONES!$L$2:$L$1000)-ROW(TRANSACCIONES!$L$2)+1),36)),"") | F41: =IF(A41="","",TODAY()-A41) | G41: =IF(A41="","",IF(E41<TODAY(),"VENCIDO",IF(E41<=TODAY()+7,"POR VENCER","AL DÍA"))) | H41: =IFERROR(INDEX(TRANSACCIONES!$K$2:$K$1000,SMALL(IF(UPPER(TRANSACCIONES!$L$2:$L$1000)="PENDIENTE",ROW(TRANSACCIONES!$L$2:$L$1000)-ROW(TRANSACCIONES!$L$2)+1),36)),"")
A42: =IFERROR(INDEX(TRANSACCIONES!$A$2:$A$1000,SMALL(IF(UPPER(TRANSACCIONES!$L$2:$L$1000)="PENDIENTE",ROW(TRANSACCIONES!$L$2:$L$1000)-ROW(TRANSACCIONES!$L$2)+1),37)),"") | B42: =IFERROR(INDEX(TRANSACCIONES!$E$2:$E$1000,SMALL(IF(UPPER(TRANSACCIONES!$L$2:$L$1000)="PENDIENTE",ROW(TRANSACCIONES!$L$2:$L$1000)-ROW(TRANSACCIONES!$L$2)+1),37)),"") | C42: =IFERROR(INDEX(TRANSACCIONES!$F$2:$F$1000,SMALL(IF(UPPER(TRANSACCIONES!$L$2:$L$1000)="PENDIENTE",ROW(TRANSACCIONES!$L$2:$L$1000)-ROW(TRANSACCIONES!$L$2)+1),37)),"") | D42: =IFERROR(INDEX(TRANSACCIONES!$I$2:$I$1000,SMALL(IF(UPPER(TRANSACCIONES!$L$2:$L$1000)="PENDIENTE",ROW(TRANSACCIONES!$L$2:$L$1000)-ROW(TRANSACCIONES!$L$2)+1),37)),"") | E42: =IFERROR(INDEX(TRANSACCIONES!$N$2:$N$1000,SMALL(IF(UPPER(TRANSACCIONES!$L$2:$L$1000)="PENDIENTE",ROW(TRANSACCIONES!$L$2:$L$1000)-ROW(TRANSACCIONES!$L$2)+1),37)),"") | F42: =IF(A42="","",TODAY()-A42) | G42: =IF(A42="","",IF(E42<TODAY(),"VENCIDO",IF(E42<=TODAY()+7,"POR VENCER","AL DÍA"))) | H42: =IFERROR(INDEX(TRANSACCIONES!$K$2:$K$1000,SMALL(IF(UPPER(TRANSACCIONES!$L$2:$L$1000)="PENDIENTE",ROW(TRANSACCIONES!$L$2:$L$1000)-ROW(TRANSACCIONES!$L$2)+1),37)),"")
A43: =IFERROR(INDEX(TRANSACCIONES!$A$2:$A$1000,SMALL(IF(UPPER(TRANSACCIONES!$L$2:$L$1000)="PENDIENTE",ROW(TRANSACCIONES!$L$2:$L$1000)-ROW(TRANSACCIONES!$L$2)+1),38)),"") | B43: =IFERROR(INDEX(TRANSACCIONES!$E$2:$E$1000,SMALL(IF(UPPER(TRANSACCIONES!$L$2:$L$1000)="PENDIENTE",ROW(TRANSACCIONES!$L$2:$L$1000)-ROW(TRANSACCIONES!$L$2)+1),38)),"") | C43: =IFERROR(INDEX(TRANSACCIONES!$F$2:$F$1000,SMALL(IF(UPPER(TRANSACCIONES!$L$2:$L$1000)="PENDIENTE",ROW(TRANSACCIONES!$L$2:$L$1000)-ROW(TRANSACCIONES!$L$2)+1),38)),"") | D43: =IFERROR(INDEX(TRANSACCIONES!$I$2:$I$1000,SMALL(IF(UPPER(TRANSACCIONES!$L$2:$L$1000)="PENDIENTE",ROW(TRANSACCIONES!$L$2:$L$1000)-ROW(TRANSACCIONES!$L$2)+1),38)),"") | E43: =IFERROR(INDEX(TRANSACCIONES!$N$2:$N$1000,SMALL(IF(UPPER(TRANSACCIONES!$L$2:$L$1000)="PENDIENTE",ROW(TRANSACCIONES!$L$2:$L$1000)-ROW(TRANSACCIONES!$L$2)+1),38)),"") | F43: =IF(A43="","",TODAY()-A43) | G43: =IF(A43="","",IF(E43<TODAY(),"VENCIDO",IF(E43<=TODAY()+7,"POR VENCER","AL DÍA"))) | H43: =IFERROR(INDEX(TRANSACCIONES!$K$2:$K$1000,SMALL(IF(UPPER(TRANSACCIONES!$L$2:$L$1000)="PENDIENTE",ROW(TRANSACCIONES!$L$2:$L$1000)-ROW(TRANSACCIONES!$L$2)+1),38)),"")
A44: =IFERROR(INDEX(TRANSACCIONES!$A$2:$A$1000,SMALL(IF(UPPER(TRANSACCIONES!$L$2:$L$1000)="PENDIENTE",ROW(TRANSACCIONES!$L$2:$L$1000)-ROW(TRANSACCIONES!$L$2)+1),39)),"") | B44: =IFERROR(INDEX(TRANSACCIONES!$E$2:$E$1000,SMALL(IF(UPPER(TRANSACCIONES!$L$2:$L$1000)="PENDIENTE",ROW(TRANSACCIONES!$L$2:$L$1000)-ROW(TRANSACCIONES!$L$2)+1),39)),"") | C44: =IFERROR(INDEX(TRANSACCIONES!$F$2:$F$1000,SMALL(IF(UPPER(TRANSACCIONES!$L$2:$L$1000)="PENDIENTE",ROW(TRANSACCIONES!$L$2:$L$1000)-ROW(TRANSACCIONES!$L$2)+1),39)),"") | D44: =IFERROR(INDEX(TRANSACCIONES!$I$2:$I$1000,SMALL(IF(UPPER(TRANSACCIONES!$L$2:$L$1000)="PENDIENTE",ROW(TRANSACCIONES!$L$2:$L$1000)-ROW(TRANSACCIONES!$L$2)+1),39)),"") | E44: =IFERROR(INDEX(TRANSACCIONES!$N$2:$N$1000,SMALL(IF(UPPER(TRANSACCIONES!$L$2:$L$1000)="PENDIENTE",ROW(TRANSACCIONES!$L$2:$L$1000)-ROW(TRANSACCIONES!$L$2)+1),39)),"") | F44: =IF(A44="","",TODAY()-A44) | G44: =IF(A44="","",IF(E44<TODAY(),"VENCIDO",IF(E44<=TODAY()+7,"POR VENCER","AL DÍA"))) | H44: =IFERROR(INDEX(TRANSACCIONES!$K$2:$K$1000,SMALL(IF(UPPER(TRANSACCIONES!$L$2:$L$1000)="PENDIENTE",ROW(TRANSACCIONES!$L$2:$L$1000)-ROW(TRANSACCIONES!$L$2)+1),39)),"")
A45: =IFERROR(INDEX(TRANSACCIONES!$A$2:$A$1000,SMALL(IF(UPPER(TRANSACCIONES!$L$2:$L$1000)="PENDIENTE",ROW(TRANSACCIONES!$L$2:$L$1000)-ROW(TRANSACCIONES!$L$2)+1),40)),"") | B45: =IFERROR(INDEX(TRANSACCIONES!$E$2:$E$1000,SMALL(IF(UPPER(TRANSACCIONES!$L$2:$L$1000)="PENDIENTE",ROW(TRANSACCIONES!$L$2:$L$1000)-ROW(TRANSACCIONES!$L$2)+1),40)),"") | C45: =IFERROR(INDEX(TRANSACCIONES!$F$2:$F$1000,SMALL(IF(UPPER(TRANSACCIONES!$L$2:$L$1000)="PENDIENTE",ROW(TRANSACCIONES!$L$2:$L$1000)-ROW(TRANSACCIONES!$L$2)+1),40)),"") | D45: =IFERROR(INDEX(TRANSACCIONES!$I$2:$I$1000,SMALL(IF(UPPER(TRANSACCIONES!$L$2:$L$1000)="PENDIENTE",ROW(TRANSACCIONES!$L$2:$L$1000)-ROW(TRANSACCIONES!$L$2)+1),40)),"") | E45: =IFERROR(INDEX(TRANSACCIONES!$N$2:$N$1000,SMALL(IF(UPPER(TRANSACCIONES!$L$2:$L$1000)="PENDIENTE",ROW(TRANSACCIONES!$L$2:$L$1000)-ROW(TRANSACCIONES!$L$2)+1),40)),"") | F45: =IF(A45="","",TODAY()-A45) | G45: =IF(A45="","",IF(E45<TODAY(),"VENCIDO",IF(E45<=TODAY()+7,"POR VENCER","AL DÍA"))) | H45: =IFERROR(INDEX(TRANSACCIONES!$K$2:$K$1000,SMALL(IF(UPPER(TRANSACCIONES!$L$2:$L$1000)="PENDIENTE",ROW(TRANSACCIONES!$L$2:$L$1000)-ROW(TRANSACCIONES!$L$2)+1),40)),"")
A46: =IFERROR(INDEX(TRANSACCIONES!$A$2:$A$1000,SMALL(IF(UPPER(TRANSACCIONES!$L$2:$L$1000)="PENDIENTE",ROW(TRANSACCIONES!$L$2:$L$1000)-ROW(TRANSACCIONES!$L$2)+1),41)),"") | B46: =IFERROR(INDEX(TRANSACCIONES!$E$2:$E$1000,SMALL(IF(UPPER(TRANSACCIONES!$L$2:$L$1000)="PENDIENTE",ROW(TRANSACCIONES!$L$2:$L$1000)-ROW(TRANSACCIONES!$L$2)+1),41)),"") | C46: =IFERROR(INDEX(TRANSACCIONES!$F$2:$F$1000,SMALL(IF(UPPER(TRANSACCIONES!$L$2:$L$1000)="PENDIENTE",ROW(TRANSACCIONES!$L$2:$L$1000)-ROW(TRANSACCIONES!$L$2)+1),41)),"") | D46: =IFERROR(INDEX(TRANSACCIONES!$I$2:$I$1000,SMALL(IF(UPPER(TRANSACCIONES!$L$2:$L$1000)="PENDIENTE",ROW(TRANSACCIONES!$L$2:$L$1000)-ROW(TRANSACCIONES!$L$2)+1),41)),"") | E46: =IFERROR(INDEX(TRANSACCIONES!$N$2:$N$1000,SMALL(IF(UPPER(TRANSACCIONES!$L$2:$L$1000)="PENDIENTE",ROW(TRANSACCIONES!$L$2:$L$1000)-ROW(TRANSACCIONES!$L$2)+1),41)),"") | F46: =IF(A46="","",TODAY()-A46) | G46: =IF(A46="","",IF(E46<TODAY(),"VENCIDO",IF(E46<=TODAY()+7,"POR VENCER","AL DÍA"))) | H46: =IFERROR(INDEX(TRANSACCIONES!$K$2:$K$1000,SMALL(IF(UPPER(TRANSACCIONES!$L$2:$L$1000)="PENDIENTE",ROW(TRANSACCIONES!$L$2:$L$1000)-ROW(TRANSACCIONES!$L$2)+1),41)),"")
A47: =IFERROR(INDEX(TRANSACCIONES!$A$2:$A$1000,SMALL(IF(UPPER(TRANSACCIONES!$L$2:$L$1000)="PENDIENTE",ROW(TRANSACCIONES!$L$2:$L$1000)-ROW(TRANSACCIONES!$L$2)+1),42)),"") | B47: =IFERROR(INDEX(TRANSACCIONES!$E$2:$E$1000,SMALL(IF(UPPER(TRANSACCIONES!$L$2:$L$1000)="PENDIENTE",ROW(TRANSACCIONES!$L$2:$L$1000)-ROW(TRANSACCIONES!$L$2)+1),42)),"") | C47: =IFERROR(INDEX(TRANSACCIONES!$F$2:$F$1000,SMALL(IF(UPPER(TRANSACCIONES!$L$2:$L$1000)="PENDIENTE",ROW(TRANSACCIONES!$L$2:$L$1000)-ROW(TRANSACCIONES!$L$2)+1),42)),"") | D47: =IFERROR(INDEX(TRANSACCIONES!$I$2:$I$1000,SMALL(IF(UPPER(TRANSACCIONES!$L$2:$L$1000)="PENDIENTE",ROW(TRANSACCIONES!$L$2:$L$1000)-ROW(TRANSACCIONES!$L$2)+1),42)),"") | E47: =IFERROR(INDEX(TRANSACCIONES!$N$2:$N$1000,SMALL(IF(UPPER(TRANSACCIONES!$L$2:$L$1000)="PENDIENTE",ROW(TRANSACCIONES!$L$2:$L$1000)-ROW(TRANSACCIONES!$L$2)+1),42)),"") | F47: =IF(A47="","",TODAY()-A47) | G47: =IF(A47="","",IF(E47<TODAY(),"VENCIDO",IF(E47<=TODAY()+7,"POR VENCER","AL DÍA"))) | H47: =IFERROR(INDEX(TRANSACCIONES!$K$2:$K$1000,SMALL(IF(UPPER(TRANSACCIONES!$L$2:$L$1000)="PENDIENTE",ROW(TRANSACCIONES!$L$2:$L$1000)-ROW(TRANSACCIONES!$L$2)+1),42)),"")
A48: =IFERROR(INDEX(TRANSACCIONES!$A$2:$A$1000,SMALL(IF(UPPER(TRANSACCIONES!$L$2:$L$1000)="PENDIENTE",ROW(TRANSACCIONES!$L$2:$L$1000)-ROW(TRANSACCIONES!$L$2)+1),43)),"") | B48: =IFERROR(INDEX(TRANSACCIONES!$E$2:$E$1000,SMALL(IF(UPPER(TRANSACCIONES!$L$2:$L$1000)="PENDIENTE",ROW(TRANSACCIONES!$L$2:$L$1000)-ROW(TRANSACCIONES!$L$2)+1),43)),"") | C48: =IFERROR(INDEX(TRANSACCIONES!$F$2:$F$1000,SMALL(IF(UPPER(TRANSACCIONES!$L$2:$L$1000)="PENDIENTE",ROW(TRANSACCIONES!$L$2:$L$1000)-ROW(TRANSACCIONES!$L$2)+1),43)),"") | D48: =IFERROR(INDEX(TRANSACCIONES!$I$2:$I$1000,SMALL(IF(UPPER(TRANSACCIONES!$L$2:$L$1000)="PENDIENTE",ROW(TRANSACCIONES!$L$2:$L$1000)-ROW(TRANSACCIONES!$L$2)+1),43)),"") | E48: =IFERROR(INDEX(TRANSACCIONES!$N$2:$N$1000,SMALL(IF(UPPER(TRANSACCIONES!$L$2:$L$1000)="PENDIENTE",ROW(TRANSACCIONES!$L$2:$L$1000)-ROW(TRANSACCIONES!$L$2)+1),43)),"") | F48: =IF(A48="","",TODAY()-A48) | G48: =IF(A48="","",IF(E48<TODAY(),"VENCIDO",IF(E48<=TODAY()+7,"POR VENCER","AL DÍA"))) | H48: =IFERROR(INDEX(TRANSACCIONES!$K$2:$K$1000,SMALL(IF(UPPER(TRANSACCIONES!$L$2:$L$1000)="PENDIENTE",ROW(TRANSACCIONES!$L$2:$L$1000)-ROW(TRANSACCIONES!$L$2)+1),43)),"")
A49: =IFERROR(INDEX(TRANSACCIONES!$A$2:$A$1000,SMALL(IF(UPPER(TRANSACCIONES!$L$2:$L$1000)="PENDIENTE",ROW(TRANSACCIONES!$L$2:$L$1000)-ROW(TRANSACCIONES!$L$2)+1),44)),"") | B49: =IFERROR(INDEX(TRANSACCIONES!$E$2:$E$1000,SMALL(IF(UPPER(TRANSACCIONES!$L$2:$L$1000)="PENDIENTE",ROW(TRANSACCIONES!$L$2:$L$1000)-ROW(TRANSACCIONES!$L$2)+1),44)),"") | C49: =IFERROR(INDEX(TRANSACCIONES!$F$2:$F$1000,SMALL(IF(UPPER(TRANSACCIONES!$L$2:$L$1000)="PENDIENTE",ROW(TRANSACCIONES!$L$2:$L$1000)-ROW(TRANSACCIONES!$L$2)+1),44)),"") | D49: =IFERROR(INDEX(TRANSACCIONES!$I$2:$I$1000,SMALL(IF(UPPER(TRANSACCIONES!$L$2:$L$1000)="PENDIENTE",ROW(TRANSACCIONES!$L$2:$L$1000)-ROW(TRANSACCIONES!$L$2)+1),44)),"") | E49: =IFERROR(INDEX(TRANSACCIONES!$N$2:$N$1000,SMALL(IF(UPPER(TRANSACCIONES!$L$2:$L$1000)="PENDIENTE",ROW(TRANSACCIONES!$L$2:$L$1000)-ROW(TRANSACCIONES!$L$2)+1),44)),"") | F49: =IF(A49="","",TODAY()-A49) | G49: =IF(A49="","",IF(E49<TODAY(),"VENCIDO",IF(E49<=TODAY()+7,"POR VENCER","AL DÍA"))) | H49: =IFERROR(INDEX(TRANSACCIONES!$K$2:$K$1000,SMALL(IF(UPPER(TRANSACCIONES!$L$2:$L$1000)="PENDIENTE",ROW(TRANSACCIONES!$L$2:$L$1000)-ROW(TRANSACCIONES!$L$2)+1),44)),"")
A50: =IFERROR(INDEX(TRANSACCIONES!$A$2:$A$1000,SMALL(IF(UPPER(TRANSACCIONES!$L$2:$L$1000)="PENDIENTE",ROW(TRANSACCIONES!$L$2:$L$1000)-ROW(TRANSACCIONES!$L$2)+1),45)),"") | B50: =IFERROR(INDEX(TRANSACCIONES!$E$2:$E$1000,SMALL(IF(UPPER(TRANSACCIONES!$L$2:$L$1000)="PENDIENTE",ROW(TRANSACCIONES!$L$2:$L$1000)-ROW(TRANSACCIONES!$L$2)+1),45)),"") | C50: =IFERROR(INDEX(TRANSACCIONES!$F$2:$F$1000,SMALL(IF(UPPER(TRANSACCIONES!$L$2:$L$1000)="PENDIENTE",ROW(TRANSACCIONES!$L$2:$L$1000)-ROW(TRANSACCIONES!$L$2)+1),45)),"") | D50: =IFERROR(INDEX(TRANSACCIONES!$I$2:$I$1000,SMALL(IF(UPPER(TRANSACCIONES!$L$2:$L$1000)="PENDIENTE",ROW(TRANSACCIONES!$L$2:$L$1000)-ROW(TRANSACCIONES!$L$2)+1),45)),"") | E50: =IFERROR(INDEX(TRANSACCIONES!$N$2:$N$1000,SMALL(IF(UPPER(TRANSACCIONES!$L$2:$L$1000)="PENDIENTE",ROW(TRANSACCIONES!$L$2:$L$1000)-ROW(TRANSACCIONES!$L$2)+1),45)),"") | F50: =IF(A50="","",TODAY()-A50) | G50: =IF(A50="","",IF(E50<TODAY(),"VENCIDO",IF(E50<=TODAY()+7,"POR VENCER","AL DÍA"))) | H50: =IFERROR(INDEX(TRANSACCIONES!$K$2:$K$1000,SMALL(IF(UPPER(TRANSACCIONES!$L$2:$L$1000)="PENDIENTE",ROW(TRANSACCIONES!$L$2:$L$1000)-ROW(TRANSACCIONES!$L$2)+1),45)),"")
A51: =IFERROR(INDEX(TRANSACCIONES!$A$2:$A$1000,SMALL(IF(UPPER(TRANSACCIONES!$L$2:$L$1000)="PENDIENTE",ROW(TRANSACCIONES!$L$2:$L$1000)-ROW(TRANSACCIONES!$L$2)+1),46)),"") | B51: =IFERROR(INDEX(TRANSACCIONES!$E$2:$E$1000,SMALL(IF(UPPER(TRANSACCIONES!$L$2:$L$1000)="PENDIENTE",ROW(TRANSACCIONES!$L$2:$L$1000)-ROW(TRANSACCIONES!$L$2)+1),46)),"") | C51: =IFERROR(INDEX(TRANSACCIONES!$F$2:$F$1000,SMALL(IF(UPPER(TRANSACCIONES!$L$2:$L$1000)="PENDIENTE",ROW(TRANSACCIONES!$L$2:$L$1000)-ROW(TRANSACCIONES!$L$2)+1),46)),"") | D51: =IFERROR(INDEX(TRANSACCIONES!$I$2:$I$1000,SMALL(IF(UPPER(TRANSACCIONES!$L$2:$L$1000)="PENDIENTE",ROW(TRANSACCIONES!$L$2:$L$1000)-ROW(TRANSACCIONES!$L$2)+1),46)),"") | E51: =IFERROR(INDEX(TRANSACCIONES!$N$2:$N$1000,SMALL(IF(UPPER(TRANSACCIONES!$L$2:$L$1000)="PENDIENTE",ROW(TRANSACCIONES!$L$2:$L$1000)-ROW(TRANSACCIONES!$L$2)+1),46)),"") | F51: =IF(A51="","",TODAY()-A51) | G51: =IF(A51="","",IF(E51<TODAY(),"VENCIDO",IF(E51<=TODAY()+7,"POR VENCER","AL DÍA"))) | H51: =IFERROR(INDEX(TRANSACCIONES!$K$2:$K$1000,SMALL(IF(UPPER(TRANSACCIONES!$L$2:$L$1000)="PENDIENTE",ROW(TRANSACCIONES!$L$2:$L$1000)-ROW(TRANSACCIONES!$L$2)+1),46)),"")
A52: =IFERROR(INDEX(TRANSACCIONES!$A$2:$A$1000,SMALL(IF(UPPER(TRANSACCIONES!$L$2:$L$1000)="PENDIENTE",ROW(TRANSACCIONES!$L$2:$L$1000)-ROW(TRANSACCIONES!$L$2)+1),47)),"") | B52: =IFERROR(INDEX(TRANSACCIONES!$E$2:$E$1000,SMALL(IF(UPPER(TRANSACCIONES!$L$2:$L$1000)="PENDIENTE",ROW(TRANSACCIONES!$L$2:$L$1000)-ROW(TRANSACCIONES!$L$2)+1),47)),"") | C52: =IFERROR(INDEX(TRANSACCIONES!$F$2:$F$1000,SMALL(IF(UPPER(TRANSACCIONES!$L$2:$L$1000)="PENDIENTE",ROW(TRANSACCIONES!$L$2:$L$1000)-ROW(TRANSACCIONES!$L$2)+1),47)),"") | D52: =IFERROR(INDEX(TRANSACCIONES!$I$2:$I$1000,SMALL(IF(UPPER(TRANSACCIONES!$L$2:$L$1000)="PENDIENTE",ROW(TRANSACCIONES!$L$2:$L$1000)-ROW(TRANSACCIONES!$L$2)+1),47)),"") | E52: =IFERROR(INDEX(TRANSACCIONES!$N$2:$N$1000,SMALL(IF(UPPER(TRANSACCIONES!$L$2:$L$1000)="PENDIENTE",ROW(TRANSACCIONES!$L$2:$L$1000)-ROW(TRANSACCIONES!$L$2)+1),47)),"") | F52: =IF(A52="","",TODAY()-A52) | G52: =IF(A52="","",IF(E52<TODAY(),"VENCIDO",IF(E52<=TODAY()+7,"POR VENCER","AL DÍA"))) | H52: =IFERROR(INDEX(TRANSACCIONES!$K$2:$K$1000,SMALL(IF(UPPER(TRANSACCIONES!$L$2:$L$1000)="PENDIENTE",ROW(TRANSACCIONES!$L$2:$L$1000)-ROW(TRANSACCIONES!$L$2)+1),47)),"")
A53: =IFERROR(INDEX(TRANSACCIONES!$A$2:$A$1000,SMALL(IF(UPPER(TRANSACCIONES!$L$2:$L$1000)="PENDIENTE",ROW(TRANSACCIONES!$L$2:$L$1000)-ROW(TRANSACCIONES!$L$2)+1),48)),"") | B53: =IFERROR(INDEX(TRANSACCIONES!$E$2:$E$1000,SMALL(IF(UPPER(TRANSACCIONES!$L$2:$L$1000)="PENDIENTE",ROW(TRANSACCIONES!$L$2:$L$1000)-ROW(TRANSACCIONES!$L$2)+1),48)),"") | C53: =IFERROR(INDEX(TRANSACCIONES!$F$2:$F$1000,SMALL(IF(UPPER(TRANSACCIONES!$L$2:$L$1000)="PENDIENTE",ROW(TRANSACCIONES!$L$2:$L$1000)-ROW(TRANSACCIONES!$L$2)+1),48)),"") | D53: =IFERROR(INDEX(TRANSACCIONES!$I$2:$I$1000,SMALL(IF(UPPER(TRANSACCIONES!$L$2:$L$1000)="PENDIENTE",ROW(TRANSACCIONES!$L$2:$L$1000)-ROW(TRANSACCIONES!$L$2)+1),48)),"") | E53: =IFERROR(INDEX(TRANSACCIONES!$N$2:$N$1000,SMALL(IF(UPPER(TRANSACCIONES!$L$2:$L$1000)="PENDIENTE",ROW(TRANSACCIONES!$L$2:$L$1000)-ROW(TRANSACCIONES!$L$2)+1),48)),"") | F53: =IF(A53="","",TODAY()-A53) | G53: =IF(A53="","",IF(E53<TODAY(),"VENCIDO",IF(E53<=TODAY()+7,"POR VENCER","AL DÍA"))) | H53: =IFERROR(INDEX(TRANSACCIONES!$K$2:$K$1000,SMALL(IF(UPPER(TRANSACCIONES!$L$2:$L$1000)="PENDIENTE",ROW(TRANSACCIONES!$L$2:$L$1000)-ROW(TRANSACCIONES!$L$2)+1),48)),"")
A54: =IFERROR(INDEX(TRANSACCIONES!$A$2:$A$1000,SMALL(IF(UPPER(TRANSACCIONES!$L$2:$L$1000)="PENDIENTE",ROW(TRANSACCIONES!$L$2:$L$1000)-ROW(TRANSACCIONES!$L$2)+1),49)),"") | B54: =IFERROR(INDEX(TRANSACCIONES!$E$2:$E$1000,SMALL(IF(UPPER(TRANSACCIONES!$L$2:$L$1000)="PENDIENTE",ROW(TRANSACCIONES!$L$2:$L$1000)-ROW(TRANSACCIONES!$L$2)+1),49)),"") | C54: =IFERROR(INDEX(TRANSACCIONES!$F$2:$F$1000,SMALL(IF(UPPER(TRANSACCIONES!$L$2:$L$1000)="PENDIENTE",ROW(TRANSACCIONES!$L$2:$L$1000)-ROW(TRANSACCIONES!$L$2)+1),49)),"") | D54: =IFERROR(INDEX(TRANSACCIONES!$I$2:$I$1000,SMALL(IF(UPPER(TRANSACCIONES!$L$2:$L$1000)="PENDIENTE",ROW(TRANSACCIONES!$L$2:$L$1000)-ROW(TRANSACCIONES!$L$2)+1),49)),"") | E54: =IFERROR(INDEX(TRANSACCIONES!$N$2:$N$1000,SMALL(IF(UPPER(TRANSACCIONES!$L$2:$L$1000)="PENDIENTE",ROW(TRANSACCIONES!$L$2:$L$1000)-ROW(TRANSACCIONES!$L$2)+1),49)),"") | F54: =IF(A54="","",TODAY()-A54) | G54: =IF(A54="","",IF(E54<TODAY(),"VENCIDO",IF(E54<=TODAY()+7,"POR VENCER","AL DÍA"))) | H54: =IFERROR(INDEX(TRANSACCIONES!$K$2:$K$1000,SMALL(IF(UPPER(TRANSACCIONES!$L$2:$L$1000)="PENDIENTE",ROW(TRANSACCIONES!$L$2:$L$1000)-ROW(TRANSACCIONES!$L$2)+1),49)),"")
A55: =IFERROR(INDEX(TRANSACCIONES!$A$2:$A$1000,SMALL(IF(UPPER(TRANSACCIONES!$L$2:$L$1000)="PENDIENTE",ROW(TRANSACCIONES!$L$2:$L$1000)-ROW(TRANSACCIONES!$L$2)+1),50)),"") | B55: =IFERROR(INDEX(TRANSACCIONES!$E$2:$E$1000,SMALL(IF(UPPER(TRANSACCIONES!$L$2:$L$1000)="PENDIENTE",ROW(TRANSACCIONES!$L$2:$L$1000)-ROW(TRANSACCIONES!$L$2)+1),50)),"") | C55: =IFERROR(INDEX(TRANSACCIONES!$F$2:$F$1000,SMALL(IF(UPPER(TRANSACCIONES!$L$2:$L$1000)="PENDIENTE",ROW(TRANSACCIONES!$L$2:$L$1000)-ROW(TRANSACCIONES!$L$2)+1),50)),"") | D55: =IFERROR(INDEX(TRANSACCIONES!$I$2:$I$1000,SMALL(IF(UPPER(TRANSACCIONES!$L$2:$L$1000)="PENDIENTE",ROW(TRANSACCIONES!$L$2:$L$1000)-ROW(TRANSACCIONES!$L$2)+1),50)),"") | E55: =IFERROR(INDEX(TRANSACCIONES!$N$2:$N$1000,SMALL(IF(UPPER(TRANSACCIONES!$L$2:$L$1000)="PENDIENTE",ROW(TRANSACCIONES!$L$2:$L$1000)-ROW(TRANSACCIONES!$L$2)+1),50)),"") | F55: =IF(A55="","",TODAY()-A55) | G55: =IF(A55="","",IF(E55<TODAY(),"VENCIDO",IF(E55<=TODAY()+7,"POR VENCER","AL DÍA"))) | H55: =IFERROR(INDEX(TRANSACCIONES!$K$2:$K$1000,SMALL(IF(UPPER(TRANSACCIONES!$L$2:$L$1000)="PENDIENTE",ROW(TRANSACCIONES!$L$2:$L$1000)-ROW(TRANSACCIONES!$L$2)+1),50)),"")

Sheet CxC
A1: 💵 CUENTAS POR COBRAR
A3: Total por Cobrar: | B3: =SUM(D6:D55)
A5: Fecha | B5: Descripción | C5: Cliente | D5: Monto | E5: Fecha Vencimiento | F5: Días Pendientes | G5: Estado | H5: Notas
A6: =IFERROR(INDEX(TRANSACCIONES!$A$2:$A$1000,SMALL(IF(UPPER(TRANSACCIONES!$L$2:$L$1000)="POR COBRAR",ROW(TRANSACCIONES!$L$2:$L$1000)-ROW(TRANSACCIONES!$L$2)+1),1)),"") | B6: =IFERROR(INDEX(TRANSACCIONES!$E$2:$E$1000,SMALL(IF(UPPER(TRANSACCIONES!$L$2:$L$1000)="POR COBRAR",ROW(TRANSACCIONES!$L$2:$L$1000)-ROW(TRANSACCIONES!$L$2)+1),1)),"") | C6: =IFERROR(INDEX(TRANSACCIONES!$F$2:$F$1000,SMALL(IF(UPPER(TRANSACCIONES!$L$2:$L$1000)="POR COBRAR",ROW(TRANSACCIONES!$L$2:$L$1000)-ROW(TRANSACCIONES!$L$2)+1),1)),"") | D6: =IFERROR(INDEX(TRANSACCIONES!$I$2:$I$1000,SMALL(IF(UPPER(TRANSACCIONES!$L$2:$L$1000)="POR COBRAR",ROW(TRANSACCIONES!$L$2:$L$1000)-ROW(TRANSACCIONES!$L$2)+1),1)),"") | E6: =IFERROR(INDEX(TRANSACCIONES!$N$2:$N$1000,SMALL(IF(UPPER(TRANSACCIONES!$L$2:$L$1000)="POR COBRAR",ROW(TRANSACCIONES!$L$2:$L$1000)-ROW(TRANSACCIONES!$L$2)+1),1)),"") | F6: =IF(A6="","",TODAY()-A6) | G6: =IF(A6="","",IF(E6<TODAY(),"VENCIDO",IF(E6<=TODAY()+7,"POR VENCER","AL DÍA"))) | H6: =IFERROR(INDEX(TRANSACCIONES!$K$2:$K$1000,SMALL(IF(UPPER(TRANSACCIONES!$L$2:$L$1000)="POR COBRAR",ROW(TRANSACCIONES!$L$2:$L$1000)-ROW(TRANSACCIONES!$L$2)+1),1)),"")
A7: =IFERROR(INDEX(TRANSACCIONES!$A$2:$A$1000,SMALL(IF(UPPER(TRANSACCIONES!$L$2:$L$1000)="POR COBRAR",ROW(TRANSACCIONES!$L$2:$L$1000)-ROW(TRANSACCIONES!$L$2)+1),2)),"") | B7: =IFERROR(INDEX(TRANSACCIONES!$E$2:$E$1000,SMALL(IF(UPPER(TRANSACCIONES!$L$2:$L$1000)="POR COBRAR",ROW(TRANSACCIONES!$L$2:$L$1000)-ROW(TRANSACCIONES!$L$2)+1),2)),"") | C7: =IFERROR(INDEX(TRANSACCIONES!$F$2:$F$1000,SMALL(IF(UPPER(TRANSACCIONES!$L$2:$L$1000)="POR COBRAR",ROW(TRANSACCIONES!$L$2:$L$1000)-ROW(TRANSACCIONES!$L$2)+1),2)),"") | D7: =IFERROR(INDEX(TRANSACCIONES!$I$2:$I$1000,SMALL(IF(UPPER(TRANSACCIONES!$L$2:$L$1000)="POR COBRAR",ROW(TRANSACCIONES!$L$2:$L$1000)-ROW(TRANSACCIONES!$L$2)+1),2)),"") | E7: =IFERROR(INDEX(TRANSACCIONES!$N$2:$N$1000,SMALL(IF(UPPER(TRANSACCIONES!$L$2:$L$1000)="POR COBRAR",ROW(TRANSACCIONES!$L$2:$L$1000)-ROW(TRANSACCIONES!$L$2)+1),2)),"") | F7: =IF(A7="","",TODAY()-A7) | G7: =IF(A7="","",IF(E7<TODAY(),"VENCIDO",IF(E7<=TODAY()+7,"POR VENCER","AL DÍA"))) | H7: =IFERROR(INDEX(TRANSACCIONES!$K$2:$K$1000,SMALL(IF(UPPER(TRANSACCIONES!$L$2:$L$1000)="POR COBRAR",ROW(TRANSACCIONES!$L$2:$L$1000)-ROW(TRANSACCIONES!$L$2)+1),2)),"")
A8: =IFERROR(INDEX(TRANSACCIONES!$A$2:$A$1000,SMALL(IF(UPPER(TRANSACCIONES!$L$2:$L$1000)="POR COBRAR",ROW(TRANSACCIONES!$L$2:$L$1000)-ROW(TRANSACCIONES!$L$2)+1),3)),"") | B8: =IFERROR(INDEX(TRANSACCIONES!$E$2:$E$1000,SMALL(IF(UPPER(TRANSACCIONES!$L$2:$L$1000)="POR COBRAR",ROW(TRANSACCIONES!$L$2:$L$1000)-ROW(TRANSACCIONES!$L$2)+1),3)),"") | C8: =IFERROR(INDEX(TRANSACCIONES!$F$2:$F$1000,SMALL(IF(UPPER(TRANSACCIONES!$L$2:$L$1000)="POR COBRAR",ROW(TRANSACCIONES!$L$2:$L$1000)-ROW(TRANSACCIONES!$L$2)+1),3)),"") | D8: =IFERROR(INDEX(TRANSACCIONES!$I$2:$I$1000,SMALL(IF(UPPER(TRANSACCIONES!$L$2:$L$1000)="POR COBRAR",ROW(TRANSACCIONES!$L$2:$L$1000)-ROW(TRANSACCIONES!$L$2)+1),3)),"") | E8: =IFERROR(INDEX(TRANSACCIONES!$N$2:$N$1000,SMALL(IF(UPPER(TRANSACCIONES!$L$2:$L$1000)="POR COBRAR",ROW(TRANSACCIONES!$L$2:$L$1000)-ROW(TRANSACCIONES!$L$2)+1),3)),"") | F8: =IF(A8="","",TODAY()-A8) | G8: =IF(A8="","",IF(E8<TODAY(),"VENCIDO",IF(E8<=TODAY()+7,"POR VENCER","AL DÍA"))) | H8: =IFERROR(INDEX(TRANSACCIONES!$K$2:$K$1000,SMALL(IF(UPPER(TRANSACCIONES!$L$2:$L$1000)="POR COBRAR",ROW(TRANSACCIONES!$L$2:$L$1000)-ROW(TRANSACCIONES!$L$2)+1),3)),"")
A9: =IFERROR(INDEX(TRANSACCIONES!$A$2:$A$1000,SMALL(IF(UPPER(TRANSACCIONES!$L$2:$L$1000)="POR COBRAR",ROW(TRANSACCIONES!$L$2:$L$1000)-ROW(TRANSACCIONES!$L$2)+1),4)),"") | B9: =IFERROR(INDEX(TRANSACCIONES!$E$2:$E$1000,SMALL(IF(UPPER(TRANSACCIONES!$L$2:$L$1000)="POR COBRAR",ROW(TRANSACCIONES!$L$2:$L$1000)-ROW(TRANSACCIONES!$L$2)+1),4)),"") | C9: =IFERROR(INDEX(TRANSACCIONES!$F$2:$F$1000,SMALL(IF(UPPER(TRANSACCIONES!$L$2:$L$1000)="POR COBRAR",ROW(TRANSACCIONES!$L$2:$L$1000)-ROW(TRANSACCIONES!$L$2)+1),4)),"") | D9: =IFERROR(INDEX(TRANSACCIONES!$I$2:$I$1000,SMALL(IF(UPPER(TRANSACCIONES!$L$2:$L$1000)="POR COBRAR",ROW(TRANSACCIONES!$L$2:$L$1000)-ROW(TRANSACCIONES!$L$2)+1),4)),"") | E9: =IFERROR(INDEX(TRANSACCIONES!$N$2:$N$1000,SMALL(IF(UPPER(TRANSACCIONES!$L$2:$L$1000)="POR COBRAR",ROW(TRANSACCIONES!$L$2:$L$1000)-ROW(TRANSACCIONES!$L$2)+1),4)),"") | F9: =IF(A9="","",TODAY()-A9) | G9: =IF(A9="","",IF(E9<TODAY(),"VENCIDO",IF(E9<=TODAY()+7,"POR VENCER","AL DÍA"))) | H9: =IFERROR(INDEX(TRANSACCIONES!$K$2:$K$1000,SMALL(IF(UPPER(TRANSACCIONES!$L$2:$L$1000)="POR COBRAR",ROW(TRANSACCIONES!$L$2:$L$1000)-ROW(TRANSACCIONES!$L$2)+1),4)),"")
A10: =IFERROR(INDEX(TRANSACCIONES!$A$2:$A$1000,SMALL(IF(UPPER(TRANSACCIONES!$L$2:$L$1000)="POR COBRAR",ROW(TRANSACCIONES!$L$2:$L$1000)-ROW(TRANSACCIONES!$L$2)+1),5)),"") | B10: =IFERROR(INDEX(TRANSACCIONES!$E$2:$E$1000,SMALL(IF(UPPER(TRANSACCIONES!$L$2:$L$1000)="POR COBRAR",ROW(TRANSACCIONES!$L$2:$L$1000)-ROW(TRANSACCIONES!$L$2)+1),5)),"") | C10: =IFERROR(INDEX(TRANSACCIONES!$F$2:$F$1000,SMALL(IF(UPPER(TRANSACCIONES!$L$2:$L$1000)="POR COBRAR",ROW(TRANSACCIONES!$L$2:$L$1000)-ROW(TRANSACCIONES!$L$2)+1),5)),"") | D10: =IFERROR(INDEX(TRANSACCIONES!$I$2:$I$1000,SMALL(IF(UPPER(TRANSACCIONES!$L$2:$L$1000)="POR COBRAR",ROW(TRANSACCIONES!$L$2:$L$1000)-ROW(TRANSACCIONES!$L$2)+1),5)),"") | E10: =IFERROR(INDEX(TRANSACCIONES!$N$2:$N$1000,SMALL(IF(UPPER(TRANSACCIONES!$L$2:$L$1000)="POR COBRAR",ROW(TRANSACCIONES!$L$2:$L$1000)-ROW(TRANSACCIONES!$L$2)+1),5)),"") | F10: =IF(A10="","",TODAY()-A10) | G10: =IF(A10="","",IF(E10<TODAY(),"VENCIDO",IF(E10<=TODAY()+7,"POR VENCER","AL DÍA"))) | H10: =IFERROR(INDEX(TRANSACCIONES!$K$2:$K$1000,SMALL(IF(UPPER(TRANSACCIONES!$L$2:$L$1000)="POR COBRAR",ROW(TRANSACCIONES!$L$2:$L$1000)-ROW(TRANSACCIONES!$L$2)+1),5)),"")
A11: =IFERROR(INDEX(TRANSACCIONES!$A$2:$A$1000,SMALL(IF(UPPER(TRANSACCIONES!$L$2:$L$1000)="POR COBRAR",ROW(TRANSACCIONES!$L$2:$L$1000)-ROW(TRANSACCIONES!$L$2)+1),6)),"") | B11: =IFERROR(INDEX(TRANSACCIONES!$E$2:$E$1000,SMALL(IF(UPPER(TRANSACCIONES!$L$2:$L$1000)="POR COBRAR",ROW(TRANSACCIONES!$L$2:$L$1000)-ROW(TRANSACCIONES!$L$2)+1),6)),"") | C11: =IFERROR(INDEX(TRANSACCIONES!$F$2:$F$1000,SMALL(IF(UPPER(TRANSACCIONES!$L$2:$L$1000)="POR COBRAR",ROW(TRANSACCIONES!$L$2:$L$1000)-ROW(TRANSACCIONES!$L$2)+1),6)),"") | D11: =IFERROR(INDEX(TRANSACCIONES!$I$2:$I$1000,SMALL(IF(UPPER(TRANSACCIONES!$L$2:$L$1000)="POR COBRAR",ROW(TRANSACCIONES!$L$2:$L$1000)-ROW(TRANSACCIONES!$L$2)+1),6)),"") | E11: =IFERROR(INDEX(TRANSACCIONES!$N$2:$N$1000,SMALL(IF(UPPER(TRANSACCIONES!$L$2:$L$1000)="POR COBRAR",ROW(TRANSACCIONES!$L$2:$L$1000)-ROW(TRANSACCIONES!$L$2)+1),6)),"") | F11: =IF(A11="","",TODAY()-A11) | G11: =IF(A11="","",IF(E11<TODAY(),"VENCIDO",IF(E11<=TODAY()+7,"POR VENCER","AL DÍA"))) | H11: =IFERROR(INDEX(TRANSACCIONES!$K$2:$K$1000,SMALL(IF(UPPER(TRANSACCIONES!$L$2:$L$1000)="POR COBRAR",ROW(TRANSACCIONES!$L$2:$L$1000)-ROW(TRANSACCIONES!$L$2)+1),6)),"")
A12: =IFERROR(INDEX(TRANSACCIONES!$A$2:$A$1000,SMALL(IF(UPPER(TRANSACCIONES!$L$2:$L$1000)="POR COBRAR",ROW(TRANSACCIONES!$L$2:$L$1000)-ROW(TRANSACCIONES!$L$2)+1),7)),"") | B12: =IFERROR(INDEX(TRANSACCIONES!$E$2:$E$1000,SMALL(IF(UPPER(TRANSACCIONES!$L$2:$L$1000)="POR COBRAR",ROW(TRANSACCIONES!$L$2:$L$1000)-ROW(TRANSACCIONES!$L$2)+1),7)),"") | C12: =IFERROR(INDEX(TRANSACCIONES!$F$2:$F$1000,SMALL(IF(UPPER(TRANSACCIONES!$L$2:$L$1000)="POR COBRAR",ROW(TRANSACCIONES!$L$2:$L$1000)-ROW(TRANSACCIONES!$L$2)+1),7)),"") | D12: =IFERROR(INDEX(TRANSACCIONES!$I$2:$I$1000,SMALL(IF(UPPER(TRANSACCIONES!$L$2:$L$1000)="POR COBRAR",ROW(TRANSACCIONES!$L$2:$L$1000)-ROW(TRANSACCIONES!$L$2)+1),7)),"") | E12: =IFERROR(INDEX(TRANSACCIONES!$N$2:$N$1000,SMALL(IF(UPPER(TRANSACCIONES!$L$2:$L$1000)="POR COBRAR",ROW(TRANSACCIONES!$L$2:$L$1000)-ROW(TRANSACCIONES!$L$2)+1),7)),"") | F12: =IF(A12="","",TODAY()-A12) | G12: =IF(A12="","",IF(E12<TODAY(),"VENCIDO",IF(E12<=TODAY()+7,"POR VENCER","AL DÍA"))) | H12: =IFERROR(INDEX(TRANSACCIONES!$K$2:$K$1000,SMALL(IF(UPPER(TRANSACCIONES!$L$2:$L$1000)="POR COBRAR",ROW(TRANSACCIONES!$L$2:$L$1000)-ROW(TRANSACCIONES!$L$2)+1),7)),"")
A13: =IFERROR(INDEX(TRANSACCIONES!$A$2:$A$1000,SMALL(IF(UPPER(TRANSACCIONES!$L$2:$L$1000)="POR COBRAR",ROW(TRANSACCIONES!$L$2:$L$1000)-ROW(TRANSACCIONES!$L$2)+1),8)),"") | B13: =IFERROR(INDEX(TRANSACCIONES!$E$2:$E$1000,SMALL(IF(UPPER(TRANSACCIONES!$L$2:$L$1000)="POR COBRAR",ROW(TRANSACCIONES!$L$2:$L$1000)-ROW(TRANSACCIONES!$L$2)+1),8)),"") | C13: =IFERROR(INDEX(TRANSACCIONES!$F$2:$F$1000,SMALL(IF(UPPER(TRANSACCIONES!$L$2:$L$1000)="POR COBRAR",ROW(TRANSACCIONES!$L$2:$L$1000)-ROW(TRANSACCIONES!$L$2)+1),8)),"") | D13: =IFERROR(INDEX(TRANSACCIONES!$I$2:$I$1000,SMALL(IF(UPPER(TRANSACCIONES!$L$2:$L$1000)="POR COBRAR",ROW(TRANSACCIONES!$L$2:$L$1000)-ROW(TRANSACCIONES!$L$2)+1),8)),"") | E13: =IFERROR(INDEX(TRANSACCIONES!$N$2:$N$1000,SMALL(IF(UPPER(TRANSACCIONES!$L$2:$L$1000)="POR COBRAR",ROW(TRANSACCIONES!$L$2:$L$1000)-ROW(TRANSACCIONES!$L$2)+1),8)),"") | F13: =IF(A13="","",TODAY()-A13) | G13: =IF(A13="","",IF(E13<TODAY(),"VENCIDO",IF(E13<=TODAY()+7,"POR VENCER","AL DÍA"))) | H13: =IFERROR(INDEX(TRANSACCIONES!$K$2:$K$1000,SMALL(IF(UPPER(TRANSACCIONES!$L$2:$L$1000)="POR COBRAR",ROW(TRANSACCIONES!$L$2:$L$1000)-ROW(TRANSACCIONES!$L$2)+1),8)),"")
A14: =IFERROR(INDEX(TRANSACCIONES!$A$2:$A$1000,SMALL(IF(UPPER(TRANSACCIONES!$L$2:$L$1000)="POR COBRAR",ROW(TRANSACCIONES!$L$2:$L$1000)-ROW(TRANSACCIONES!$L$2)+1),9)),"") | B14: =IFERROR(INDEX(TRANSACCIONES!$E$2:$E$1000,SMALL(IF(UPPER(TRANSACCIONES!$L$2:$L$1000)="POR COBRAR",ROW(TRANSACCIONES!$L$2:$L$1000)-ROW(TRANSACCIONES!$L$2)+1),9)),"") | C14: =IFERROR(INDEX(TRANSACCIONES!$F$2:$F$1000,SMALL(IF(UPPER(TRANSACCIONES!$L$2:$L$1000)="POR COBRAR",ROW(TRANSACCIONES!$L$2:$L$1000)-ROW(TRANSACCIONES!$L$2)+1),9)),"") | D14: =IFERROR(INDEX(TRANSACCIONES!$I$2:$I$1000,SMALL(IF(UPPER(TRANSACCIONES!$L$2:$L$1000)="POR COBRAR",ROW(TRANSACCIONES!$L$2:$L$1000)-ROW(TRANSACCIONES!$L$2)+1),9)),"") | E14: =IFERROR(INDEX(TRANSACCIONES!$N$2:$N$1000,SMALL(IF(UPPER(TRANSACCIONES!$L$2:$L$1000)="POR COBRAR",ROW(TRANSACCIONES!$L$2:$L$1000)-ROW(TRANSACCIONES!$L$2)+1),9)),"") | F14: =IF(A14="","",TODAY()-A14) | G14: =IF(A14="","",IF(E14<TODAY(),"VENCIDO",IF(E14<=TODAY()+7,"POR VENCER","AL DÍA"))) | H14: =IFERROR(INDEX(TRANSACCIONES!$K$2:$K$1000,SMALL(IF(UPPER(TRANSACCIONES!$L$2:$L$1000)="POR COBRAR",ROW(TRANSACCIONES!$L$2:$L$1000)-ROW(TRANSACCIONES!$L$2)+1),9)),"")
A15: =IFERROR(INDEX(TRANSACCIONES!$A$2:$A$1000,SMALL(IF(UPPER(TRANSACCIONES!$L$2:$L$1000)="POR COBRAR",ROW(TRANSACCIONES!$L$2:$L$1000)-ROW(TRANSACCIONES!$L$2)+1),10)),"") | B15: =IFERROR(INDEX(TRANSACCIONES!$E$2:$E$1000,SMALL(IF(UPPER(TRANSACCIONES!$L$2:$L$1000)="POR COBRAR",ROW(TRANSACCIONES!$L$2:$L$1000)-ROW(TRANSACCIONES!$L$2)+1),10)),"") | C15: =IFERROR(INDEX(TRANSACCIONES!$F$2:$F$1000,SMALL(IF(UPPER(TRANSACCIONES!$L$2:$L$1000)="POR COBRAR",ROW(TRANSACCIONES!$L$2:$L$1000)-ROW(TRANSACCIONES!$L$2)+1),10)),"") | D15: =IFERROR(INDEX(TRANSACCIONES!$I$2:$I$1000,SMALL(IF(UPPER(TRANSACCIONES!$L$2:$L$1000)="POR COBRAR",ROW(TRANSACCIONES!$L$2:$L$1000)-ROW(TRANSACCIONES!$L$2)+1),10)),"") | E15: =IFERROR(INDEX(TRANSACCIONES!$N$2:$N$1000,SMALL(IF(UPPER(TRANSACCIONES!$L$2:$L$1000)="POR COBRAR",ROW(TRANSACCIONES!$L$2:$L$1000)-ROW(TRANSACCIONES!$L$2)+1),10)),"") | F15: =IF(A15="","",TODAY()-A15) | G15: =IF(A15="","",IF(E15<TODAY(),"VENCIDO",IF(E15<=TODAY()+7,"POR VENCER","AL DÍA"))) | H15: =IFERROR(INDEX(TRANSACCIONES!$K$2:$K$1000,SMALL(IF(UPPER(TRANSACCIONES!$L$2:$L$1000)="POR COBRAR",ROW(TRANSACCIONES!$L$2:$L$1000)-ROW(TRANSACCIONES!$L$2)+1),10)),"")
A16: =IFERROR(INDEX(TRANSACCIONES!$A$2:$A$1000,SMALL(IF(UPPER(TRANSACCIONES!$L$2:$L$1000)="POR COBRAR",ROW(TRANSACCIONES!$L$2:$L$1000)-ROW(TRANSACCIONES!$L$2)+1),11)),"") | B16: =IFERROR(INDEX(TRANSACCIONES!$E$2:$E$1000,SMALL(IF(UPPER(TRANSACCIONES!$L$2:$L$1000)="POR COBRAR",ROW(TRANSACCIONES!$L$2:$L$1000)-ROW(TRANSACCIONES!$L$2)+1),11)),"") | C16: =IFERROR(INDEX(TRANSACCIONES!$F$2:$F$1000,SMALL(IF(UPPER(TRANSACCIONES!$L$2:$L$1000)="POR COBRAR",ROW(TRANSACCIONES!$L$2:$L$1000)-ROW(TRANSACCIONES!$L$2)+1),11)),"") | D16: =IFERROR(INDEX(TRANSACCIONES!$I$2:$I$1000,SMALL(IF(UPPER(TRANSACCIONES!$L$2:$L$1000)="POR COBRAR",ROW(TRANSACCIONES!$L$2:$L$1000)-ROW(TRANSACCIONES!$L$2)+1),11)),"") | E16: =IFERROR(INDEX(TRANSACCIONES!$N$2:$N$1000,SMALL(IF(UPPER(TRANSACCIONES!$L$2:$L$1000)="POR COBRAR",ROW(TRANSACCIONES!$L$2:$L$1000)-ROW(TRANSACCIONES!$L$2)+1),11)),"") | F16: =IF(A16="","",TODAY()-A16) | G16: =IF(A16="","",IF(E16<TODAY(),"VENCIDO",IF(E16<=TODAY()+7,"POR VENCER","AL DÍA"))) | H16: =IFERROR(INDEX(TRANSACCIONES!$K$2:$K$1000,SMALL(IF(UPPER(TRANSACCIONES!$L$2:$L$1000)="POR COBRAR",ROW(TRANSACCIONES!$L$2:$L$1000)-ROW(TRANSACCIONES!$L$2)+1),11)),"")
A17: =IFERROR(INDEX(TRANSACCIONES!$A$2:$A$1000,SMALL(IF(UPPER(TRANSACCIONES!$L$2:$L$1000)="POR COBRAR",ROW(TRANSACCIONES!$L$2:$L$1000)-ROW(TRANSACCIONES!$L$2)+1),12)),"") | B17: =IFERROR(INDEX(TRANSACCIONES!$E$2:$E$1000,SMALL(IF(UPPER(TRANSACCIONES!$L$2:$L$1000)="POR COBRAR",ROW(TRANSACCIONES!$L$2:$L$1000)-ROW(TRANSACCIONES!$L$2)+1),12)),"") | C17: =IFERROR(INDEX(TRANSACCIONES!$F$2:$F$1000,SMALL(IF(UPPER(TRANSACCIONES!$L$2:$L$1000)="POR COBRAR",ROW(TRANSACCIONES!$L$2:$L$1000)-ROW(TRANSACCIONES!$L$2)+1),12)),"") | D17: =IFERROR(INDEX(TRANSACCIONES!$I$2:$I$1000,SMALL(IF(UPPER(TRANSACCIONES!$L$2:$L$1000)="POR COBRAR",ROW(TRANSACCIONES!$L$2:$L$1000)-ROW(TRANSACCIONES!$L$2)+1),12)),"") | E17: =IFERROR(INDEX(TRANSACCIONES!$N$2:$N$1000,SMALL(IF(UPPER(TRANSACCIONES!$L$2:$L$1000)="POR COBRAR",ROW(TRANSACCIONES!$L$2:$L$1000)-ROW(TRANSACCIONES!$L$2)+1),12)),"") | F17: =IF(A17="","",TODAY()-A17) | G17: =IF(A17="","",IF(E17<TODAY(),"VENCIDO",IF(E17<=TODAY()+7,"POR VENCER","AL DÍA"))) | H17: =IFERROR(INDEX(TRANSACCIONES!$K$2:$K$1000,SMALL(IF(UPPER(TRANSACCIONES!$L$2:$L$1000)="POR COBRAR",ROW(TRANSACCIONES!$L$2:$L$1000)-ROW(TRANSACCIONES!$L$2)+1),12)),"")
A18: =IFERROR(INDEX(TRANSACCIONES!$A$2:$A$1000,SMALL(IF(UPPER(TRANSACCIONES!$L$2:$L$1000)="POR COBRAR",ROW(TRANSACCIONES!$L$2:$L$1000)-ROW(TRANSACCIONES!$L$2)+1),13)),"") | B18: =IFERROR(INDEX(TRANSACCIONES!$E$2:$E$1000,SMALL(IF(UPPER(TRANSACCIONES!$L$2:$L$1000)="POR COBRAR",ROW(TRANSACCIONES!$L$2:$L$1000)-ROW(TRANSACCIONES!$L$2)+1),13)),"") | C18: =IFERROR(INDEX(TRANSACCIONES!$F$2:$F$1000,SMALL(IF(UPPER(TRANSACCIONES!$L$2:$L$1000)="POR COBRAR",ROW(TRANSACCIONES!$L$2:$L$1000)-ROW(TRANSACCIONES!$L$2)+1),13)),"") | D18: =IFERROR(INDEX(TRANSACCIONES!$I$2:$I$1000,SMALL(IF(UPPER(TRANSACCIONES!$L$2:$L$1000)="POR COBRAR",ROW(TRANSACCIONES!$L$2:$L$1000)-ROW(TRANSACCIONES!$L$2)+1),13)),"") | E18: =IFERROR(INDEX(TRANSACCIONES!$N$2:$N$1000,SMALL(IF(UPPER(TRANSACCIONES!$L$2:$L$1000)="POR COBRAR",ROW(TRANSACCIONES!$L$2:$L$1000)-ROW(TRANSACCIONES!$L$2)+1),13)),"") | F18: =IF(A18="","",TODAY()-A18) | G18: =IF(A18="","",IF(E18<TODAY(),"VENCIDO",IF(E18<=TODAY()+7,"POR VENCER","AL DÍA"))) | H18: =IFERROR(INDEX(TRANSACCIONES!$K$2:$K$1000,SMALL(IF(UPPER(TRANSACCIONES!$L$2:$L$1000)="POR COBRAR",ROW(TRANSACCIONES!$L$2:$L$1000)-ROW(TRANSACCIONES!$L$2)+1),13)),"")
A19: =IFERROR(INDEX(TRANSACCIONES!$A$2:$A$1000,SMALL(IF(UPPER(TRANSACCIONES!$L$2:$L$1000)="POR COBRAR",ROW(TRANSACCIONES!$L$2:$L$1000)-ROW(TRANSACCIONES!$L$2)+1),14)),"") | B19: =IFERROR(INDEX(TRANSACCIONES!$E$2:$E$1000,SMALL(IF(UPPER(TRANSACCIONES!$L$2:$L$1000)="POR COBRAR",ROW(TRANSACCIONES!$L$2:$L$1000)-ROW(TRANSACCIONES!$L$2)+1),14)),"") | C19: =IFERROR(INDEX(TRANSACCIONES!$F$2:$F$1000,SMALL(IF(UPPER(TRANSACCIONES!$L$2:$L$1000)="POR COBRAR",ROW(TRANSACCIONES!$L$2:$L$1000)-ROW(TRANSACCIONES!$L$2)+1),14)),"") | D19: =IFERROR(INDEX(TRANSACCIONES!$I$2:$I$1000,SMALL(IF(UPPER(TRANSACCIONES!$L$2:$L$1000)="POR COBRAR",ROW(TRANSACCIONES!$L$2:$L$1000)-ROW(TRANSACCIONES!$L$2)+1),14)),"") | E19: =IFERROR(INDEX(TRANSACCIONES!$N$2:$N$1000,SMALL(IF(UPPER(TRANSACCIONES!$L$2:$L$1000)="POR COBRAR",ROW(TRANSACCIONES!$L$2:$L$1000)-ROW(TRANSACCIONES!$L$2)+1),14)),"") | F19: =IF(A19="","",TODAY()-A19) | G19: =IF(A19="","",IF(E19<TODAY(),"VENCIDO",IF(E19<=TODAY()+7,"POR VENCER","AL DÍA"))) | H19: =IFERROR(INDEX(TRANSACCIONES!$K$2:$K$1000,SMALL(IF(UPPER(TRANSACCIONES!$L$2:$L$1000)="POR COBRAR",ROW(TRANSACCIONES!$L$2:$L$1000)-ROW(TRANSACCIONES!$L$2)+1),14)),"")
A20: =IFERROR(INDEX(TRANSACCIONES!$A$2:$A$1000,SMALL(IF(UPPER(TRANSACCIONES!$L$2:$L$1000)="POR COBRAR",ROW(TRANSACCIONES!$L$2:$L$1000)-ROW(TRANSACCIONES!$L$2)+1),15)),"") | B20: =IFERROR(INDEX(TRANSACCIONES!$E$2:$E$1000,SMALL(IF(UPPER(TRANSACCIONES!$L$2:$L$1000)="POR COBRAR",ROW(TRANSACCIONES!$L$2:$L$1000)-ROW(TRANSACCIONES!$L$2)+1),15)),"") | C20: =IFERROR(INDEX(TRANSACCIONES!$F$2:$F$1000,SMALL(IF(UPPER(TRANSACCIONES!$L$2:$L$1000)="POR COBRAR",ROW(TRANSACCIONES!$L$2:$L$1000)-ROW(TRANSACCIONES!$L$2)+1),15)),"") | D20: =IFERROR(INDEX(TRANSACCIONES!$I$2:$I$1000,SMALL(IF(UPPER(TRANSACCIONES!$L$2:$L$1000)="POR COBRAR",ROW(TRANSACCIONES!$L$2:$L$1000)-ROW(TRANSACCIONES!$L$2)+1),15)),"") | E20: =IFERROR(INDEX(TRANSACCIONES!$N$2:$N$1000,SMALL(IF(UPPER(TRANSACCIONES!$L$2:$L$1000)="POR COBRAR",ROW(TRANSACCIONES!$L$2:$L$1000)-ROW(TRANSACCIONES!$L$2)+1),15)),"") | F20: =IF(A20="","",TODAY()-A20) | G20: =IF(A20="","",IF(E20<TODAY(),"VENCIDO",IF(E20<=TODAY()+7,"POR VENCER","AL DÍA"))) | H20: =IFERROR(INDEX(TRANSACCIONES!$K$2:$K$1000,SMALL(IF(UPPER(TRANSACCIONES!$L$2:$L$1000)="POR COBRAR",ROW(TRANSACCIONES!$L$2:$L$1000)-ROW(TRANSACCIONES!$L$2)+1),15)),"")
A21: =IFERROR(INDEX(TRANSACCIONES!$A$2:$A$1000,SMALL(IF(UPPER(TRANSACCIONES!$L$2:$L$1000)="POR COBRAR",ROW(TRANSACCIONES!$L$2:$L$1000)-ROW(TRANSACCIONES!$L$2)+1),16)),"") | B21: =IFERROR(INDEX(TRANSACCIONES!$E$2:$E$1000,SMALL(IF(UPPER(TRANSACCIONES!$L$2:$L$1000)="POR COBRAR",ROW(TRANSACCIONES!$L$2:$L$1000)-ROW(TRANSACCIONES!$L$2)+1),16)),"") | C21: =IFERROR(INDEX(TRANSACCIONES!$F$2:$F$1000,SMALL(IF(UPPER(TRANSACCIONES!$L$2:$L$1000)="POR COBRAR",ROW(TRANSACCIONES!$L$2:$L$1000)-ROW(TRANSACCIONES!$L$2)+1),16)),"") | D21: =IFERROR(INDEX(TRANSACCIONES!$I$2:$I$1000,SMALL(IF(UPPER(TRANSACCIONES!$L$2:$L$1000)="POR COBRAR",ROW(TRANSACCIONES!$L$2:$L$1000)-ROW(TRANSACCIONES!$L$2)+1),16)),"") | E21: =IFERROR(INDEX(TRANSACCIONES!$N$2:$N$1000,SMALL(IF(UPPER(TRANSACCIONES!$L$2:$L$1000)="POR COBRAR",ROW(TRANSACCIONES!$L$2:$L$1000)-ROW(TRANSACCIONES!$L$2)+1),16)),"") | F21: =IF(A21="","",TODAY()-A21) | G21: =IF(A21="","",IF(E21<TODAY(),"VENCIDO",IF(E21<=TODAY()+7,"POR VENCER","AL DÍA"))) | H21: =IFERROR(INDEX(TRANSACCIONES!$K$2:$K$1000,SMALL(IF(UPPER(TRANSACCIONES!$L$2:$L$1000)="POR COBRAR",ROW(TRANSACCIONES!$L$2:$L$1000)-ROW(TRANSACCIONES!$L$2)+1),16)),"")
A22: =IFERROR(INDEX(TRANSACCIONES!$A$2:$A$1000,SMALL(IF(UPPER(TRANSACCIONES!$L$2:$L$1000)="POR COBRAR",ROW(TRANSACCIONES!$L$2:$L$1000)-ROW(TRANSACCIONES!$L$2)+1),17)),"") | B22: =IFERROR(INDEX(TRANSACCIONES!$E$2:$E$1000,SMALL(IF(UPPER(TRANSACCIONES!$L$2:$L$1000)="POR COBRAR",ROW(TRANSACCIONES!$L$2:$L$1000)-ROW(TRANSACCIONES!$L$2)+1),17)),"") | C22: =IFERROR(INDEX(TRANSACCIONES!$F$2:$F$1000,SMALL(IF(UPPER(TRANSACCIONES!$L$2:$L$1000)="POR COBRAR",ROW(TRANSACCIONES!$L$2:$L$1000)-ROW(TRANSACCIONES!$L$2)+1),17)),"") | D22: =IFERROR(INDEX(TRANSACCIONES!$I$2:$I$1000,SMALL(IF(UPPER(TRANSACCIONES!$L$2:$L$1000)="POR COBRAR",ROW(TRANSACCIONES!$L$2:$L$1000)-ROW(TRANSACCIONES!$L$2)+1),17)),"") | E22: =IFERROR(INDEX(TRANSACCIONES!$N$2:$N$1000,SMALL(IF(UPPER(TRANSACCIONES!$L$2:$L$1000)="POR COBRAR",ROW(TRANSACCIONES!$L$2:$L$1000)-ROW(TRANSACCIONES!$L$2)+1),17)),"") | F22: =IF(A22="","",TODAY()-A22) | G22: =IF(A22="","",IF(E22<TODAY(),"VENCIDO",IF(E22<=TODAY()+7,"POR VENCER","AL DÍA"))) | H22: =IFERROR(INDEX(TRANSACCIONES!$K$2:$K$1000,SMALL(IF(UPPER(TRANSACCIONES!$L$2:$L$1000)="POR COBRAR",ROW(TRANSACCIONES!$L$2:$L$1000)-ROW(TRANSACCIONES!$L$2)+1),17)),"")
A23: =IFERROR(INDEX(TRANSACCIONES!$A$2:$A$1000,SMALL(IF(UPPER(TRANSACCIONES!$L$2:$L$1000)="POR COBRAR",ROW(TRANSACCIONES!$L$2:$L$1000)-ROW(TRANSACCIONES!$L$2)+1),18)),"") | B23: =IFERROR(INDEX(TRANSACCIONES!$E$2:$E$1000,SMALL(IF(UPPER(TRANSACCIONES!$L$2:$L$1000)="POR COBRAR",ROW(TRANSACCIONES!$L$2:$L$1000)-ROW(TRANSACCIONES!$L$2)+1),18)),"") | C23: =IFERROR(INDEX(TRANSACCIONES!$F$2:$F$1000,SMALL(IF(UPPER(TRANSACCIONES!$L$2:$L$1000)="POR COBRAR",ROW(TRANSACCIONES!$L$2:$L$1000)-ROW(TRANSACCIONES!$L$2)+1),18)),"") | D23: =IFERROR(INDEX(TRANSACCIONES!$I$2:$I$1000,SMALL(IF(UPPER(TRANSACCIONES!$L$2:$L$1000)="POR COBRAR",ROW(TRANSACCIONES!$L$2:$L$1000)-ROW(TRANSACCIONES!$L$2)+1),18)),"") | E23: =IFERROR(INDEX(TRANSACCIONES!$N$2:$N$1000,SMALL(IF(UPPER(TRANSACCIONES!$L$2:$L$1000)="POR COBRAR",ROW(TRANSACCIONES!$L$2:$L$1000)-ROW(TRANSACCIONES!$L$2)+1),18)),"") | F23: =IF(A23="","",TODAY()-A23) | G23: =IF(A23="","",IF(E23<TODAY(),"VENCIDO",IF(E23<=TODAY()+7,"POR VENCER","AL DÍA"))) | H23: =IFERROR(INDEX(TRANSACCIONES!$K$2:$K$1000,SMALL(IF(UPPER(TRANSACCIONES!$L$2:$L$1000)="POR COBRAR",ROW(TRANSACCIONES!$L$2:$L$1000)-ROW(TRANSACCIONES!$L$2)+1),18)),"")
A24: =IFERROR(INDEX(TRANSACCIONES!$A$2:$A$1000,SMALL(IF(UPPER(TRANSACCIONES!$L$2:$L$1000)="POR COBRAR",ROW(TRANSACCIONES!$L$2:$L$1000)-ROW(TRANSACCIONES!$L$2)+1),19)),"") | B24: =IFERROR(INDEX(TRANSACCIONES!$E$2:$E$1000,SMALL(IF(UPPER(TRANSACCIONES!$L$2:$L$1000)="POR COBRAR",ROW(TRANSACCIONES!$L$2:$L$1000)-ROW(TRANSACCIONES!$L$2)+1),19)),"") | C24: =IFERROR(INDEX(TRANSACCIONES!$F$2:$F$1000,SMALL(IF(UPPER(TRANSACCIONES!$L$2:$L$1000)="POR COBRAR",ROW(TRANSACCIONES!$L$2:$L$1000)-ROW(TRANSACCIONES!$L$2)+1),19)),"") | D24: =IFERROR(INDEX(TRANSACCIONES!$I$2:$I$1000,SMALL(IF(UPPER(TRANSACCIONES!$L$2:$L$1000)="POR COBRAR",ROW(TRANSACCIONES!$L$2:$L$1000)-ROW(TRANSACCIONES!$L$2)+1),19)),"") | E24: =IFERROR(INDEX(TRANSACCIONES!$N$2:$N$1000,SMALL(IF(UPPER(TRANSACCIONES!$L$2:$L$1000)="POR COBRAR",ROW(TRANSACCIONES!$L$2:$L$1000)-ROW(TRANSACCIONES!$L$2)+1),19)),"") | F24: =IF(A24="","",TODAY()-A24) | G24: =IF(A24="","",IF(E24<TODAY(),"VENCIDO",IF(E24<=TODAY()+7,"POR VENCER","AL DÍA"))) | H24: =IFERROR(INDEX(TRANSACCIONES!$K$2:$K$1000,SMALL(IF(UPPER(TRANSACCIONES!$L$2:$L$1000)="POR COBRAR",ROW(TRANSACCIONES!$L$2:$L$1000)-ROW(TRANSACCIONES!$L$2)+1),19)),"")
A25: =IFERROR(INDEX(TRANSACCIONES!$A$2:$A$1000,SMALL(IF(UPPER(TRANSACCIONES!$L$2:$L$1000)="POR COBRAR",ROW(TRANSACCIONES!$L$2:$L$1000)-ROW(TRANSACCIONES!$L$2)+1),20)),"") | B25: =IFERROR(INDEX(TRANSACCIONES!$E$2:$E$1000,SMALL(IF(UPPER(TRANSACCIONES!$L$2:$L$1000)="POR COBRAR",ROW(TRANSACCIONES!$L$2:$L$1000)-ROW(TRANSACCIONES!$L$2)+1),20)),"") | C25: =IFERROR(INDEX(TRANSACCIONES!$F$2:$F$1000,SMALL(IF(UPPER(TRANSACCIONES!$L$2:$L$1000)="POR COBRAR",ROW(TRANSACCIONES!$L$2:$L$1000)-ROW(TRANSACCIONES!$L$2)+1),20)),"") | D25: =IFERROR(INDEX(TRANSACCIONES!$I$2:$I$1000,SMALL(IF(UPPER(TRANSACCIONES!$L$2:$L$1000)="POR COBRAR",ROW(TRANSACCIONES!$L$2:$L$1000)-ROW(TRANSACCIONES!$L$2)+1),20)),"") | E25: =IFERROR(INDEX(TRANSACCIONES!$N$2:$N$1000,SMALL(IF(UPPER(TRANSACCIONES!$L$2:$L$1000)="POR COBRAR",ROW(TRANSACCIONES!$L$2:$L$1000)-ROW(TRANSACCIONES!$L$2)+1),20)),"") | F25: =IF(A25="","",TODAY()-A25) | G25: =IF(A25="","",IF(E25<TODAY(),"VENCIDO",IF(E25<=TODAY()+7,"POR VENCER","AL DÍA"))) | H25: =IFERROR(INDEX(TRANSACCIONES!$K$2:$K$1000,SMALL(IF(UPPER(TRANSACCIONES!$L$2:$L$1000)="POR COBRAR",ROW(TRANSACCIONES!$L$2:$L$1000)-ROW(TRANSACCIONES!$L$2)+1),20)),"")
A26: =IFERROR(INDEX(TRANSACCIONES!$A$2:$A$1000,SMALL(IF(UPPER(TRANSACCIONES!$L$2:$L$1000)="POR COBRAR",ROW(TRANSACCIONES!$L$2:$L$1000)-ROW(TRANSACCIONES!$L$2)+1),21)),"") | B26: =IFERROR(INDEX(TRANSACCIONES!$E$2:$E$1000,SMALL(IF(UPPER(TRANSACCIONES!$L$2:$L$1000)="POR COBRAR",ROW(TRANSACCIONES!$L$2:$L$1000)-ROW(TRANSACCIONES!$L$2)+1),21)),"") | C26: =IFERROR(INDEX(TRANSACCIONES!$F$2:$F$1000,SMALL(IF(UPPER(TRANSACCIONES!$L$2:$L$1000)="POR COBRAR",ROW(TRANSACCIONES!$L$2:$L$1000)-ROW(TRANSACCIONES!$L$2)+1),21)),"") | D26: =IFERROR(INDEX(TRANSACCIONES!$I$2:$I$1000,SMALL(IF(UPPER(TRANSACCIONES!$L$2:$L$1000)="POR COBRAR",ROW(TRANSACCIONES!$L$2:$L$1000)-ROW(TRANSACCIONES!$L$2)+1),21)),"") | E26: =IFERROR(INDEX(TRANSACCIONES!$N$2:$N$1000,SMALL(IF(UPPER(TRANSACCIONES!$L$2:$L$1000)="POR COBRAR",ROW(TRANSACCIONES!$L$2:$L$1000)-ROW(TRANSACCIONES!$L$2)+1),21)),"") | F26: =IF(A26="","",TODAY()-A26) | G26: =IF(A26="","",IF(E26<TODAY(),"VENCIDO",IF(E26<=TODAY()+7,"POR VENCER","AL DÍA"))) | H26: =IFERROR(INDEX(TRANSACCIONES!$K$2:$K$1000,SMALL(IF(UPPER(TRANSACCIONES!$L$2:$L$1000)="POR COBRAR",ROW(TRANSACCIONES!$L$2:$L$1000)-ROW(TRANSACCIONES!$L$2)+1),21)),"")
A27: =IFERROR(INDEX(TRANSACCIONES!$A$2:$A$1000,SMALL(IF(UPPER(TRANSACCIONES!$L$2:$L$1000)="POR COBRAR",ROW(TRANSACCIONES!$L$2:$L$1000)-ROW(TRANSACCIONES!$L$2)+1),22)),"") | B27: =IFERROR(INDEX(TRANSACCIONES!$E$2:$E$1000,SMALL(IF(UPPER(TRANSACCIONES!$L$2:$L$1000)="POR COBRAR",ROW(TRANSACCIONES!$L$2:$L$1000)-ROW(TRANSACCIONES!$L$2)+1),22)),"") | C27: =IFERROR(INDEX(TRANSACCIONES!$F$2:$F$1000,SMALL(IF(UPPER(TRANSACCIONES!$L$2:$L$1000)="POR COBRAR",ROW(TRANSACCIONES!$L$2:$L$1000)-ROW(TRANSACCIONES!$L$2)+1),22)),"") | D27: =IFERROR(INDEX(TRANSACCIONES!$I$2:$I$1000,SMALL(IF(UPPER(TRANSACCIONES!$L$2:$L$1000)="POR COBRAR",ROW(TRANSACCIONES!$L$2:$L$1000)-ROW(TRANSACCIONES!$L$2)+1),22)),"") | E27: =IFERROR(INDEX(TRANSACCIONES!$N$2:$N$1000,SMALL(IF(UPPER(TRANSACCIONES!$L$2:$L$1000)="POR COBRAR",ROW(TRANSACCIONES!$L$2:$L$1000)-ROW(TRANSACCIONES!$L$2)+1),22)),"") | F27: =IF(A27="","",TODAY()-A27) | G27: =IF(A27="","",IF(E27<TODAY(),"VENCIDO",IF(E27<=TODAY()+7,"POR VENCER","AL DÍA"))) | H27: =IFERROR(INDEX(TRANSACCIONES!$K$2:$K$1000,SMALL(IF(UPPER(TRANSACCIONES!$L$2:$L$1000)="POR COBRAR",ROW(TRANSACCIONES!$L$2:$L$1000)-ROW(TRANSACCIONES!$L$2)+1),22)),"")
A28: =IFERROR(INDEX(TRANSACCIONES!$A$2:$A$1000,SMALL(IF(UPPER(TRANSACCIONES!$L$2:$L$1000)="POR COBRAR",ROW(TRANSACCIONES!$L$2:$L$1000)-ROW(TRANSACCIONES!$L$2)+1),23)),"") | B28: =IFERROR(INDEX(TRANSACCIONES!$E$2:$E$1000,SMALL(IF(UPPER(TRANSACCIONES!$L$2:$L$1000)="POR COBRAR",ROW(TRANSACCIONES!$L$2:$L$1000)-ROW(TRANSACCIONES!$L$2)+1),23)),"") | C28: =IFERROR(INDEX(TRANSACCIONES!$F$2:$F$1000,SMALL(IF(UPPER(TRANSACCIONES!$L$2:$L$1000)="POR COBRAR",ROW(TRANSACCIONES!$L$2:$L$1000)-ROW(TRANSACCIONES!$L$2)+1),23)),"") | D28: =IFERROR(INDEX(TRANSACCIONES!$I$2:$I$1000,SMALL(IF(UPPER(TRANSACCIONES!$L$2:$L$1000)="POR COBRAR",ROW(TRANSACCIONES!$L$2:$L$1000)-ROW(TRANSACCIONES!$L$2)+1),23)),"") | E28: =IFERROR(INDEX(TRANSACCIONES!$N$2:$N$1000,SMALL(IF(UPPER(TRANSACCIONES!$L$2:$L$1000)="POR COBRAR",ROW(TRANSACCIONES!$L$2:$L$1000)-ROW(TRANSACCIONES!$L$2)+1),23)),"") | F28: =IF(A28="","",TODAY()-A28) | G28: =IF(A28="","",IF(E28<TODAY(),"VENCIDO",IF(E28<=TODAY()+7,"POR VENCER","AL DÍA"))) | H28: =IFERROR(INDEX(TRANSACCIONES!$K$2:$K$1000,SMALL(IF(UPPER(TRANSACCIONES!$L$2:$L$1000)="POR COBRAR",ROW(TRANSACCIONES!$L$2:$L$1000)-ROW(TRANSACCIONES!$L$2)+1),23)),"")
A29: =IFERROR(INDEX(TRANSACCIONES!$A$2:$A$1000,SMALL(IF(UPPER(TRANSACCIONES!$L$2:$L$1000)="POR COBRAR",ROW(TRANSACCIONES!$L$2:$L$1000)-ROW(TRANSACCIONES!$L$2)+1),24)),"") | B29: =IFERROR(INDEX(TRANSACCIONES!$E$2:$E$1000,SMALL(IF(UPPER(TRANSACCIONES!$L$2:$L$1000)="POR COBRAR",ROW(TRANSACCIONES!$L$2:$L$1000)-ROW(TRANSACCIONES!$L$2)+1),24)),"") | C29: =IFERROR(INDEX(TRANSACCIONES!$F$2:$F$1000,SMALL(IF(UPPER(TRANSACCIONES!$L$2:$L$1000)="POR COBRAR",ROW(TRANSACCIONES!$L$2:$L$1000)-ROW(TRANSACCIONES!$L$2)+1),24)),"") | D29: =IFERROR(INDEX(TRANSACCIONES!$I$2:$I$1000,SMALL(IF(UPPER(TRANSACCIONES!$L$2:$L$1000)="POR COBRAR",ROW(TRANSACCIONES!$L$2:$L$1000)-ROW(TRANSACCIONES!$L$2)+1),24)),"") | E29: =IFERROR(INDEX(TRANSACCIONES!$N$2:$N$1000,SMALL(IF(UPPER(TRANSACCIONES!$L$2:$L$1000)="POR COBRAR",ROW(TRANSACCIONES!$L$2:$L$1000)-ROW(TRANSACCIONES!$L$2)+1),24)),"") | F29: =IF(A29="","",TODAY()-A29) | G29: =IF(A29="","",IF(E29<TODAY(),"VENCIDO",IF(E29<=TODAY()+7,"POR VENCER","AL DÍA"))) | H29: =IFERROR(INDEX(TRANSACCIONES!$K$2:$K$1000,SMALL(IF(UPPER(TRANSACCIONES!$L$2:$L$1000)="POR COBRAR",ROW(TRANSACCIONES!$L$2:$L$1000)-ROW(TRANSACCIONES!$L$2)+1),24)),"")
A30: =IFERROR(INDEX(TRANSACCIONES!$A$2:$A$1000,SMALL(IF(UPPER(TRANSACCIONES!$L$2:$L$1000)="POR COBRAR",ROW(TRANSACCIONES!$L$2:$L$1000)-ROW(TRANSACCIONES!$L$2)+1),25)),"") | B30: =IFERROR(INDEX(TRANSACCIONES!$E$2:$E$1000,SMALL(IF(UPPER(TRANSACCIONES!$L$2:$L$1000)="POR COBRAR",ROW(TRANSACCIONES!$L$2:$L$1000)-ROW(TRANSACCIONES!$L$2)+1),25)),"") | C30: =IFERROR(INDEX(TRANSACCIONES!$F$2:$F$1000,SMALL(IF(UPPER(TRANSACCIONES!$L$2:$L$1000)="POR COBRAR",ROW(TRANSACCIONES!$L$2:$L$1000)-ROW(TRANSACCIONES!$L$2)+1),25)),"") | D30: =IFERROR(INDEX(TRANSACCIONES!$I$2:$I$1000,SMALL(IF(UPPER(TRANSACCIONES!$L$2:$L$1000)="POR COBRAR",ROW(TRANSACCIONES!$L$2:$L$1000)-ROW(TRANSACCIONES!$L$2)+1),25)),"") | E30: =IFERROR(INDEX(TRANSACCIONES!$N$2:$N$1000,SMALL(IF(UPPER(TRANSACCIONES!$L$2:$L$1000)="POR COBRAR",ROW(TRANSACCIONES!$L$2:$L$1000)-ROW(TRANSACCIONES!$L$2)+1),25)),"") | F30: =IF(A30="","",TODAY()-A30) | G30: =IF(A30="","",IF(E30<TODAY(),"VENCIDO",IF(E30<=TODAY()+7,"POR VENCER","AL DÍA"))) | H30: =IFERROR(INDEX(TRANSACCIONES!$K$2:$K$1000,SMALL(IF(UPPER(TRANSACCIONES!$L$2:$L$1000)="POR COBRAR",ROW(TRANSACCIONES!$L$2:$L$1000)-ROW(TRANSACCIONES!$L$2)+1),25)),"")
A31: =IFERROR(INDEX(TRANSACCIONES!$A$2:$A$1000,SMALL(IF(UPPER(TRANSACCIONES!$L$2:$L$1000)="POR COBRAR",ROW(TRANSACCIONES!$L$2:$L$1000)-ROW(TRANSACCIONES!$L$2)+1),26)),"") | B31: =IFERROR(INDEX(TRANSACCIONES!$E$2:$E$1000,SMALL(IF(UPPER(TRANSACCIONES!$L$2:$L$1000)="POR COBRAR",ROW(TRANSACCIONES!$L$2:$L$1000)-ROW(TRANSACCIONES!$L$2)+1),26)),"") | C31: =IFERROR(INDEX(TRANSACCIONES!$F$2:$F$1000,SMALL(IF(UPPER(TRANSACCIONES!$L$2:$L$1000)="POR COBRAR",ROW(TRANSACCIONES!$L$2:$L$1000)-ROW(TRANSACCIONES!$L$2)+1),26)),"") | D31: =IFERROR(INDEX(TRANSACCIONES!$I$2:$I$1000,SMALL(IF(UPPER(TRANSACCIONES!$L$2:$L$1000)="POR COBRAR",ROW(TRANSACCIONES!$L$2:$L$1000)-ROW(TRANSACCIONES!$L$2)+1),26)),"") | E31: =IFERROR(INDEX(TRANSACCIONES!$N$2:$N$1000,SMALL(IF(UPPER(TRANSACCIONES!$L$2:$L$1000)="POR COBRAR",ROW(TRANSACCIONES!$L$2:$L$1000)-ROW(TRANSACCIONES!$L$2)+1),26)),"") | F31: =IF(A31="","",TODAY()-A31) | G31: =IF(A31="","",IF(E31<TODAY(),"VENCIDO",IF(E31<=TODAY()+7,"POR VENCER","AL DÍA"))) | H31: =IFERROR(INDEX(TRANSACCIONES!$K$2:$K$1000,SMALL(IF(UPPER(TRANSACCIONES!$L$2:$L$1000)="POR COBRAR",ROW(TRANSACCIONES!$L$2:$L$1000)-ROW(TRANSACCIONES!$L$2)+1),26)),"")
A32: =IFERROR(INDEX(TRANSACCIONES!$A$2:$A$1000,SMALL(IF(UPPER(TRANSACCIONES!$L$2:$L$1000)="POR COBRAR",ROW(TRANSACCIONES!$L$2:$L$1000)-ROW(TRANSACCIONES!$L$2)+1),27)),"") | B32: =IFERROR(INDEX(TRANSACCIONES!$E$2:$E$1000,SMALL(IF(UPPER(TRANSACCIONES!$L$2:$L$1000)="POR COBRAR",ROW(TRANSACCIONES!$L$2:$L$1000)-ROW(TRANSACCIONES!$L$2)+1),27)),"") | C32: =IFERROR(INDEX(TRANSACCIONES!$F$2:$F$1000,SMALL(IF(UPPER(TRANSACCIONES!$L$2:$L$1000)="POR COBRAR",ROW(TRANSACCIONES!$L$2:$L$1000)-ROW(TRANSACCIONES!$L$2)+1),27)),"") | D32: =IFERROR(INDEX(TRANSACCIONES!$I$2:$I$1000,SMALL(IF(UPPER(TRANSACCIONES!$L$2:$L$1000)="POR COBRAR",ROW(TRANSACCIONES!$L$2:$L$1000)-ROW(TRANSACCIONES!$L$2)+1),27)),"") | E32: =IFERROR(INDEX(TRANSACCIONES!$N$2:$N$1000,SMALL(IF(UPPER(TRANSACCIONES!$L$2:$L$1000)="POR COBRAR",ROW(TRANSACCIONES!$L$2:$L$1000)-ROW(TRANSACCIONES!$L$2)+1),27)),"") | F32: =IF(A32="","",TODAY()-A32) | G32: =IF(A32="","",IF(E32<TODAY(),"VENCIDO",IF(E32<=TODAY()+7,"POR VENCER","AL DÍA"))) | H32: =IFERROR(INDEX(TRANSACCIONES!$K$2:$K$1000,SMALL(IF(UPPER(TRANSACCIONES!$L$2:$L$1000)="POR COBRAR",ROW(TRANSACCIONES!$L$2:$L$1000)-ROW(TRANSACCIONES!$L$2)+1),27)),"")
A33: =IFERROR(INDEX(TRANSACCIONES!$A$2:$A$1000,SMALL(IF(UPPER(TRANSACCIONES!$L$2:$L$1000)="POR COBRAR",ROW(TRANSACCIONES!$L$2:$L$1000)-ROW(TRANSACCIONES!$L$2)+1),28)),"") | B33: =IFERROR(INDEX(TRANSACCIONES!$E$2:$E$1000,SMALL(IF(UPPER(TRANSACCIONES!$L$2:$L$1000)="POR COBRAR",ROW(TRANSACCIONES!$L$2:$L$1000)-ROW(TRANSACCIONES!$L$2)+1),28)),"") | C33: =IFERROR(INDEX(TRANSACCIONES!$F$2:$F$1000,SMALL(IF(UPPER(TRANSACCIONES!$L$2:$L$1000)="POR COBRAR",ROW(TRANSACCIONES!$L$2:$L$1000)-ROW(TRANSACCIONES!$L$2)+1),28)),"") | D33: =IFERROR(INDEX(TRANSACCIONES!$I$2:$I$1000,SMALL(IF(UPPER(TRANSACCIONES!$L$2:$L$1000)="POR COBRAR",ROW(TRANSACCIONES!$L$2:$L$1000)-ROW(TRANSACCIONES!$L$2)+1),28)),"") | E33: =IFERROR(INDEX(TRANSACCIONES!$N$2:$N$1000,SMALL(IF(UPPER(TRANSACCIONES!$L$2:$L$1000)="POR COBRAR",ROW(TRANSACCIONES!$L$2:$L$1000)-ROW(TRANSACCIONES!$L$2)+1),28)),"") | F33: =IF(A33="","",TODAY()-A33) | G33: =IF(A33="","",IF(E33<TODAY(),"VENCIDO",IF(E33<=TODAY()+7,"POR VENCER","AL DÍA"))) | H33: =IFERROR(INDEX(TRANSACCIONES!$K$2:$K$1000,SMALL(IF(UPPER(TRANSACCIONES!$L$2:$L$1000)="POR COBRAR",ROW(TRANSACCIONES!$L$2:$L$1000)-ROW(TRANSACCIONES!$L$2)+1),28)),"")
A34: =IFERROR(INDEX(TRANSACCIONES!$A$2:$A$1000,SMALL(IF(UPPER(TRANSACCIONES!$L$2:$L$1000)="POR COBRAR",ROW(TRANSACCIONES!$L$2:$L$1000)-ROW(TRANSACCIONES!$L$2)+1),29)),"") | B34: =IFERROR(INDEX(TRANSACCIONES!$E$2:$E$1000,SMALL(IF(UPPER(TRANSACCIONES!$L$2:$L$1000)="POR COBRAR",ROW(TRANSACCIONES!$L$2:$L$1000)-ROW(TRANSACCIONES!$L$2)+1),29)),"") | C34: =IFERROR(INDEX(TRANSACCIONES!$F$2:$F$1000,SMALL(IF(UPPER(TRANSACCIONES!$L$2:$L$1000)="POR COBRAR",ROW(TRANSACCIONES!$L$2:$L$1000)-ROW(TRANSACCIONES!$L$2)+1),29)),"") | D34: =IFERROR(INDEX(TRANSACCIONES!$I$2:$I$1000,SMALL(IF(UPPER(TRANSACCIONES!$L$2:$L$1000)="POR COBRAR",ROW(TRANSACCIONES!$L$2:$L$1000)-ROW(TRANSACCIONES!$L$2)+1),29)),"") | E34: =IFERROR(INDEX(TRANSACCIONES!$N$2:$N$1000,SMALL(IF(UPPER(TRANSACCIONES!$L$2:$L$1000)="POR COBRAR",ROW(TRANSACCIONES!$L$2:$L$1000)-ROW(TRANSACCIONES!$L$2)+1),29)),"") | F34: =IF(A34="","",TODAY()-A34) | G34: =IF(A34="","",IF(E34<TODAY(),"VENCIDO",IF(E34<=TODAY()+7,"POR VENCER","AL DÍA"))) | H34: =IFERROR(INDEX(TRANSACCIONES!$K$2:$K$1000,SMALL(IF(UPPER(TRANSACCIONES!$L$2:$L$1000)="POR COBRAR",ROW(TRANSACCIONES!$L$2:$L$1000)-ROW(TRANSACCIONES!$L$2)+1),29)),"")
A35: =IFERROR(INDEX(TRANSACCIONES!$A$2:$A$1000,SMALL(IF(UPPER(TRANSACCIONES!$L$2:$L$1000)="POR COBRAR",ROW(TRANSACCIONES!$L$2:$L$1000)-ROW(TRANSACCIONES!$L$2)+1),30)),"") | B35: =IFERROR(INDEX(TRANSACCIONES!$E$2:$E$1000,SMALL(IF(UPPER(TRANSACCIONES!$L$2:$L$1000)="POR COBRAR",ROW(TRANSACCIONES!$L$2:$L$1000)-ROW(TRANSACCIONES!$L$2)+1),30)),"") | C35: =IFERROR(INDEX(TRANSACCIONES!$F$2:$F$1000,SMALL(IF(UPPER(TRANSACCIONES!$L$2:$L$1000)="POR COBRAR",ROW(TRANSACCIONES!$L$2:$L$1000)-ROW(TRANSACCIONES!$L$2)+1),30)),"") | D35: =IFERROR(INDEX(TRANSACCIONES!$I$2:$I$1000,SMALL(IF(UPPER(TRANSACCIONES!$L$2:$L$1000)="POR COBRAR",ROW(TRANSACCIONES!$L$2:$L$1000)-ROW(TRANSACCIONES!$L$2)+1),30)),"") | E35: =IFERROR(INDEX(TRANSACCIONES!$N$2:$N$1000,SMALL(IF(UPPER(TRANSACCIONES!$L$2:$L$1000)="POR COBRAR",ROW(TRANSACCIONES!$L$2:$L$1000)-ROW(TRANSACCIONES!$L$2)+1),30)),"") | F35: =IF(A35="","",TODAY()-A35) | G35: =IF(A35="","",IF(E35<TODAY(),"VENCIDO",IF(E35<=TODAY()+7,"POR VENCER","AL DÍA"))) | H35: =IFERROR(INDEX(TRANSACCIONES!$K$2:$K$1000,SMALL(IF(UPPER(TRANSACCIONES!$L$2:$L$1000)="POR COBRAR",ROW(TRANSACCIONES!$L$2:$L$1000)-ROW(TRANSACCIONES!$L$2)+1),30)),"")
A36: =IFERROR(INDEX(TRANSACCIONES!$A$2:$A$1000,SMALL(IF(UPPER(TRANSACCIONES!$L$2:$L$1000)="POR COBRAR",ROW(TRANSACCIONES!$L$2:$L$1000)-ROW(TRANSACCIONES!$L$2)+1),31)),"") | B36: =IFERROR(INDEX(TRANSACCIONES!$E$2:$E$1000,SMALL(IF(UPPER(TRANSACCIONES!$L$2:$L$1000)="POR COBRAR",ROW(TRANSACCIONES!$L$2:$L$1000)-ROW(TRANSACCIONES!$L$2)+1),31)),"") | C36: =IFERROR(INDEX(TRANSACCIONES!$F$2:$F$1000,SMALL(IF(UPPER(TRANSACCIONES!$L$2:$L$1000)="POR COBRAR",ROW(TRANSACCIONES!$L$2:$L$1000)-ROW(TRANSACCIONES!$L$2)+1),31)),"") | D36: =IFERROR(INDEX(TRANSACCIONES!$I$2:$I$1000,SMALL(IF(UPPER(TRANSACCIONES!$L$2:$L$1000)="POR COBRAR",ROW(TRANSACCIONES!$L$2:$L$1000)-ROW(TRANSACCIONES!$L$2)+1),31)),"") | E36: =IFERROR(INDEX(TRANSACCIONES!$N$2:$N$1000,SMALL(IF(UPPER(TRANSACCIONES!$L$2:$L$1000)="POR COBRAR",ROW(TRANSACCIONES!$L$2:$L$1000)-ROW(TRANSACCIONES!$L$2)+1),31)),"") | F36: =IF(A36="","",TODAY()-A36) | G36: =IF(A36="","",IF(E36<TODAY(),"VENCIDO",IF(E36<=TODAY()+7,"POR VENCER","AL DÍA"))) | H36: =IFERROR(INDEX(TRANSACCIONES!$K$2:$K$1000,SMALL(IF(UPPER(TRANSACCIONES!$L$2:$L$1000)="POR COBRAR",ROW(TRANSACCIONES!$L$2:$L$1000)-ROW(TRANSACCIONES!$L$2)+1),31)),"")
A37: =IFERROR(INDEX(TRANSACCIONES!$A$2:$A$1000,SMALL(IF(UPPER(TRANSACCIONES!$L$2:$L$1000)="POR COBRAR",ROW(TRANSACCIONES!$L$2:$L$1000)-ROW(TRANSACCIONES!$L$2)+1),32)),"") | B37: =IFERROR(INDEX(TRANSACCIONES!$E$2:$E$1000,SMALL(IF(UPPER(TRANSACCIONES!$L$2:$L$1000)="POR COBRAR",ROW(TRANSACCIONES!$L$2:$L$1000)-ROW(TRANSACCIONES!$L$2)+1),32)),"") | C37: =IFERROR(INDEX(TRANSACCIONES!$F$2:$F$1000,SMALL(IF(UPPER(TRANSACCIONES!$L$2:$L$1000)="POR COBRAR",ROW(TRANSACCIONES!$L$2:$L$1000)-ROW(TRANSACCIONES!$L$2)+1),32)),"") | D37: =IFERROR(INDEX(TRANSACCIONES!$I$2:$I$1000,SMALL(IF(UPPER(TRANSACCIONES!$L$2:$L$1000)="POR COBRAR",ROW(TRANSACCIONES!$L$2:$L$1000)-ROW(TRANSACCIONES!$L$2)+1),32)),"") | E37: =IFERROR(INDEX(TRANSACCIONES!$N$2:$N$1000,SMALL(IF(UPPER(TRANSACCIONES!$L$2:$L$1000)="POR COBRAR",ROW(TRANSACCIONES!$L$2:$L$1000)-ROW(TRANSACCIONES!$L$2)+1),32)),"") | F37: =IF(A37="","",TODAY()-A37) | G37: =IF(A37="","",IF(E37<TODAY(),"VENCIDO",IF(E37<=TODAY()+7,"POR VENCER","AL DÍA"))) | H37: =IFERROR(INDEX(TRANSACCIONES!$K$2:$K$1000,SMALL(IF(UPPER(TRANSACCIONES!$L$2:$L$1000)="POR COBRAR",ROW(TRANSACCIONES!$L$2:$L$1000)-ROW(TRANSACCIONES!$L$2)+1),32)),"")
A38: =IFERROR(INDEX(TRANSACCIONES!$A$2:$A$1000,SMALL(IF(UPPER(TRANSACCIONES!$L$2:$L$1000)="POR COBRAR",ROW(TRANSACCIONES!$L$2:$L$1000)-ROW(TRANSACCIONES!$L$2)+1),33)),"") | B38: =IFERROR(INDEX(TRANSACCIONES!$E$2:$E$1000,SMALL(IF(UPPER(TRANSACCIONES!$L$2:$L$1000)="POR COBRAR",ROW(TRANSACCIONES!$L$2:$L$1000)-ROW(TRANSACCIONES!$L$2)+1),33)),"") | C38: =IFERROR(INDEX(TRANSACCIONES!$F$2:$F$1000,SMALL(IF(UPPER(TRANSACCIONES!$L$2:$L$1000)="POR COBRAR",ROW(TRANSACCIONES!$L$2:$L$1000)-ROW(TRANSACCIONES!$L$2)+1),33)),"") | D38: =IFERROR(INDEX(TRANSACCIONES!$I$2:$I$1000,SMALL(IF(UPPER(TRANSACCIONES!$L$2:$L$1000)="POR COBRAR",ROW(TRANSACCIONES!$L$2:$L$1000)-ROW(TRANSACCIONES!$L$2)+1),33)),"") | E38: =IFERROR(INDEX(TRANSACCIONES!$N$2:$N$1000,SMALL(IF(UPPER(TRANSACCIONES!$L$2:$L$1000)="POR COBRAR",ROW(TRANSACCIONES!$L$2:$L$1000)-ROW(TRANSACCIONES!$L$2)+1),33)),"") | F38: =IF(A38="","",TODAY()-A38) | G38: =IF(A38="","",IF(E38<TODAY(),"VENCIDO",IF(E38<=TODAY()+7,"POR VENCER","AL DÍA"))) | H38: =IFERROR(INDEX(TRANSACCIONES!$K$2:$K$1000,SMALL(IF(UPPER(TRANSACCIONES!$L$2:$L$1000)="POR COBRAR",ROW(TRANSACCIONES!$L$2:$L$1000)-ROW(TRANSACCIONES!$L$2)+1),33)),"")
A39: =IFERROR(INDEX(TRANSACCIONES!$A$2:$A$1000,SMALL(IF(UPPER(TRANSACCIONES!$L$2:$L$1000)="POR COBRAR",ROW(TRANSACCIONES!$L$2:$L$1000)-ROW(TRANSACCIONES!$L$2)+1),34)),"") | B39: =IFERROR(INDEX(TRANSACCIONES!$E$2:$E$1000,SMALL(IF(UPPER(TRANSACCIONES!$L$2:$L$1000)="POR COBRAR",ROW(TRANSACCIONES!$L$2:$L$1000)-ROW(TRANSACCIONES!$L$2)+1),34)),"") | C39: =IFERROR(INDEX(TRANSACCIONES!$F$2:$F$1000,SMALL(IF(UPPER(TRANSACCIONES!$L$2:$L$1000)="POR COBRAR",ROW(TRANSACCIONES!$L$2:$L$1000)-ROW(TRANSACCIONES!$L$2)+1),34)),"") | D39: =IFERROR(INDEX(TRANSACCIONES!$I$2:$I$1000,SMALL(IF(UPPER(TRANSACCIONES!$L$2:$L$1000)="POR COBRAR",ROW(TRANSACCIONES!$L$2:$L$1000)-ROW(TRANSACCIONES!$L$2)+1),34)),"") | E39: =IFERROR(INDEX(TRANSACCIONES!$N$2:$N$1000,SMALL(IF(UPPER(TRANSACCIONES!$L$2:$L$1000)="POR COBRAR",ROW(TRANSACCIONES!$L$2:$L$1000)-ROW(TRANSACCIONES!$L$2)+1),34)),"") | F39: =IF(A39="","",TODAY()-A39) | G39: =IF(A39="","",IF(E39<TODAY(),"VENCIDO",IF(E39<=TODAY()+7,"POR VENCER","AL DÍA"))) | H39: =IFERROR(INDEX(TRANSACCIONES!$K$2:$K$1000,SMALL(IF(UPPER(TRANSACCIONES!$L$2:$L$1000)="POR COBRAR",ROW(TRANSACCIONES!$L$2:$L$1000)-ROW(TRANSACCIONES!$L$2)+1),34)),"")
A40: =IFERROR(INDEX(TRANSACCIONES!$A$2:$A$1000,SMALL(IF(UPPER(TRANSACCIONES!$L$2:$L$1000)="POR COBRAR",ROW(TRANSACCIONES!$L$2:$L$1000)-ROW(TRANSACCIONES!$L$2)+1),35)),"") | B40: =IFERROR(INDEX(TRANSACCIONES!$E$2:$E$1000,SMALL(IF(UPPER(TRANSACCIONES!$L$2:$L$1000)="POR COBRAR",ROW(TRANSACCIONES!$L$2:$L$1000)-ROW(TRANSACCIONES!$L$2)+1),35)),"") | C40: =IFERROR(INDEX(TRANSACCIONES!$F$2:$F$1000,SMALL(IF(UPPER(TRANSACCIONES!$L$2:$L$1000)="POR COBRAR",ROW(TRANSACCIONES!$L$2:$L$1000)-ROW(TRANSACCIONES!$L$2)+1),35)),"") | D40: =IFERROR(INDEX(TRANSACCIONES!$I$2:$I$1000,SMALL(IF(UPPER(TRANSACCIONES!$L$2:$L$1000)="POR COBRAR",ROW(TRANSACCIONES!$L$2:$L$1000)-ROW(TRANSACCIONES!$L$2)+1),35)),"") | E40: =IFERROR(INDEX(TRANSACCIONES!$N$2:$N$1000,SMALL(IF(UPPER(TRANSACCIONES!$L$2:$L$1000)="POR COBRAR",ROW(TRANSACCIONES!$L$2:$L$1000)-ROW(TRANSACCIONES!$L$2)+1),35)),"") | F40: =IF(A40="","",TODAY()-A40) | G40: =IF(A40="","",IF(E40<TODAY(),"VENCIDO",IF(E40<=TODAY()+7,"POR VENCER","AL DÍA"))) | H40: =IFERROR(INDEX(TRANSACCIONES!$K$2:$K$1000,SMALL(IF(UPPER(TRANSACCIONES!$L$2:$L$1000)="POR COBRAR",ROW(TRANSACCIONES!$L$2:$L$1000)-ROW(TRANSACCIONES!$L$2)+1),35)),"")
A41: =IFERROR(INDEX(TRANSACCIONES!$A$2:$A$1000,SMALL(IF(UPPER(TRANSACCIONES!$L$2:$L$1000)="POR COBRAR",ROW(TRANSACCIONES!$L$2:$L$1000)-ROW(TRANSACCIONES!$L$2)+1),36)),"") | B41: =IFERROR(INDEX(TRANSACCIONES!$E$2:$E$1000,SMALL(IF(UPPER(TRANSACCIONES!$L$2:$L$1000)="POR COBRAR",ROW(TRANSACCIONES!$L$2:$L$1000)-ROW(TRANSACCIONES!$L$2)+1),36)),"") | C41: =IFERROR(INDEX(TRANSACCIONES!$F$2:$F$1000,SMALL(IF(UPPER(TRANSACCIONES!$L$2:$L$1000)="POR COBRAR",ROW(TRANSACCIONES!$L$2:$L$1000)-ROW(TRANSACCIONES!$L$2)+1),36)),"") | D41: =IFERROR(INDEX(TRANSACCIONES!$I$2:$I$1000,SMALL(IF(UPPER(TRANSACCIONES!$L$2:$L$1000)="POR COBRAR",ROW(TRANSACCIONES!$L$2:$L$1000)-ROW(TRANSACCIONES!$L$2)+1),36)),"") | E41: =IFERROR(INDEX(TRANSACCIONES!$N$2:$N$1000,SMALL(IF(UPPER(TRANSACCIONES!$L$2:$L$1000)="POR COBRAR",ROW(TRANSACCIONES!$L$2:$L$1000)-ROW(TRANSACCIONES!$L$2)+1),36)),"") | F41: =IF(A41="","",TODAY()-A41) | G41: =IF(A41="","",IF(E41<TODAY(),"VENCIDO",IF(E41<=TODAY()+7,"POR VENCER","AL DÍA"))) | H41: =IFERROR(INDEX(TRANSACCIONES!$K$2:$K$1000,SMALL(IF(UPPER(TRANSACCIONES!$L$2:$L$1000)="POR COBRAR",ROW(TRANSACCIONES!$L$2:$L$1000)-ROW(TRANSACCIONES!$L$2)+1),36)),"")
A42: =IFERROR(INDEX(TRANSACCIONES!$A$2:$A$1000,SMALL(IF(UPPER(TRANSACCIONES!$L$2:$L$1000)="POR COBRAR",ROW(TRANSACCIONES!$L$2:$L$1000)-ROW(TRANSACCIONES!$L$2)+1),37)),"") | B42: =IFERROR(INDEX(TRANSACCIONES!$E$2:$E$1000,SMALL(IF(UPPER(TRANSACCIONES!$L$2:$L$1000)="POR COBRAR",ROW(TRANSACCIONES!$L$2:$L$1000)-ROW(TRANSACCIONES!$L$2)+1),37)),"") | C42: =IFERROR(INDEX(TRANSACCIONES!$F$2:$F$1000,SMALL(IF(UPPER(TRANSACCIONES!$L$2:$L$1000)="POR COBRAR",ROW(TRANSACCIONES!$L$2:$L$1000)-ROW(TRANSACCIONES!$L$2)+1),37)),"") | D42: =IFERROR(INDEX(TRANSACCIONES!$I$2:$I$1000,SMALL(IF(UPPER(TRANSACCIONES!$L$2:$L$1000)="POR COBRAR",ROW(TRANSACCIONES!$L$2:$L$1000)-ROW(TRANSACCIONES!$L$2)+1),37)),"") | E42: =IFERROR(INDEX(TRANSACCIONES!$N$2:$N$1000,SMALL(IF(UPPER(TRANSACCIONES!$L$2:$L$1000)="POR COBRAR",ROW(TRANSACCIONES!$L$2:$L$1000)-ROW(TRANSACCIONES!$L$2)+1),37)),"") | F42: =IF(A42="","",TODAY()-A42) | G42: =IF(A42="","",IF(E42<TODAY(),"VENCIDO",IF(E42<=TODAY()+7,"POR VENCER","AL DÍA"))) | H42: =IFERROR(INDEX(TRANSACCIONES!$K$2:$K$1000,SMALL(IF(UPPER(TRANSACCIONES!$L$2:$L$1000)="POR COBRAR",ROW(TRANSACCIONES!$L$2:$L$1000)-ROW(TRANSACCIONES!$L$2)+1),37)),"")
A43: =IFERROR(INDEX(TRANSACCIONES!$A$2:$A$1000,SMALL(IF(UPPER(TRANSACCIONES!$L$2:$L$1000)="POR COBRAR",ROW(TRANSACCIONES!$L$2:$L$1000)-ROW(TRANSACCIONES!$L$2)+1),38)),"") | B43: =IFERROR(INDEX(TRANSACCIONES!$E$2:$E$1000,SMALL(IF(UPPER(TRANSACCIONES!$L$2:$L$1000)="POR COBRAR",ROW(TRANSACCIONES!$L$2:$L$1000)-ROW(TRANSACCIONES!$L$2)+1),38)),"") | C43: =IFERROR(INDEX(TRANSACCIONES!$F$2:$F$1000,SMALL(IF(UPPER(TRANSACCIONES!$L$2:$L$1000)="POR COBRAR",ROW(TRANSACCIONES!$L$2:$L$1000)-ROW(TRANSACCIONES!$L$2)+1),38)),"") | D43: =IFERROR(INDEX(TRANSACCIONES!$I$2:$I$1000,SMALL(IF(UPPER(TRANSACCIONES!$L$2:$L$1000)="POR COBRAR",ROW(TRANSACCIONES!$L$2:$L$1000)-ROW(TRANSACCIONES!$L$2)+1),38)),"") | E43: =IFERROR(INDEX(TRANSACCIONES!$N$2:$N$1000,SMALL(IF(UPPER(TRANSACCIONES!$L$2:$L$1000)="POR COBRAR",ROW(TRANSACCIONES!$L$2:$L$1000)-ROW(TRANSACCIONES!$L$2)+1),38)),"") | F43: =IF(A43="","",TODAY()-A43) | G43: =IF(A43="","",IF(E43<TODAY(),"VENCIDO",IF(E43<=TODAY()+7,"POR VENCER","AL DÍA"))) | H43: =IFERROR(INDEX(TRANSACCIONES!$K$2:$K$1000,SMALL(IF(UPPER(TRANSACCIONES!$L$2:$L$1000)="POR COBRAR",ROW(TRANSACCIONES!$L$2:$L$1000)-ROW(TRANSACCIONES!$L$2)+1),38)),"")
A44: =IFERROR(INDEX(TRANSACCIONES!$A$2:$A$1000,SMALL(IF(UPPER(TRANSACCIONES!$L$2:$L$1000)="POR COBRAR",ROW(TRANSACCIONES!$L$2:$L$1000)-ROW(TRANSACCIONES!$L$2)+1),39)),"") | B44: =IFERROR(INDEX(TRANSACCIONES!$E$2:$E$1000,SMALL(IF(UPPER(TRANSACCIONES!$L$2:$L$1000)="POR COBRAR",ROW(TRANSACCIONES!$L$2:$L$1000)-ROW(TRANSACCIONES!$L$2)+1),39)),"") | C44: =IFERROR(INDEX(TRANSACCIONES!$F$2:$F$1000,SMALL(IF(UPPER(TRANSACCIONES!$L$2:$L$1000)="POR COBRAR",ROW(TRANSACCIONES!$L$2:$L$1000)-ROW(TRANSACCIONES!$L$2)+1),39)),"") | D44: =IFERROR(INDEX(TRANSACCIONES!$I$2:$I$1000,SMALL(IF(UPPER(TRANSACCIONES!$L$2:$L$1000)="POR COBRAR",ROW(TRANSACCIONES!$L$2:$L$1000)-ROW(TRANSACCIONES!$L$2)+1),39)),"") | E44: =IFERROR(INDEX(TRANSACCIONES!$N$2:$N$1000,SMALL(IF(UPPER(TRANSACCIONES!$L$2:$L$1000)="POR COBRAR",ROW(TRANSACCIONES!$L$2:$L$1000)-ROW(TRANSACCIONES!$L$2)+1),39)),"") | F44: =IF(A44="","",TODAY()-A44) | G44: =IF(A44="","",IF(E44<TODAY(),"VENCIDO",IF(E44<=TODAY()+7,"POR VENCER","AL DÍA"))) | H44: =IFERROR(INDEX(TRANSACCIONES!$K$2:$K$1000,SMALL(IF(UPPER(TRANSACCIONES!$L$2:$L$1000)="POR COBRAR",ROW(TRANSACCIONES!$L$2:$L$1000)-ROW(TRANSACCIONES!$L$2)+1),39)),"")
A45: =IFERROR(INDEX(TRANSACCIONES!$A$2:$A$1000,SMALL(IF(UPPER(TRANSACCIONES!$L$2:$L$1000)="POR COBRAR",ROW(TRANSACCIONES!$L$2:$L$1000)-ROW(TRANSACCIONES!$L$2)+1),40)),"") | B45: =IFERROR(INDEX(TRANSACCIONES!$E$2:$E$1000,SMALL(IF(UPPER(TRANSACCIONES!$L$2:$L$1000)="POR COBRAR",ROW(TRANSACCIONES!$L$2:$L$1000)-ROW(TRANSACCIONES!$L$2)+1),40)),"") | C45: =IFERROR(INDEX(TRANSACCIONES!$F$2:$F$1000,SMALL(IF(UPPER(TRANSACCIONES!$L$2:$L$1000)="POR COBRAR",ROW(TRANSACCIONES!$L$2:$L$1000)-ROW(TRANSACCIONES!$L$2)+1),40)),"") | D45: =IFERROR(INDEX(TRANSACCIONES!$I$2:$I$1000,SMALL(IF(UPPER(TRANSACCIONES!$L$2:$L$1000)="POR COBRAR",ROW(TRANSACCIONES!$L$2:$L$1000)-ROW(TRANSACCIONES!$L$2)+1),40)),"") | E45: =IFERROR(INDEX(TRANSACCIONES!$N$2:$N$1000,SMALL(IF(UPPER(TRANSACCIONES!$L$2:$L$1000)="POR COBRAR",ROW(TRANSACCIONES!$L$2:$L$1000)-ROW(TRANSACCIONES!$L$2)+1),40)),"") | F45: =IF(A45="","",TODAY()-A45) | G45: =IF(A45="","",IF(E45<TODAY(),"VENCIDO",IF(E45<=TODAY()+7,"POR VENCER","AL DÍA"))) | H45: =IFERROR(INDEX(TRANSACCIONES!$K$2:$K$1000,SMALL(IF(UPPER(TRANSACCIONES!$L$2:$L$1000)="POR COBRAR",ROW(TRANSACCIONES!$L$2:$L$1000)-ROW(TRANSACCIONES!$L$2)+1),40)),"")
A46: =IFERROR(INDEX(TRANSACCIONES!$A$2:$A$1000,SMALL(IF(UPPER(TRANSACCIONES!$L$2:$L$1000)="POR COBRAR",ROW(TRANSACCIONES!$L$2:$L$1000)-ROW(TRANSACCIONES!$L$2)+1),41)),"") | B46: =IFERROR(INDEX(TRANSACCIONES!$E$2:$E$1000,SMALL(IF(UPPER(TRANSACCIONES!$L$2:$L$1000)="POR COBRAR",ROW(TRANSACCIONES!$L$2:$L$1000)-ROW(TRANSACCIONES!$L$2)+1),41)),"") | C46: =IFERROR(INDEX(TRANSACCIONES!$F$2:$F$1000,SMALL(IF(UPPER(TRANSACCIONES!$L$2:$L$1000)="POR COBRAR",ROW(TRANSACCIONES!$L$2:$L$1000)-ROW(TRANSACCIONES!$L$2)+1),41)),"") | D46: =IFERROR(INDEX(TRANSACCIONES!$I$2:$I$1000,SMALL(IF(UPPER(TRANSACCIONES!$L$2:$L$1000)="POR COBRAR",ROW(TRANSACCIONES!$L$2:$L$1000)-ROW(TRANSACCIONES!$L$2)+1),41)),"") | E46: =IFERROR(INDEX(TRANSACCIONES!$N$2:$N$1000,SMALL(IF(UPPER(TRANSACCIONES!$L$2:$L$1000)="POR COBRAR",ROW(TRANSACCIONES!$L$2:$L$1000)-ROW(TRANSACCIONES!$L$2)+1),41)),"") | F46: =IF(A46="","",TODAY()-A46) | G46: =IF(A46="","",IF(E46<TODAY(),"VENCIDO",IF(E46<=TODAY()+7,"POR VENCER","AL DÍA"))) | H46: =IFERROR(INDEX(TRANSACCIONES!$K$2:$K$1000,SMALL(IF(UPPER(TRANSACCIONES!$L$2:$L$1000)="POR COBRAR",ROW(TRANSACCIONES!$L$2:$L$1000)-ROW(TRANSACCIONES!$L$2)+1),41)),"")
A47: =IFERROR(INDEX(TRANSACCIONES!$A$2:$A$1000,SMALL(IF(UPPER(TRANSACCIONES!$L$2:$L$1000)="POR COBRAR",ROW(TRANSACCIONES!$L$2:$L$1000)-ROW(TRANSACCIONES!$L$2)+1),42)),"") | B47: =IFERROR(INDEX(TRANSACCIONES!$E$2:$E$1000,SMALL(IF(UPPER(TRANSACCIONES!$L$2:$L$1000)="POR COBRAR",ROW(TRANSACCIONES!$L$2:$L$1000)-ROW(TRANSACCIONES!$L$2)+1),42)),"") | C47: =IFERROR(INDEX(TRANSACCIONES!$F$2:$F$1000,SMALL(IF(UPPER(TRANSACCIONES!$L$2:$L$1000)="POR COBRAR",ROW(TRANSACCIONES!$L$2:$L$1000)-ROW(TRANSACCIONES!$L$2)+1),42)),"") | D47: =IFERROR(INDEX(TRANSACCIONES!$I$2:$I$1000,SMALL(IF(UPPER(TRANSACCIONES!$L$2:$L$1000)="POR COBRAR",ROW(TRANSACCIONES!$L$2:$L$1000)-ROW(TRANSACCIONES!$L$2)+1),42)),"") | E47: =IFERROR(INDEX(TRANSACCIONES!$N$2:$N$1000,SMALL(IF(UPPER(TRANSACCIONES!$L$2:$L$1000)="POR COBRAR",ROW(TRANSACCIONES!$L$2:$L$1000)-ROW(TRANSACCIONES!$L$2)+1),42)),"") | F47: =IF(A47="","",TODAY()-A47) | G47: =IF(A47="","",IF(E47<TODAY(),"VENCIDO",IF(E47<=TODAY()+7,"POR VENCER","AL DÍA"))) | H47: =IFERROR(INDEX(TRANSACCIONES!$K$2:$K$1000,SMALL(IF(UPPER(TRANSACCIONES!$L$2:$L$1000)="POR COBRAR",ROW(TRANSACCIONES!$L$2:$L$1000)-ROW(TRANSACCIONES!$L$2)+1),42)),"")
A48: =IFERROR(INDEX(TRANSACCIONES!$A$2:$A$1000,SMALL(IF(UPPER(TRANSACCIONES!$L$2:$L$1000)="POR COBRAR",ROW(TRANSACCIONES!$L$2:$L$1000)-ROW(TRANSACCIONES!$L$2)+1),43)),"") | B48: =IFERROR(INDEX(TRANSACCIONES!$E$2:$E$1000,SMALL(IF(UPPER(TRANSACCIONES!$L$2:$L$1000)="POR COBRAR",ROW(TRANSACCIONES!$L$2:$L$1000)-ROW(TRANSACCIONES!$L$2)+1),43)),"") | C48: =IFERROR(INDEX(TRANSACCIONES!$F$2:$F$1000,SMALL(IF(UPPER(TRANSACCIONES!$L$2:$L$1000)="POR COBRAR",ROW(TRANSACCIONES!$L$2:$L$1000)-ROW(TRANSACCIONES!$L$2)+1),43)),"") | D48: =IFERROR(INDEX(TRANSACCIONES!$I$2:$I$1000,SMALL(IF(UPPER(TRANSACCIONES!$L$2:$L$1000)="POR COBRAR",ROW(TRANSACCIONES!$L$2:$L$1000)-ROW(TRANSACCIONES!$L$2)+1),43)),"") | E48: =IFERROR(INDEX(TRANSACCIONES!$N$2:$N$1000,SMALL(IF(UPPER(TRANSACCIONES!$L$2:$L$1000)="POR COBRAR",ROW(TRANSACCIONES!$L$2:$L$1000)-ROW(TRANSACCIONES!$L$2)+1),43)),"") | F48: =IF(A48="","",TODAY()-A48) | G48: =IF(A48="","",IF(E48<TODAY(),"VENCIDO",IF(E48<=TODAY()+7,"POR VENCER","AL DÍA"))) | H48: =IFERROR(INDEX(TRANSACCIONES!$K$2:$K$1000,SMALL(IF(UPPER(TRANSACCIONES!$L$2:$L$1000)="POR COBRAR",ROW(TRANSACCIONES!$L$2:$L$1000)-ROW(TRANSACCIONES!$L$2)+1),43)),"")
A49: =IFERROR(INDEX(TRANSACCIONES!$A$2:$A$1000,SMALL(IF(UPPER(TRANSACCIONES!$L$2:$L$1000)="POR COBRAR",ROW(TRANSACCIONES!$L$2:$L$1000)-ROW(TRANSACCIONES!$L$2)+1),44)),"") | B49: =IFERROR(INDEX(TRANSACCIONES!$E$2:$E$1000,SMALL(IF(UPPER(TRANSACCIONES!$L$2:$L$1000)="POR COBRAR",ROW(TRANSACCIONES!$L$2:$L$1000)-ROW(TRANSACCIONES!$L$2)+1),44)),"") | C49: =IFERROR(INDEX(TRANSACCIONES!$F$2:$F$1000,SMALL(IF(UPPER(TRANSACCIONES!$L$2:$L$1000)="POR COBRAR",ROW(TRANSACCIONES!$L$2:$L$1000)-ROW(TRANSACCIONES!$L$2)+1),44)),"") | D49: =IFERROR(INDEX(TRANSACCIONES!$I$2:$I$1000,SMALL(IF(UPPER(TRANSACCIONES!$L$2:$L$1000)="POR COBRAR",ROW(TRANSACCIONES!$L$2:$L$1000)-ROW(TRANSACCIONES!$L$2)+1),44)),"") | E49: =IFERROR(INDEX(TRANSACCIONES!$N$2:$N$1000,SMALL(IF(UPPER(TRANSACCIONES!$L$2:$L$1000)="POR COBRAR",ROW(TRANSACCIONES!$L$2:$L$1000)-ROW(TRANSACCIONES!$L$2)+1),44)),"") | F49: =IF(A49="","",TODAY()-A49) | G49: =IF(A49="","",IF(E49<TODAY(),"VENCIDO",IF(E49<=TODAY()+7,"POR VENCER","AL DÍA"))) | H49: =IFERROR(INDEX(TRANSACCIONES!$K$2:$K$1000,SMALL(IF(UPPER(TRANSACCIONES!$L$2:$L$1000)="POR COBRAR",ROW(TRANSACCIONES!$L$2:$L$1000)-ROW(TRANSACCIONES!$L$2)+1),44)),"")
A50: =IFERROR(INDEX(TRANSACCIONES!$A$2:$A$1000,SMALL(IF(UPPER(TRANSACCIONES!$L$2:$L$1000)="POR COBRAR",ROW(TRANSACCIONES!$L$2:$L$1000)-ROW(TRANSACCIONES!$L$2)+1),45)),"") | B50: =IFERROR(INDEX(TRANSACCIONES!$E$2:$E$1000,SMALL(IF(UPPER(TRANSACCIONES!$L$2:$L$1000)="POR COBRAR",ROW(TRANSACCIONES!$L$2:$L$1000)-ROW(TRANSACCIONES!$L$2)+1),45)),"") | C50: =IFERROR(INDEX(TRANSACCIONES!$F$2:$F$1000,SMALL(IF(UPPER(TRANSACCIONES!$L$2:$L$1000)="POR COBRAR",ROW(TRANSACCIONES!$L$2:$L$1000)-ROW(TRANSACCIONES!$L$2)+1),45)),"") | D50: =IFERROR(INDEX(TRANSACCIONES!$I$2:$I$1000,SMALL(IF(UPPER(TRANSACCIONES!$L$2:$L$1000)="POR COBRAR",ROW(TRANSACCIONES!$L$2:$L$1000)-ROW(TRANSACCIONES!$L$2)+1),45)),"") | E50: =IFERROR(INDEX(TRANSACCIONES!$N$2:$N$1000,SMALL(IF(UPPER(TRANSACCIONES!$L$2:$L$1000)="POR COBRAR",ROW(TRANSACCIONES!$L$2:$L$1000)-ROW(TRANSACCIONES!$L$2)+1),45)),"") | F50: =IF(A50="","",TODAY()-A50) | G50: =IF(A50="","",IF(E50<TODAY(),"VENCIDO",IF(E50<=TODAY()+7,"POR VENCER","AL DÍA"))) | H50: =IFERROR(INDEX(TRANSACCIONES!$K$2:$K$1000,SMALL(IF(UPPER(TRANSACCIONES!$L$2:$L$1000)="POR COBRAR",ROW(TRANSACCIONES!$L$2:$L$1000)-ROW(TRANSACCIONES!$L$2)+1),45)),"")
A51: =IFERROR(INDEX(TRANSACCIONES!$A$2:$A$1000,SMALL(IF(UPPER(TRANSACCIONES!$L$2:$L$1000)="POR COBRAR",ROW(TRANSACCIONES!$L$2:$L$1000)-ROW(TRANSACCIONES!$L$2)+1),46)),"") | B51: =IFERROR(INDEX(TRANSACCIONES!$E$2:$E$1000,SMALL(IF(UPPER(TRANSACCIONES!$L$2:$L$1000)="POR COBRAR",ROW(TRANSACCIONES!$L$2:$L$1000)-ROW(TRANSACCIONES!$L$2)+1),46)),"") | C51: =IFERROR(INDEX(TRANSACCIONES!$F$2:$F$1000,SMALL(IF(UPPER(TRANSACCIONES!$L$2:$L$1000)="POR COBRAR",ROW(TRANSACCIONES!$L$2:$L$1000)-ROW(TRANSACCIONES!$L$2)+1),46)),"") | D51: =IFERROR(INDEX(TRANSACCIONES!$I$2:$I$1000,SMALL(IF(UPPER(TRANSACCIONES!$L$2:$L$1000)="POR COBRAR",ROW(TRANSACCIONES!$L$2:$L$1000)-ROW(TRANSACCIONES!$L$2)+1),46)),"") | E51: =IFERROR(INDEX(TRANSACCIONES!$N$2:$N$1000,SMALL(IF(UPPER(TRANSACCIONES!$L$2:$L$1000)="POR COBRAR",ROW(TRANSACCIONES!$L$2:$L$1000)-ROW(TRANSACCIONES!$L$2)+1),46)),"") | F51: =IF(A51="","",TODAY()-A51) | G51: =IF(A51="","",IF(E51<TODAY(),"VENCIDO",IF(E51<=TODAY()+7,"POR VENCER","AL DÍA"))) | H51: =IFERROR(INDEX(TRANSACCIONES!$K$2:$K$1000,SMALL(IF(UPPER(TRANSACCIONES!$L$2:$L$1000)="POR COBRAR",ROW(TRANSACCIONES!$L$2:$L$1000)-ROW(TRANSACCIONES!$L$2)+1),46)),"")
A52: =IFERROR(INDEX(TRANSACCIONES!$A$2:$A$1000,SMALL(IF(UPPER(TRANSACCIONES!$L$2:$L$1000)="POR COBRAR",ROW(TRANSACCIONES!$L$2:$L$1000)-ROW(TRANSACCIONES!$L$2)+1),47)),"") | B52: =IFERROR(INDEX(TRANSACCIONES!$E$2:$E$1000,SMALL(IF(UPPER(TRANSACCIONES!$L$2:$L$1000)="POR COBRAR",ROW(TRANSACCIONES!$L$2:$L$1000)-ROW(TRANSACCIONES!$L$2)+1),47)),"") | C52: =IFERROR(INDEX(TRANSACCIONES!$F$2:$F$1000,SMALL(IF(UPPER(TRANSACCIONES!$L$2:$L$1000)="POR COBRAR",ROW(TRANSACCIONES!$L$2:$L$1000)-ROW(TRANSACCIONES!$L$2)+1),47)),"") | D52: =IFERROR(INDEX(TRANSACCIONES!$I$2:$I$1000,SMALL(IF(UPPER(TRANSACCIONES!$L$2:$L$1000)="POR COBRAR",ROW(TRANSACCIONES!$L$2:$L$1000)-ROW(TRANSACCIONES!$L$2)+1),47)),"") | E52: =IFERROR(INDEX(TRANSACCIONES!$N$2:$N$1000,SMALL(IF(UPPER(TRANSACCIONES!$L$2:$L$1000)="POR COBRAR",ROW(TRANSACCIONES!$L$2:$L$1000)-ROW(TRANSACCIONES!$L$2)+1),47)),"") | F52: =IF(A52="","",TODAY()-A52) | G52: =IF(A52="","",IF(E52<TODAY(),"VENCIDO",IF(E52<=TODAY()+7,"POR VENCER","AL DÍA"))) | H52: =IFERROR(INDEX(TRANSACCIONES!$K$2:$K$1000,SMALL(IF(UPPER(TRANSACCIONES!$L$2:$L$1000)="POR COBRAR",ROW(TRANSACCIONES!$L$2:$L$1000)-ROW(TRANSACCIONES!$L$2)+1),47)),"")
A53: =IFERROR(INDEX(TRANSACCIONES!$A$2:$A$1000,SMALL(IF(UPPER(TRANSACCIONES!$L$2:$L$1000)="POR COBRAR",ROW(TRANSACCIONES!$L$2:$L$1000)-ROW(TRANSACCIONES!$L$2)+1),48)),"") | B53: =IFERROR(INDEX(TRANSACCIONES!$E$2:$E$1000,SMALL(IF(UPPER(TRANSACCIONES!$L$2:$L$1000)="POR COBRAR",ROW(TRANSACCIONES!$L$2:$L$1000)-ROW(TRANSACCIONES!$L$2)+1),48)),"") | C53: =IFERROR(INDEX(TRANSACCIONES!$F$2:$F$1000,SMALL(IF(UPPER(TRANSACCIONES!$L$2:$L$1000)="POR COBRAR",ROW(TRANSACCIONES!$L$2:$L$1000)-ROW(TRANSACCIONES!$L$2)+1),48)),"") | D53: =IFERROR(INDEX(TRANSACCIONES!$I$2:$I$1000,SMALL(IF(UPPER(TRANSACCIONES!$L$2:$L$1000)="POR COBRAR",ROW(TRANSACCIONES!$L$2:$L$1000)-ROW(TRANSACCIONES!$L$2)+1),48)),"") | E53: =IFERROR(INDEX(TRANSACCIONES!$N$2:$N$1000,SMALL(IF(UPPER(TRANSACCIONES!$L$2:$L$1000)="POR COBRAR",ROW(TRANSACCIONES!$L$2:$L$1000)-ROW(TRANSACCIONES!$L$2)+1),48)),"") | F53: =IF(A53="","",TODAY()-A53) | G53: =IF(A53="","",IF(E53<TODAY(),"VENCIDO",IF(E53<=TODAY()+7,"POR VENCER","AL DÍA"))) | H53: =IFERROR(INDEX(TRANSACCIONES!$K$2:$K$1000,SMALL(IF(UPPER(TRANSACCIONES!$L$2:$L$1000)="POR COBRAR",ROW(TRANSACCIONES!$L$2:$L$1000)-ROW(TRANSACCIONES!$L$2)+1),48)),"")
A54: =IFERROR(INDEX(TRANSACCIONES!$A$2:$A$1000,SMALL(IF(UPPER(TRANSACCIONES!$L$2:$L$1000)="POR COBRAR",ROW(TRANSACCIONES!$L$2:$L$1000)-ROW(TRANSACCIONES!$L$2)+1),49)),"") | B54: =IFERROR(INDEX(TRANSACCIONES!$E$2:$E$1000,SMALL(IF(UPPER(TRANSACCIONES!$L$2:$L$1000)="POR COBRAR",ROW(TRANSACCIONES!$L$2:$L$1000)-ROW(TRANSACCIONES!$L$2)+1),49)),"") | C54: =IFERROR(INDEX(TRANSACCIONES!$F$2:$F$1000,SMALL(IF(UPPER(TRANSACCIONES!$L$2:$L$1000)="POR COBRAR",ROW(TRANSACCIONES!$L$2:$L$1000)-ROW(TRANSACCIONES!$L$2)+1),49)),"") | D54: =IFERROR(INDEX(TRANSACCIONES!$I$2:$I$1000,SMALL(IF(UPPER(TRANSACCIONES!$L$2:$L$1000)="POR COBRAR",ROW(TRANSACCIONES!$L$2:$L$1000)-ROW(TRANSACCIONES!$L$2)+1),49)),"") | E54: =IFERROR(INDEX(TRANSACCIONES!$N$2:$N$1000,SMALL(IF(UPPER(TRANSACCIONES!$L$2:$L$1000)="POR COBRAR",ROW(TRANSACCIONES!$L$2:$L$1000)-ROW(TRANSACCIONES!$L$2)+1),49)),"") | F54: =IF(A54="","",TODAY()-A54) | G54: =IF(A54="","",IF(E54<TODAY(),"VENCIDO",IF(E54<=TODAY()+7,"POR VENCER","AL DÍA"))) | H54: =IFERROR(INDEX(TRANSACCIONES!$K$2:$K$1000,SMALL(IF(UPPER(TRANSACCIONES!$L$2:$L$1000)="POR COBRAR",ROW(TRANSACCIONES!$L$2:$L$1000)-ROW(TRANSACCIONES!$L$2)+1),49)),"")
A55: =IFERROR(INDEX(TRANSACCIONES!$A$2:$A$1000,SMALL(IF(UPPER(TRANSACCIONES!$L$2:$L$1000)="POR COBRAR",ROW(TRANSACCIONES!$L$2:$L$1000)-ROW(TRANSACCIONES!$L$2)+1),50)),"") | B55: =IFERROR(INDEX(TRANSACCIONES!$E$2:$E$1000,SMALL(IF(UPPER(TRANSACCIONES!$L$2:$L$1000)="POR COBRAR",ROW(TRANSACCIONES!$L$2:$L$1000)-ROW(TRANSACCIONES!$L$2)+1),50)),"") | C55: =IFERROR(INDEX(TRANSACCIONES!$F$2:$F$1000,SMALL(IF(UPPER(TRANSACCIONES!$L$2:$L$1000)="POR COBRAR",ROW(TRANSACCIONES!$L$2:$L$1000)-ROW(TRANSACCIONES!$L$2)+1),50)),"") | D55: =IFERROR(INDEX(TRANSACCIONES!$I$2:$I$1000,SMALL(IF(UPPER(TRANSACCIONES!$L$2:$L$1000)="POR COBRAR",ROW(TRANSACCIONES!$L$2:$L$1000)-ROW(TRANSACCIONES!$L$2)+1),50)),"") | E55: =IFERROR(INDEX(TRANSACCIONES!$N$2:$N$1000,SMALL(IF(UPPER(TRANSACCIONES!$L$2:$L$1000)="POR COBRAR",ROW(TRANSACCIONES!$L$2:$L$1000)-ROW(TRANSACCIONES!$L$2)+1),50)),"") | F55: =IF(A55="","",TODAY()-A55) | G55: =IF(A55="","",IF(E55<TODAY(),"VENCIDO",IF(E55<=TODAY()+7,"POR VENCER","AL DÍA"))) | H55: =IFERROR(INDEX(TRANSACCIONES!$K$2:$K$1000,SMALL(IF(UPPER(TRANSACCIONES!$L$2:$L$1000)="POR COBRAR",ROW(TRANSACCIONES!$L$2:$L$1000)-ROW(TRANSACCIONES!$L$2)+1),50)),"")

Sheet ENTIDADES_ALIAS
A1: Alias | B1: Entidad Real | C1: Tipo | D1: Notas
A2: XXXXXXXXXX1066X | B2: BNCR Cuenta Corriente Colones | C2: Cuenta | D2: Cuenta corriente BNCR en colones (enmascarada)
A3: XXXXXXXXXX8618X | B3: BNCR Cuenta Corriente Dólares | C3: Cuenta | D3: Cuenta corriente BNCR en dólares (enmascarada)
A4: BNCR CRC Ahorros (***8618) | B4: BNCR Ahorros Colones | C4: Cuenta | D4: Cuenta de ahorros BNCR en colones
A5: BNCR USD Ahorros (***1066) | B5: BNCR Ahorros Dólares | C5: Cuenta | D5: Cuenta de ahorros BNCR en dólares
A6: BNCR CRC Corriente (***2186) | B6: BNCR Cuenta Corriente Colones 2186 | C6: Cuenta | D6: Cuenta corriente BNCR en colones
A7: BNCR USD Corriente (***9589) | B7: BNCR Cuenta Corriente Dólares 9589 | C7: Cuenta | D7: Cuenta corriente BNCR en dólares
A8: BNCR USD Corriente (***1112) | B8: BNCR Cuenta Corriente Dólares 1112 | C8: Cuenta | D8: Cuenta corriente BNCR en dólares (alternativa)
A9: XXXX-XXXX-XXXX-1234 | B9: Tarjeta Visa BAC 1234 | C9: Tarjeta | D9: Tarjeta de crédito BAC Visa
A10: XXXX-XXXX-XXXX-5678 | B10: Tarjeta MasterCard BAC 5678 | C10: Tarjeta | D10: Tarjeta de crédito BAC MasterCard
A11: ICE | B11: Instituto Costarricense de Electricidad | C11: Proveedor | D11: Servicios eléctricos y telecomunicaciones
A12: KOLBI | B12: Instituto Costarricense de Electricidad - Kolbi | C12: Proveedor | D12: Servicios de telecomunicaciones móviles
A13: Credomatic | B13: Tarjeta Credomatic | C13: Tarjeta | D13: Tarjeta de crédito Credomatic - Pago: 15/11/2025

Sheet ESTADO_RESULTADOS
A1: ESTADO DE RESULTADOS (P&L)
A2: AlvaroVelascoNet SRL - Período: November 2025
A4: CONCEPTO | B4: MONTO (₡) | C4: MONTO ($)
A5: 📈 INGRESOS
A6: Ventas de Servicios | B6: =SUMIFS(TRANSACCIONES!I:I,TRANSACCIONES!C:C,"INGRESO",TRANSACCIONES!L:L,"COBRADO",TRANSACCIONES!D:D,"Ingresos") | C6: =B6/540
A7: Otros Ingresos | B7: =SUMIFS(TRANSACCIONES!I:I,TRANSACCIONES!C:C,"INGRESO",TRANSACCIONES!L:L,"COBRADO",TRANSACCIONES!D:D,"<>Ingresos") | C7: =B7/540
A8: TOTAL INGRESOS | B8: =SUM(B6:B7) | C8: =B8/540
A10: 📉 GASTOS OPERATIVOS
A11: Operaciones | B11: =SUMIFS(TRANSACCIONES!I:I,TRANSACCIONES!C:C,"EGRESO",TRANSACCIONES!L:L,"PAGADO",TRANSACCIONES!D:D,"Operaciones") | C11: =B11/540
A12: Administrativos | B12: =SUMIFS(TRANSACCIONES!I:I,TRANSACCIONES!C:C,"EGRESO",TRANSACCIONES!L:L,"PAGADO",TRANSACCIONES!D:D,"Administrativos") | C12: =B12/540
A13: Ventas | B13: =SUMIFS(TRANSACCIONES!I:I,TRANSACCIONES!C:C,"EGRESO",TRANSACCIONES!L:L,"PAGADO",TRANSACCIONES!D:D,"Ventas") | C13: =B13/540
A14: Financieros | B14: =SUMIFS(TRANSACCIONES!I:I,TRANSACCIONES!C:C,"EGRESO",TRANSACCIONES!L:L,"PAGADO",TRANSACCIONES!D:D,"Financieros") | C14: =B14/540
A15: TOTAL GASTOS | B15: =SUM(B11:B14) | C15: =B15/540
A17: 💰 UTILIDAD/PÉRDIDA NETA
A18: RESULTADO DEL PERÍODO | B18: =B8-ABS(B15) | C18: =B18/540

Sheet BALANCE_GENERAL
A1: BALANCE GENERAL
A2: AlvaroVelascoNet SRL - Al 14/11/2025
A4: CONCEPTO | B4: MONTO (₡) | C4: MONTO ($)
A5: 📊 ACTIVOS
A6: Efectivo en Bancos | B6: =SUMIFS(TRANSACCIONES!I:I,TRANSACCIONES!L:L,"PAGADO",TRANSACCIONES!C:C,"INGRESO")-SUMIFS(TRANSACCIONES!I:I,TRANSACCIONES!L:L,"PAGADO",TRANSACCIONES!C:C,"EGRESO") | C6: =B6/540
A7: Cuentas por Cobrar | B7: =SUMIFS(TRANSACCIONES!I:I,TRANSACCIONES!C:C,"INGRESO",TRANSACCIONES!L:L,"POR COBRAR") | C7: =B7/540
A8: TOTAL ACTIVOS | B8: =SUM(B6:B7) | C8: =B8/540
A10: 📉 PASIVOS
A11: Cuentas por Pagar | B11: =ABS(SUMIFS(TRANSACCIONES!I:I,TRANSACCIONES!C:C,"EGRESO",TRANSACCIONES!L:L,"PENDIENTE")) | C11: =B11/540
A12: (incluye Tarjetas de Crédito)
A13: TOTAL PASIVOS | B13: =B11 | C13: =B13/540
A15: 💼 PATRIMONIO
A16: Patrimonio Neto | B16: =B8-B13 | C16: =B16/540

Sheet FLUJO_CAJA
A1: FLUJO DE CAJA
A2: AlvaroVelascoNet SRL - Período: November 2025
A4: CONCEPTO | B4: MONTO (₡) | C4: MONTO ($)
A5: 📈 ENTRADAS DE EFECTIVO
A6: Cobros de Ventas | B6: =SUMIFS(TRANSACCIONES!I:I,TRANSACCIONES!C:C,"INGRESO",TRANSACCIONES!L:L,"COBRADO") | C6: =B6/540
A7: Otros Ingresos | B7: =0 | C7: =B7/540
A8: TOTAL ENTRADAS | B8: =SUM(B6:B7) | C8: =B8/540
A10: 📉 SALIDAS DE EFECTIVO
A11: Pagos a Proveedores | B11: =ABS(SUMIFS(TRANSACCIONES!I:I,TRANSACCIONES!C:C,"EGRESO",TRANSACCIONES!L:L,"PAGADO")) | C11: =B11/540
A12: Gastos Operativos | B12: =0 | C12: =B12/540
A13: TOTAL SALIDAS | B13: =SUM(B11:B12) | C13: =B13/540
A15: 💰 FLUJO NETO DE CAJA
A16: FLUJO DEL PERÍODO | B16: =B8-B13 | C16: =B16/540

Sheet DASHBOARD_VISUAL
A1: 📊 DASHBOARD FINANCIERO
A2: Actualizado: 14/11/2025 17:47
A4: EFECTIVO DISPONIBLE | E4: CUENTAS POR COBRAR | I4: CUENTAS POR PAGAR
A5: =SUMIFS(TRANSACCIONES!I:I,TRANSACCIONES!L:L,"PAGADO",TRANSACCIONES!C:C,"INGRESO")-SUMIFS(TRANSACCIONES!I:I,TRANSACCIONES!L:L,"PAGADO",TRANSACCIONES!C:C,"EGRESO") | E5: =SUMIFS(TRANSACCIONES!I:I,TRANSACCIONES!C:C,"INGRESO",TRANSACCIONES!L:L,"POR COBRAR") | I5: =ABS(SUMIFS(TRANSACCIONES!I:I,TRANSACCIONES!C:C,"EGRESO",TRANSACCIONES!L:L,"PENDIENTE"))
A7: INGRESOS DEL MES | E7: GASTOS DEL MES | I7: UTILIDAD/PÉRDIDA
A8: =SUMIFS(TRANSACCIONES!I:I,TRANSACCIONES!C:C,"INGRESO",TRANSACCIONES!L:L,"COBRADO") | E8: =ABS(SUMIFS(TRANSACCIONES!I:I,TRANSACCIONES!C:C,"EGRESO",TRANSACCIONES!L:L,"PAGADO")) | I8: =A8-E8
A11: CONCEPTO | B11: MONTO
A12: Ingresos | B12: =A7
A13: Gastos | B13: =E7
A31: ⚠️ ALERTAS Y NOTIFICACIONES
A32: CxP vencen en 7 días: | B32: =COUNTIFS(CxP!F:F,"<"&TODAY()+7,CxP!F:F,">="&TODAY())
A33: CxP VENCIDAS: | B33: =COUNTIF(CxP!F:F,"<"&TODAY())
A34: CxC atrasadas (+30 días): | B34: =COUNTIF(CxC!F:F,"<"&TODAY()-30)

Sheet CONCILIACION
A1: CONCILIACIÓN BANCARIA
A2: Fecha: 14/11/2025
A4: 📋 INSTRUCCIONES:
A5: 1. Ingresa el saldo según tu extracto bancario en la columna "Saldo Extracto"
A6: 2. El sistema calculará automáticamente el saldo según transacciones
A7: 3. La columna "Diferencia" mostrará cualquier discrepancia
A8: 4. Investiga las diferencias (pueden ser transacciones en tránsito o errores)
A10: 💡 TIPS:
A11: - Verde = Saldos coinciden
A12: - Rojo = Hay diferencia (revisar)
A13: - Considera cheques no cobrados y depósitos en tránsito
A15: CUENTA | B15: SALDO SISTEMA (₡) | C15: SALDO EXTRACTO (₡) | D15: DIFERENCIA (₡) | E15: STATUS
A16: BNCR Ahorros Colones (***8618) | B16: =SUMIFS(TRANSACCIONES!I:I,TRANSACCIONES!G:G,A16,TRANSACCIONES!L:L,"PAGADO",TRANSACCIONES!C:C,"INGRESO")-SUMIFS(TRANSACCIONES!I:I,TRANSACCIONES!G:G,A16,TRANSACCIONES!L:L,"PAGADO",TRANSACCIONES!C:C,"EGRESO") | D16: =C16-B16 | E16: =IF(C16="","Pendiente",IF(ABS(D16)<1,"✅ OK","⚠️ Revisar"))
A17: BNCR Ahorros Dólares (***1066) | B17: =SUMIFS(TRANSACCIONES!I:I,TRANSACCIONES!G:G,A17,TRANSACCIONES!L:L,"PAGADO",TRANSACCIONES!C:C,"INGRESO")-SUMIFS(TRANSACCIONES!I:I,TRANSACCIONES!G:G,A17,TRANSACCIONES!L:L,"PAGADO",TRANSACCIONES!C:C,"EGRESO") | D17: =C17-B17 | E17: =IF(C17="","Pendiente",IF(ABS(D17)<1,"✅ OK","⚠️ Revisar"))
A18: BNCR CC Colones (***2186) | B18: =SUMIFS(TRANSACCIONES!I:I,TRANSACCIONES!G:G,A18,TRANSACCIONES!L:L,"PAGADO",TRANSACCIONES!C:C,"INGRESO")-SUMIFS(TRANSACCIONES!I:I,TRANSACCIONES!G:G,A18,TRANSACCIONES!L:L,"PAGADO",TRANSACCIONES!C:C,"EGRESO") | D18: =C18-B18 | E18: =IF(C18="","Pendiente",IF(ABS(D18)<1,"✅ OK","⚠️ Revisar"))
A19: BNCR CC Dólares (***9589) | B19: =SUMIFS(TRANSACCIONES!I:I,TRANSACCIONES!G:G,A19,TRANSACCIONES!L:L,"PAGADO",TRANSACCIONES!C:C,"INGRESO")-SUMIFS(TRANSACCIONES!I:I,TRANSACCIONES!G:G,A19,TRANSACCIONES!L:L,"PAGADO",TRANSACCIONES!C:C,"EGRESO") | D19: =C19-B19 | E19: =IF(C19="","Pendiente",IF(ABS(D19)<1,"✅ OK","⚠️ Revisar"))
A20: BNCR CC Dólares (***1112) | B20: =SUMIFS(TRANSACCIONES!I:I,TRANSACCIONES!G:G,A20,TRANSACCIONES!L:L,"PAGADO",TRANSACCIONES!C:C,"INGRESO")-SUMIFS(TRANSACCIONES!I:I,TRANSACCIONES!G:G,A20,TRANSACCIONES!L:L,"PAGADO",TRANSACCIONES!C:C,"EGRESO") | D20: =C20-B20 | E20: =IF(C20="","Pendiente",IF(ABS(D20)<1,"✅ OK","⚠️ Revisar"))
A21: Promerica SINPE Colones (***1708) | B21: =SUMIFS(TRANSACCIONES!I:I,TRANSACCIONES!G:G,A21,TRANSACCIONES!L:L,"PAGADO",TRANSACCIONES!C:C,"INGRESO")-SUMIFS(TRANSACCIONES!I:I,TRANSACCIONES!G:G,A21,TRANSACCIONES!L:L,"PAGADO",TRANSACCIONES!C:C,"EGRESO") | D21: =C21-B21 | E21: =IF(C21="","Pendiente",IF(ABS(D21)<1,"✅ OK","⚠️ Revisar"))
A22: Promerica CC Corporativa Dólares (***1774) | B22: =SUMIFS(TRANSACCIONES!I:I,TRANSACCIONES!G:G,A22,TRANSACCIONES!L:L,"PAGADO",TRANSACCIONES!C:C,"INGRESO")-SUMIFS(TRANSACCIONES!I:I,TRANSACCIONES!G:G,A22,TRANSACCIONES!L:L,"PAGADO",TRANSACCIONES!C:C,"EGRESO") | D22: =C22-B22 | E22: =IF(C22="","Pendiente",IF(ABS(D22)<1,"✅ OK","⚠️ Revisar"))
A25: 📊 RESUMEN
A26: Total Saldo Sistema: | B26: =SUM(B16:B23)
A27: Total Saldo Extractos: | B27: =SUM(C16:C24)
A28: DIFERENCIA TOTAL: | B28: =B27-B26
A30: Cuentas conciliadas: | B30: =COUNTIF(E16:E26,"✅ OK")
A31: Cuentas con diferencias: | B31: =COUNTIF(E16:E27,"⚠️ Revisar")
A34: 🔄 TRANSACCIONES EN TRÁNSITO
A35: Posibles causas de diferencias:
A36: • Cheques emitidos no cobrados
A37: • Depósitos en tránsito
A38: • Cargos bancarios no registrados
A39: • Intereses no contabilizados
A40: • Errores de captura
A41: • Transacciones del extracto no ingresadas al sistema

Sheet CONFIG
A1: CONFIGURACIONES DEL SISTEMA v4.0
A3: 💱 TIPO DE CAMBIO
A4: Tipo de Cambio Actual (USD → CRC) | B4: Valor | C4: Fecha
A5: TC USD a CRC | B5: 540 | C5: 45975.741
A7: 💳 FECHAS DE PAGO TARJETAS DE CRÉDITO
A8: Tarjeta | B8: Día de Pago | C8: Límite | D8: Entidad
A9: Visa Clásica BNCR (***3519) | B9: 17 | C9: $1,200.00 | D9: BNCR
A10: Visa Platino BNCR (***8055) | B10: 5 | C10: $1,600.00 | D10: BNCR
A11: MasterCard Oro BNCR (***9208) | B11: 13 | C11: $5,000.00 | D11: BNCR
A12: Credomatic (***XXXX) | B12: 15 | C12: Por definir | D12: Credomatic
A14: ⚙️ CONFIGURACIONES GENERALES
A15: Configuración | B15: Valor | C15: Descripción
A16: Empresa | B16: AV Business Solutions | C16: Nombre de la empresa principal
A17: Propietario | B17: Álvaro Velasco | C17: Propietario del negocio
A18: Moneda Base | B18: CRC | C18: Moneda base para reportes
A19: Tasa IVA (%) | B19: 13 | C19: Tasa de IVA en Costa Rica
A20: Días alerta CxP | B20: 7 | C20: Días antes de vencimiento para alertas
A21: Días alerta CxC | B21: 15 | C21: Días después de vencimiento para alertas
A23: 🏭 EMPRESAS ZONA FRANCA (EXENTAS DE IVA)
A24: Empresa | B24: Nombre Completo | D24: Notas
A25: VWR | B25: VWR Internacional Ltda | D25: Zona franca - NO cobra IVA
A26: RS Hughes | B26: RS Hughes Co. | D26: Zona franca - NO cobra IVA
A28: 📋 INSTRUCCIONES DE USO
A29: ✅ Esta hoja NO está protegida - puedes editar las celdas amarillas
A30: 💡 Actualiza el tipo de cambio periódicamente para cálculos precisos
A31: 📅 Verifica las fechas de pago de tarjetas mensualmente
A32: 🏭 Las empresas de zona franca (VWR, RS Hughes) NO pagan IVA
A33: ⚠️ NO modifiques las fórmulas en otras hojas que referencian esta CONFIG

Sheet IVA_CONTROL
A1: CONTROL DE IVA - DECLARACIÓN FISCAL
A2: Reporte generado: 14/11/2025 17:47
A4: 📊 RESUMEN IVA
A5: Concepto | B5: Monto | C5: IVA (13%) | D5: Estado
A6: ✅ IVA Compras (Crédito Fiscal) | B6: =SUMIFS(TRANSACCIONES!I:I,TRANSACCIONES!C:C,"EGRESO",TRANSACCIONES!L:L,"PAGADO")-SUMIFS(TRANSACCIONES!I:I,TRANSACCIONES!C:C,"EGRESO",TRANSACCIONES!L:L,"PAGADO",TRANSACCIONES!F:F,"VWR*")-SUMIFS(TRANSACCIONES!I:I,TRANSACCIONES!C:C,"EGRESO",TRANSACCIONES!L:L,"PAGADO",TRANSACCIONES!F:F,"RS Hughes*") | C6: =SUMIFS(TRANSACCIONES!M:M,TRANSACCIONES!C:C,"EGRESO",TRANSACCIONES!L:L,"PAGADO")-SUMIFS(TRANSACCIONES!M:M,TRANSACCIONES!C:C,"EGRESO",TRANSACCIONES!L:L,"PAGADO",TRANSACCIONES!F:F,"VWR*")-SUMIFS(TRANSACCIONES!M:M,TRANSACCIONES!C:C,"EGRESO",TRANSACCIONES!L:L,"PAGADO",TRANSACCIONES!F:F,"RS Hughes*") | D6: A favor del contribuyente
A7: 💰 IVA Ventas (Débito Fiscal) | B7: =SUMIFS(TRANSACCIONES!I:I,TRANSACCIONES!C:C,"INGRESO",TRANSACCIONES!L:L,"COBRADO") | C7: =SUMIFS(TRANSACCIONES!M:M,TRANSACCIONES!C:C,"INGRESO",TRANSACCIONES!L:L,"COBRADO") | D7: A pagar a Hacienda
A8: 📈 BALANCE IVA (Débito - Crédito) | C8: =C7-ABS(C6) | D8: =IF(C8>0,"A PAGAR",IF(C8<0,"A FAVOR","EN CERO"))
A10: 🏭 EMPRESAS ZONA FRANCA (EXENTAS DE IVA)
A11: Empresa | B11: Total Compras | C11: IVA (₡0) | D11: Estado
A12: VWR Internacional Ltda | B12: =SUMIFS(TRANSACCIONES!I:I,TRANSACCIONES!F:F,"VWR*",TRANSACCIONES!C:C,"EGRESO",TRANSACCIONES!L:L,"PAGADO") | C12: 0 | D12: EXENTO - Zona Franca
A13: RS Hughes Co. | B13: =SUMIFS(TRANSACCIONES!I:I,TRANSACCIONES!F:F,"RS Hughes*",TRANSACCIONES!C:C,"EGRESO",TRANSACCIONES!L:L,"PAGADO") | C13: 0 | D13: EXENTO - Zona Franca
A15: 📋 INSTRUCCIONES PARA DECLARACIÓN
A16: ✅ Revise el BALANCE IVA antes de hacer la declaración mensual
A17: 💡 Si el balance es positivo, debe PAGAR a Hacienda
A18: 💡 Si el balance es negativo, tiene CRÉDITO FISCAL para el siguiente mes
A19: 🏭 VWR y RS Hughes NO generan IVA (zona franca)
A20: ⚠️ Asegúrese de que todas las facturas en TRANSACCIONES tengan el IVA correctamente registrado en columna M
A21: 📅 La declaración de IVA se hace mensualmente (15 del mes siguiente)

Sheet PRESUPUESTO
A1: CONTROL PRESUPUESTARIO - PRESUPUESTO VS REAL
A3: 💰 PRESUPUESTO DE INGRESOS MENSUALES
A4: Categoría | B4: Presupuestado | C4: Real | D4: Variación | E4: % Ejecución | F4: Estado
A5: Ingresos | B5: 0 | C5: =SUMIFS(TRANSACCIONES!I:I,TRANSACCIONES!C:C,"INGRESO",TRANSACCIONES!L:L,"COBRADO",TRANSACCIONES!D:D,A5) | D5: =C5-B5 | E5: =IF(B5=0,0,C5/B5) | F5: =IF(B5=0,"Sin presupuesto",IF(E5>=1,"✅ Cumplido",IF(E5>=0.8,"⚠️ Por debajo","🔴 Crítico")))
A6: Ventas | B6: 0 | C6: =SUMIFS(TRANSACCIONES!I:I,TRANSACCIONES!C:C,"INGRESO",TRANSACCIONES!L:L,"COBRADO",TRANSACCIONES!D:D,A6) | D6: =C6-B6 | E6: =IF(B6=0,0,C6/B6) | F6: =IF(B6=0,"Sin presupuesto",IF(E6>=1,"✅ Cumplido",IF(E6>=0.8,"⚠️ Por debajo","🔴 Crítico")))
A7: Proyectos | B7: 0 | C7: =SUMIFS(TRANSACCIONES!I:I,TRANSACCIONES!C:C,"INGRESO",TRANSACCIONES!L:L,"COBRADO",TRANSACCIONES!D:D,A7) | D7: =C7-B7 | E7: =IF(B7=0,0,C7/B7) | F7: =IF(B7=0,"Sin presupuesto",IF(E7>=1,"✅ Cumplido",IF(E7>=0.8,"⚠️ Por debajo","🔴 Crítico")))
A8: Otros | B8: 0 | C8: =SUMIFS(TRANSACCIONES!I:I,TRANSACCIONES!C:C,"INGRESO",TRANSACCIONES!L:L,"COBRADO",TRANSACCIONES!D:D,A8) | D8: =C8-B8 | E8: =IF(B8=0,0,C8/B8) | F8: =IF(B8=0,"Sin presupuesto",IF(E8>=1,"✅ Cumplido",IF(E8>=0.8,"⚠️ Por debajo","🔴 Crítico")))
A9: TOTAL INGRESOS | B9: =SUM(B5:B8) | C9: =SUM(C5:C8) | D9: =C9-B9 | E9: =IF(B9=0,0,C9/B9)
A11: 💸 PRESUPUESTO DE GASTOS MENSUALES
A12: Categoría | B12: Presupuestado | C12: Real | D12: Variación | E12: % Ejecución | F12: Estado
A13: Operaciones | B13: 0 | C13: =ABS(SUMIFS(TRANSACCIONES!I:I,TRANSACCIONES!C:C,"EGRESO",TRANSACCIONES!L:L,"PAGADO",TRANSACCIONES!D:D,A13)) | D13: =B13-C13 | E13: =IF(B13=0,0,C13/B13) | F13: =IF(B13=0,"Sin presupuesto",IF(E13<=1,"✅ Dentro",IF(E13<=1.1,"⚠️ Excedido","🔴 Crítico")))
A14: Proyectos | B14: 0 | C14: =ABS(SUMIFS(TRANSACCIONES!I:I,TRANSACCIONES!C:C,"EGRESO",TRANSACCIONES!L:L,"PAGADO",TRANSACCIONES!D:D,A14)) | D14: =B14-C14 | E14: =IF(B14=0,0,C14/B14) | F14: =IF(B14=0,"Sin presupuesto",IF(E14<=1,"✅ Dentro",IF(E14<=1.1,"⚠️ Excedido","🔴 Crítico")))
A15: Administrativo | B15: 0 | C15: =ABS(SUMIFS(TRANSACCIONES!I:I,TRANSACCIONES!C:C,"EGRESO",TRANSACCIONES!L:L,"PAGADO",TRANSACCIONES!D:D,A15)) | D15: =B15-C15 | E15: =IF(B15=0,0,C15/B15) | F15: =IF(B15=0,"Sin presupuesto",IF(E15<=1,"✅ Dentro",IF(E15<=1.1,"⚠️ Excedido","🔴 Crítico")))
A16: Otros | B16: 0 | C16: =ABS(SUMIFS(TRANSACCIONES!I:I,TRANSACCIONES!C:C,"EGRESO",TRANSACCIONES!L:L,"PAGADO",TRANSACCIONES!D:D,A16)) | D16: =B16-C16 | E16: =IF(B16=0,0,C16/B16) | F16: =IF(B16=0,"Sin presupuesto",IF(E16<=1,"✅ Dentro",IF(E16<=1.1,"⚠️ Excedido","🔴 Crítico")))
A17: TOTAL GASTOS | B17: =SUM(B13:B16) | C17: =SUM(C13:C16) | D17: =B17-C17 | E17: =IF(B17=0,0,C17/B17)
A19: 📊 RESUMEN GENERAL
A20: Concepto | B20: Presupuestado | C20: Real | D20: Variación
A21: UTILIDAD NETA | B21: =B9-B17 | C21: =C9-C17 | D21: =C21-B21

Sheet PERSONAL_VS_NEGOCIO
A1: 🏢 ANÁLISIS: GASTOS PERSONALES VS NEGOCIO
A2: Objetivo: Sanear finanzas separando claramente lo personal de lo del negocio
A4: 📊 RESUMEN COMPARATIVO
A5: Tipo | B5: Total Ingresos | C5: Total Gastos | D5: Balance | E5: % del Total
A6: 🏢 NEGOCIO | B6: =SUMIFS(TRANSACCIONES!I:I,TRANSACCIONES!C:C,"INGRESO",TRANSACCIONES!P:P,"Negocio",TRANSACCIONES!L:L,"COBRADO") | C6: =ABS(SUMIFS(TRANSACCIONES!I:I,TRANSACCIONES!C:C,"EGRESO",TRANSACCIONES!P:P,"Negocio",TRANSACCIONES!L:L,"PAGADO")) | D6: =B6-C6 | E6: =C6/(C6+C7)
A7: 👤 PERSONAL (Álvaro) | B7: =SUMIFS(TRANSACCIONES!I:I,TRANSACCIONES!C:C,"INGRESO",TRANSACCIONES!P:P,"Personal",TRANSACCIONES!L:L,"COBRADO") | C7: =ABS(SUMIFS(TRANSACCIONES!I:I,TRANSACCIONES!C:C,"EGRESO",TRANSACCIONES!P:P,"Personal",TRANSACCIONES!L:L,"PAGADO")) | D7: =B7-C7 | E7: =C7/(C6+C7)
A8: TOTAL | B8: =B6+B7 | C8: =C6+C7 | D8: =D6+D7 | E8: 100%
A10: 📋 DESGLOSE DE GASTOS POR CATEGORÍA
A11: Categoría | B11: Negocio | C11: Personal | D11: Total | E11: % Personal
A12: Operaciones | B12: =ABS(SUMIFS(TRANSACCIONES!I:I,TRANSACCIONES!C:C,"EGRESO",TRANSACCIONES!D:D,A12,TRANSACCIONES!P:P,"Negocio",TRANSACCIONES!L:L,"PAGADO")) | C12: =ABS(SUMIFS(TRANSACCIONES!I:I,TRANSACCIONES!C:C,"EGRESO",TRANSACCIONES!D:D,A12,TRANSACCIONES!P:P,"Personal",TRANSACCIONES!L:L,"PAGADO")) | D12: =B12+C12 | E12: =IF(D12=0,0,C12/D12)
A13: Proyectos | B13: =ABS(SUMIFS(TRANSACCIONES!I:I,TRANSACCIONES!C:C,"EGRESO",TRANSACCIONES!D:D,A13,TRANSACCIONES!P:P,"Negocio",TRANSACCIONES!L:L,"PAGADO")) | C13: =ABS(SUMIFS(TRANSACCIONES!I:I,TRANSACCIONES!C:C,"EGRESO",TRANSACCIONES!D:D,A13,TRANSACCIONES!P:P,"Personal",TRANSACCIONES!L:L,"PAGADO")) | D13: =B13+C13 | E13: =IF(D13=0,0,C13/D13)
A14: Administrativo | B14: =ABS(SUMIFS(TRANSACCIONES!I:I,TRANSACCIONES!C:C,"EGRESO",TRANSACCIONES!D:D,A14,TRANSACCIONES!P:P,"Negocio",TRANSACCIONES!L:L,"PAGADO")) | C14: =ABS(SUMIFS(TRANSACCIONES!I:I,TRANSACCIONES!C:C,"EGRESO",TRANSACCIONES!D:D,A14,TRANSACCIONES!P:P,"Personal",TRANSACCIONES!L:L,"PAGADO")) | D14: =B14+C14 | E14: =IF(D14=0,0,C14/D14)
A15: Ventas | B15: =ABS(SUMIFS(TRANSACCIONES!I:I,TRANSACCIONES!C:C,"EGRESO",TRANSACCIONES!D:D,A15,TRANSACCIONES!P:P,"Negocio",TRANSACCIONES!L:L,"PAGADO")) | C15: =ABS(SUMIFS(TRANSACCIONES!I:I,TRANSACCIONES!C:C,"EGRESO",TRANSACCIONES!D:D,A15,TRANSACCIONES!P:P,"Personal",TRANSACCIONES!L:L,"PAGADO")) | D15: =B15+C15 | E15: =IF(D15=0,0,C15/D15)
A16: Otros | B16: =ABS(SUMIFS(TRANSACCIONES!I:I,TRANSACCIONES!C:C,"EGRESO",TRANSACCIONES!D:D,A16,TRANSACCIONES!P:P,"Negocio",TRANSACCIONES!L:L,"PAGADO")) | C16: =ABS(SUMIFS(TRANSACCIONES!I:I,TRANSACCIONES!C:C,"EGRESO",TRANSACCIONES!D:D,A16,TRANSACCIONES!P:P,"Personal",TRANSACCIONES!L:L,"PAGADO")) | D16: =B16+C16 | E16: =IF(D16=0,0,C16/D16)
A18: ⚠️ ALERTAS Y RECOMENDACIONES
A19: Alerta | C19: Valor | D19: Estado
A20: Porcentaje de gastos personales | C20: =E7 | D20: =IF(C20>0.5,"🔴 MUY ALTO - Reducir gastos personales",IF(C20>0.3,"⚠️ MODERADO - Revisar clasificación","✅ OK - Bien separado"))
A21: Balance personal (debe ser positivo) | C21: =D7 | D21: =IF(C21<0,"🔴 NEGATIVO - Gastos personales exceden ingresos","✅ OK - Balance positivo")
A23: 📋 INSTRUCCIONES PARA SANEAMIENTO
A24: ✅ Al ingresar transacciones en TRANSACCIONES, marca en columna P si es "Personal" o "Negocio"
A25: 💡 Gastos de Álvaro (comida, transporte personal, etc.) = Personal
A26: 💡 Gastos del negocio (nómina, proveedores, servicios) = Negocio
A27: ⚠️ NUNCA mezcles fondos - separa claramente las cuentas
A28: 📊 Revisa este reporte mensualmente para verificar que la separación sea correcta
A29: 🎯 META: Lograr que gastos personales sean < 30% del total
